Workbook

Sheet 01_Raw
A1: ID | B1: Customer_Name | C1: Order_ID | D1: Order_Date | E1: Product | F1: Category | G1: Quantity | H1: Price | I1: Payment_Method | J1: Status | K1: Total
A2: 100 | B2: Customer_100 | C2: ORD-41285 | D2: 11/22/2024 | E2: Blender | F2: Home | G2: 3 | H2: 38 | I2: Cash on Delivery | J2: Shipped | K2: 114
A3: 101 | B3: Customer_101 | C3: ORD-35783 | D3: 7/5/2025 | E3: Smartphone | F3: Electronics | G3: 2 | H3: abd | I3: PayPal | J3: Processing
A4: 102 | B4: Customer_102 | C4: ORD-84355 | D4: 12/23/2024 | E4: Tennis Racket | F4: Sports | G4: 1 | H4: 389.05 | I4: PayPal | J4: Delivered | K4: 389.05
A5: 103 | B5: Customer_103 | C5: ORD-57811 | D5: 3/19/2025 | E5: Science | F5: Books | G5: 5 | H5: 233.92 | I5: PayPal | J5: Processing | K5: 1169.6
A6: 104 | B6: Customer_104 | C6: ORD-93614 | D6: 10/20/2025 | E6: Biography | F6: Books | G6: 1 | H6: 552.51 | I6: Cash on Delivery | J6: Processing | K6: 552.51
A7: 105 | B7: Customer_105 | C7: ORD-22442 | D7: 11/20/2024 | E7: Tennis Racket | F7: Sports | G7: 3 | H7: 122.06 | I7: Cash on Delivery | J7: Cancelled | K7: 366.18
A8: 106 | B8: Customer_106 | C8: ORD-25885 | D8: 2/2/2025 | E8: Blender | F8: Home | H8: 978.63 | I8: Bank Transfer | J8: Processing
A9: 107 | B9: Customer_107 | C9: ORD-89122 | D9: 1/3/2025 | E9: Biography | F9: Books | G9: 5 | H9: 587.68 | I9: PayPal | J9: Returned | K9: 2938.4
A10: 108 | B10: Customer_108 | C10: ORD-64400 | D10: 10/23/2025 | E10: Science | F10: Books | G10: 1 | H10: 600.29 | I10: Cash on Delivery | J10: Processing | K10: 600.29
A11: 109 | B11: Customer_109 | C11: ORD-18512 | D11: 5/3/2025 | E11: Tennis Racket | F11: Sports | G11: 5 | H11: 168.34 | I11: Credit Card | J11: Shipped | K11: 841.7
A12: 110 | B12: Customer_110 | C12: ORD-61020 | D12: 9/26/2025 | E12: Basketball | F12: sports | G12: 5 | H12: four hundred | I12: Cash on Delivery | J12: Cancelled
A13: 111 | B13: Customer_111 | C13: ORD-72349 | D13: 10/22/2025 | E13: Comics | F13: Books | G13: 2 | H13: 865.77 | I13: Credit Card | J13: Returned | K13: 1731.54
A14: 112 | B14: Customer_112 | C14: ORD-80867 | D14: 3/2/2025 | E14: Shoes | F14: Clothing | G14: 4 | H14: 752.13 | I14: Bank Transfer | J14: Delivered | K14: 3008.52
A15: 113 | B15: Customer_113 | C15: ORD-23994 | D15: 7/24/2025 | E15: Fiction | F15: Books | G15: 1 | H15: 411.81 | I15: Credit Card | J15: Processing | K15: 411.81
A16: 114 | B16: Customer_114 | C16: ORD-77417 | D16: Jan 5 2023 | E16: Smartphone | F16: Electronics | G16: 2 | H16: 413.13 | I16: Cash on Delivery | J16: Shipped | K16: 826.26
A17: 115 | B17: Customer_115 | C17: ORD-72778 | D17: 1/10/2025 | E17: Fiction | F17: Books | G17: 2 | H17: 796.84 | I17: Cash on Delivery | J17: Returned | K17: 1115.576
A18: 116 | B18: Customer_116 | C18: ORD-63660 | D18: 10/30/2025 | E18: Microwave | F18: Home | G18: 4 | I18: Cash on Delivery | J18: Processing
A19: 117 | B19: Customer_117 | C19: ORD-72751 | D19: 2/12/2025 | E19: Blender | F19: electronic | G19: -2 | H19: 10000 | I19: Cash on Delivery | J19: Processing | K19: -20000
A20: 118 | B20: Customer_118 | C20: ORD-96061 | D20: 5/31/2025 | E20: Science | F20: Books | G20: 5 | H20: 247.82 | I20: PayPal | J20: Processing | K20: 1239.1
A21: 119 | B21: Customer_119 | C21: ORD-76016 | D21: 12/19/2024 | E21: Basketball | F21: Sports | G21: 4 | H21: 438.19 | I21: Cash on Delivery | J21: Processing | K21: 1752.76
A22: 120 | B22: Customer_120 | C22: ORD-14659 | D22: 6/13/2025 | E22: Yoga Mat | F22: ELECTRONICS | G22: 5 | H22: 300$ | I22: Credit Card | J22: Cancelled
A23: 121 | B23: Customer_121 | C23: ORD-80067 | D23: 10/11/2025 | E23: Basketball | F23: Sports | G23: 4 | H23: 523.01 | I23: Credit Card | J23: Delivered | K23: 2092.04
A24: 122 | B24: Customer_122 | C24: ORD-21443 | D24: 5/16/2025 | E24: Microwave | F24: Home | G24: 2 | H24: 556.93 | I24: PayPal | J24: Shipped | K24: 1113.86
A25: 123 | B25: Customer_123 | C25: ORD-11314 | D25: 10/6/2025 | E25: Vacuum | F25: electronic | G25: 3 | H25: 615.91 | I25: Cash on Delivery | J25: Cancelled | K25: 1847.73
A26: 124 | B26: Customer_124 | C26: ORD-46136 | D26: 5/31/2025 | E26: Comics | F26: Books | G26: 5 | I26: PayPal | J26: Cancelled
A27: 125 | B27: Customer_125 | C27: ORD-23202 | D27: 2/9/2025 | E27: Comics | F27: Books | G27: 4 | H27: 765.69 | I27: PayPal | J27: Shipped | K27: 3062.76
A28: 126 | B28: Customer_126 | C28: ORD-11261 | D28: 5/18/2025 | E28: Shoes | F28: Clothing | G28: 4 | H28: 836.8 | I28: Bank Transfer | J28: Cancelled | K28: 3347.2
A29: 127 | B29: Customer_127 | C29: ORD-65482 | D29: 5/12/2025 | E29: Blender | F29: Home | G29: 5 | H29: 336.02 | I29: Bank Transfer | J29: Returned | K29: 1680.1
A30: 128 | B30: Customer_128 | C30: ORD-12270 | D30: 11/10/2024 | E30: Lamp | F30: electronics | G30: 3 | H30: 898.69 | I30: Bank Transfer | J30: Delivered | K30: 2696.07
A31: 129 | B31: Customer_129 | C31: ORD-48863 | D31: 6/22/2025 | E31: Science | F31: Books | G31: 4 | H31: 736.71 | I31: Bank Transfer | J31: Returned | K31: 2946.84
A32: 130 | B32: Customer_130 | C32: ORD-34007 | D32: 8/15/2025 | E32: Tennis Racket | F32: Sports | G32: 2 | I32: Bank Transfer | J32: Processing
A33: 131 | B33: Customer_131 | C33: ORD-91396 | D33: 6/11/2025 | E33: Lamp | F33: Home | G33: 5 | H33: 616.63 | I33: PayPal | J33: Shipped | K33: 3083.15
A34: 132 | B34: Customer_132 | C34: ORD-40186 | D34: 4/2/2025 | E34: Yoga Mat | F34: ELECTRONICS | G34: 1 | H34: 266.7 | I34: PayPal | J34: Delivered | K34: 266.7
A35: 133 | B35: Customer_133 | C35: ORD-68182 | D35: 12/5/2024 | E35: Biography | F35: nan | G35: 5 | H35: 343.24 | I35: Credit Card | J35: Shipped | K35: 1716.2
A36: 134 | B36: Customer_134 | C36: ORD-16585 | D36: 10/4/2025 | E36: T-shirt | F36: Clothing | G36: -5 | H36: 591.53 | I36: PayPal | J36: Shipped | K36: -2957.65
A37: 135 | B37: Customer_135 | C37: ORD-33656 | D37: 2/9/2025 | E37: Smartwatch | F37: electronics | G37: 4 | H37: 446.19 | I37: Cash on Delivery | J37: Cancelled | K37: 1784.76
A38: 136 | B38: Customer_136 | C38: ORD-20985 | D38: 6/12/2025 | E38: Headphones | G38: 1 | H38: 696.71 | I38: Credit Card | J38: Delivered | K38: 696.71
A39: 137 | B39: Customer_137 | C39: ORD-91254 | D39: 2/23/2025 | E39: Vacuum | F39: Home | G39: 3 | H39: -100 | I39: Cash on Delivery | J39: Delivered | K39: -300
A40: 138 | B40: Customer_138 | C40: ORD-34319 | D40: 8/9/2025 | E40: Lamp | F40: Home | G40: 1 | H40: 531.06 | I40: PayPal | J40: Processing | K40: 531.06
A41: 139 | B41: Customer_139 | C41: ORD-38418 | D41: 2/9/2025 | E41: Smartphone | F41: Electronics | G41: 2 | H41: 681.38 | I41: Credit Card | J41: Cancelled | K41: 1362.76
A42: 140 | B42: Customer_140 | C42: ORD-67096 | D42: 2/26/2025 | E42: Fiction | F42: Books | G42: 4 | H42: 588.98 | I42: Credit Card | J42: Returned | K42: 2355.92
A43: 141 | B43: Customer_141 | C43: ORD-45059 | D43: 2/13/2025 | E43: Fiction | F43: Books | G43: 3 | H43: 546.04 | I43: Cash on Delivery | J43: Returned | K43: 1638.12
A44: 142 | B44: Customer_142 | C44: ORD-69018 | D44: 10/30/2025 | E44: Shoes | F44: Clothing | G44: 5 | H44: 645.26 | I44: Credit Card | J44: Shipped | K44: 2258.41 | N44: =5*645.26 -> 3226.3
A45: 143 | B45: Customer_143 | C45: ORD-14329 | D45: 7/11/2025 | E45: T-shirt | F45: Clothing | G45: 5 | H45: 826.77 | I45: Bank Transfer | J45: Cancelled | K45: 4133.85
A46: 144 | B46: Customer_144 | C46: ORD-89452 | D46: 1/27/2025 | E46: Football | F46: Sports | G46: 5 | H46: 849.07 | I46: Bank Transfer | J46: Processing | K46: 4245.35
A47: 145 | B47: Customer_145 | C47: ORD-75314 | D47: 5/1/2023 | E47: Laptop | F47: Electronics | G47: 2 | H47: 860.99 | I47: Bank Transfer | J47: Returned | K47: 1721.98
A48: 146 | B48: Customer_146 | C48: ORD-32755 | D48: 7/9/2025 | E48: Basketball | F48: electronic | G48: 2 | H48: 705.42 | I48: Bank Transfer | J48: Processing | K48: 1410.84
A49: 147 | B49: Customer_147 | C49: ORD-80707 | D49: 5/1/2025 | E49: Jacket | F49: Clothing | G49: 4 | H49: 596.15 | I49: Cash on Delivery | J49: Shipped | K49: 2384.6
A50: 148 | B50: Customer_148 | C50: ORD-38423 | D50: 3/13/2025 | E50: Tennis Racket | F50: Sports | G50: 1 | H50: 660.98 | I50: Cash on Delivery | J50: Returned | K50: 660.98
A51: 149 | B51: Customer_149 | C51: ORD-95911 | D51: 6/29/2025 | E51: Comics | F51: Books | G51: 5 | H51: 896.38 | I51: Bank Transfer | J51: Cancelled | K51: 4481.9
A52: 150 | B52: Customer_150 | C52: ORD-76902 | D52: 11/27/2024 | E52: Yoga Mat | F52: Sports | G52: 1 | H52: 206.19 | I52: Credit Card | J52: Returned | K52: 206.19
A53: 151 | B53: Customer_151 | C53: ORD-56552 | D53: 7/1/2025 | E53: Comics | F53: Books | G53: 2 | H53: 457.16 | I53: PayPal | J53: Processing | K53: 640.024
A54: 152 | B54: Customer_152 | C54: ORD-72869 | D54: 9/22/2025 | E54: Lamp | F54: Home | G54: 3 | H54: 233.11 | I54: PayPal | J54: Returned | K54: 699.33
A55: 153 | B55: Customer_153 | C55: ORD-29721 | D55: 7/16/2025 | E55: Yoga Mat | F55: Sports | G55: 4 | H55: 278.9 | I55: Cash on Delivery | J55: Processing | K55: 1115.6
A56: 154 | B56: Customer_154 | C56: ORD-95990 | D56: 2/21/2025 | E56: Blender | F56: Home | G56: 5 | H56: 789.64 | I56: Cash on Delivery | J56: Cancelled | K56: 3948.2
A57: 155 | B57: Customer_155 | C57: ORD-20182 | D57: 5/1/2025 | E57: shoes | F57: Clothing | G57: 1 | H57: 40.95 | I57: PayPal | J57: Returned | K57: 40.95
A58: 156 | B58: Customer_156 | C58: ORD-34679 | D58: 11/28/2024 | E58: Jeans | F58: Clothing | G58: 2 | I58: Bank Transfer | J58: Shipped
A59: 157 | B59: Customer_157 | C59: ORD-34407 | D59: 11/6/2025 | E59: Jacket | F59: Clothing | G59: 4 | H59: 275.1 | I59: Bank Transfer | J59: Processing | K59: 1100.4
A60: 158 | B60: Customer_158 | C60: ORD-35817 | D60: 4/5/2025 | E60: Smartwatch | F60: Electronics | G60: 1 | H60: 933.58 | I60: Cash on Delivery | J60: Shipped | K60: 933.58
A61: 159 | B61: Customer_159 | C61: ORD-98162 | D61: 7/28/2025 | E61: Microwave | F61: Home | G61: 3 | H61: 163.16 | I61: PayPal | J61: Shipped | K61: 489.48
A62: 160 | B62: Customer_160 | C62: ORD-96037 | D62: 1/3/2025 | E62: Science | F62: Books | G62: 5 | H62: 242.52 | I62: Cash on Delivery | J62: Returned | K62: 1212.6
A63: 161 | B63: Customer_161 | C63: ORD-27653 | D63: 12/15/2024 | E63: Science | F63: Books | G63: 4 | H63: 209.32 | I63: Bank Transfer | J63: Shipped | K63: 837.28
A64: 162 | B64: Customer_162 | C64: ORD-27743 | D64: 5/19/2025 | E64: Blender | F64: Home | G64: 2 | H64: 155.76 | I64: Credit Card | J64: Returned | K64: 311.52
A65: 163 | B65: Customer_163 | C65: ORD-24378 | D65: 1/5/2023 | E65: Smartwatch | F65: Electronics | G65: 3 | H65: 235.26 | I65: Cash on Delivery | J65: Shipped | K65: 705.78
A66: 164 | B66: Customer_164 | C66: ORD-23010 | D66: 2/9/2025 | E66: Tennis Racket | F66: Sports | H66: 587.64 | I66: Credit Card | J66: Returned
A67: 165 | B67: Customer_165 | C67: ORD-55695 | D67: 11/8/2024 | E67: Shoes | F67: Clothing | G67: 2 | H67: 443.13 | I67: Credit Card | J67: Delivered | K67: 886.26
A68: 166 | B68: Customer_166 | C68: ORD-97756 | D68: 7/3/2025 | E68: T-shirt | F68: electronics | G68: 2 | H68: 569.38 | I68: Cash on Delivery | J68: Shipped | K68: 1138.76
A69: 167 | B69: Customer_167 | C69: ORD-30329 | D69: 8/7/2025 | E69: Basketball | F69: Sports | H69: 593.93 | I69: Cash on Delivery | J69: Processing
A70: 168 | B70: Customer_168 | C70: ORD-53430 | D70: 11/4/2025 | E70: Biography | F70: Books | G70: 2 | H70: 141.49 | I70: PayPal | J70: Cancelled | K70: 282.98
A71: 169 | B71: Customer_169 | C71: ORD-75539 | D71: 8/12/2025 | E71: Basketball | F71: Sports | G71: 1 | H71: 582.13 | I71: Credit Card | J71: Returned | K71: 582.13
A72: 170 | B72: Customer_170 | C72: ORD-21530 | D72: 10/3/2025 | E72: Jeans | F72: Clothing | G72: 5 | H72: 741.63 | I72: Bank Transfer | J72: Processing | K72: 3708.15
A73: 171 | B73: Customer_171 | C73: ORD-99790 | D73: 12/6/2024 | E73: Shoes | F73: Clothing | G73: 3 | H73: 688.68 | I73: PayPal | J73: Processing | K73: 2066.04
A74: 172 | B74: Customer_172 | C74: ORD-48008 | D74: 11/18/2024 | E74: Comics | F74: Books | G74: 2 | H74: 942.76 | I74: Bank Transfer | J74: Returned | K74: 1885.52
A75: 173 | B75: Customer_173 | C75: ORD-42171 | D75: 10/11/2025 | E75: Lamp | F75: Home | G75: 5 | H75: 351.89 | I75: Credit Card | J75: Shipped | K75: 1759.45
A76: 174 | B76: Customer_174 | C76: ORD-16766 | D76: 9/20/2025 | E76: Microwave | F76: ELECTRONICS | G76: 4 | H76: 187.48 | I76: Credit Card | J76: Returned | K76: 749.92
A77: 175 | B77: Customer_175 | C77: ORD-56651 | D77: 2/24/2025 | E77: Headphones | F77: Electronics | G77: 1 | H77: 111.36 | I77: Credit Card | J77: Processing | K77: 111.36
A78: 176 | B78: Customer_176 | C78: ORD-95794 | D78: 7/22/2025 | E78: Comics | F78: Books | G78: 5 | H78: 530.52 | I78: Cash on Delivery | J78: Shipped | K78: 2652.6
A79: 177 | B79: Customer_177 | C79: ORD-64136 | D79: 7/28/2025 | E79: Laptop | F79: Electronics | G79: 1 | H79: 69.48 | I79: Bank Transfer | J79: Returned | K79: 69.48
A80: 178 | B80: Customer_178 | C80: ORD-89906 | D80: 9/18/2025 | E80: Tennis Racket | F80: Sports | G80: 3 | H80: 472.14 | I80: PayPal | J80: Returned | K80: 1416.42
A81: 179 | B81: Customer_179 | C81: ORD-99328 | D81: 9/3/2025 | E81: Yoga Mat | F81: Sports | G81: 3 | H81: 868.67 | I81: PayPal | J81: Delivered | K81: 2606.01
A82: 180 | B82: Customer_180 | C82: ORD-86629 | D82: 3/26/2025 | E82: Laptop | G82: 2 | H82: 418.38 | I82: Credit Card | J82: Processing | K82: 836.76
A83: 181 | B83: Customer_181 | C83: ORD-54481 | D83: 12/29/2024 | E83: Smartphone | F83: nan | G83: 1 | H83: 266.48 | I83: Cash on Delivery | J83: Cancelled | K83: 266.48
A84: 182 | B84: Customer_182 | C84: ORD-79672 | D84: 8/3/2025 | E84: Shoes | G84: 4 | H84: 538.35 | I84: PayPal | J84: Processing | K84: 2153.4
A85: 183 | B85: Customer_183 | C85: ORD-20916 | D85: 3/10/2025 | E85: Shoes | F85: Clothing | G85: 5 | I85: Cash on Delivery | J85: Returned
A86: 184 | B86: Customer_184 | C86: ORD-67799 | D86: 2/15/2025 | E86: Jeans | G86: 4 | H86: 101.19 | I86: Bank Transfer | J86: Processing | K86: 404.76
A87: 185 | B87: Customer_185 | C87: ORD-57123 | D87: 8/14/2025 | E87: Football | F87: Sports | G87: 2 | H87: 730.92 | I87: Cash on Delivery | J87: Cancelled | K87: 1023.288
A88: 186 | B88: Customer_186 | C88: ORD-90569 | D88: 10/6/2025 | E88: Laptop | F88: Electronics | G88: 1 | H88: 365.34 | I88: Bank Transfer | J88: Delivered | K88: 365.34
A89: 187 | B89: Customer_187 | C89: ORD-41292 | D89: 11/19/2024 | E89: Smartphone | F89: Electronics | G89: 3 | H89: 882.96 | I89: Bank Transfer | J89: Returned | K89: 2648.88
A90: 188 | B90: Customer_188 | C90: ORD-58590 | D90: 11/19/2024 | E90: Microwave | F90: Home | G90: 5 | H90: 504.05 | I90: Cash on Delivery | J90: Shipped | K90: 2520.25
A91: 189 | B91: Customer_189 | C91: ORD-30627 | D91: 8/14/2025 | E91: Lamp | F91: Home | G91: 1 | H91: 814.68 | I91: Cash on Delivery | J91: Returned | K91: 814.68
A92: 190 | B92: Customer_190 | C92: ORD-38469 | D92: 6/29/2025 | E92: Vacuum | F92: Home | G92: 1 | H92: 920.37 | I92: Bank Transfer | J92: Processing | K92: 920.37
A93: 191 | B93: Customer_191 | C93: ORD-41810 | D93: 7/18/2025 | E93: Fiction | F93: Books | G93: 2 | H93: 881.02 | I93: Cash on Delivery | J93: Returned | K93: 1762.04
A94: 192 | B94: Customer_192 | C94: ORD-35144 | D94: abc | E94: Jacket | F94: Clothing | G94: 4a | H94: 203.63 | I94: Credit Card | J94: Returned
A95: 193 | B95: Customer_193 | C95: ORD-42475 | D95: 6/6/2025 | E95: Basketball | H95: 522.02 | I95: PayPal | J95: Shipped
A96: 194 | B96: Customer_194 | C96: ORD-69764 | D96: 2/10/2025 | E96: Lamp | F96: Home | G96: 5 | H96: 944.54 | I96: Cash on Delivery | J96: Returned | K96: 4722.7
A97: 195 | B97: Customer_195 | C97: ORD-82876 | D97: 6/19/2025 | E97: Biography | F97: Books | G97: 5 | H97: 817.46 | I97: Cash on Delivery | J97: Returned | K97: 4087.3
A98: 196 | B98: Customer_196 | C98: ORD-78384 | D98: 12/23/2024 | E98: Vacuum | F98: Home | H98: abd | I98: PayPal | J98: Delivered
A99: 197 | B99: Customer_197 | C99: ORD-79139 | D99: 6/23/2025 | E99: Blender | F99: Home | G99: 1 | H99: 160.16 | I99: PayPal | J99: Cancelled | K99: 160.16
A100: 198 | B100: Customer_198 | C100: ORD-14608 | D100: 7/27/2025 | E100: Vacuum | G100: 2 | H100: 497.01 | I100: Cash on Delivery | J100: Shipped | K100: 994.02
...

Sheet 02_Audit
A1: Issue | B1: Column(s) | C1: Records Affected | D1: Decision
A2: Leading spaces in headers | B2: Customer_Name, Category | C2: 2 columns | D2: Renamed manually to clean headers
A3: Inconsistent text casing | B3: Category | C3: 9 distinct values | D3: Standardized with TRIM + PROPER → 5 valid categories
A4: Misspelled category ("electronic") | B4: Category | C4: - | D4: Corrected to "Electronics" via IF
A5: Nulls stored as literal "nan" | B5: Category | C5: 2 | D5: Flagged as "Missing" (source export artifact)
A6: Empty strings vs true blanks | B6: Price, Quantity, Category, Total | C6: - | D6: Detected with LEN(TRIM())=0; ISBLANK failed to catch them
A7: Missing Values | B7: Category 8 · Quantity 5 · Price 5 · Total 14 | C7: 32 | D7: Labeled "Missing", not deleted
A8: Non-numeric values | B8: Price ("abd" ×2, "four hundred"), Quantity ("4a") | C8: 4 | D8: Flagged "Invalid" — not guessed
A9: Currency symbol in value | B9: Price ("300$") | C9: 1 | D9: Removed with SUBSTITUTE → 300
A10: US decimal notation (period) | B10: Price, Total | C10: all | D10: Converted to regional separator before VALUE
A11: Inconsistent date formats | B11: Order_Date | C11: 2 | D11: "Jan 5 2023" corrected manually; "abc" flagged Invalid
A12: Regional date misparse risk | B12: Order_Date | C12: all | D12: Excel read M/D as D/M causing silent errors; parsed explicitly with FIND/LEFT/MID/RIGHT + DATE, standardized to ISO YYYY-MM-DD
A13: Exact duplicate row | B13: All | C13: 1 (ID 146) | D13: Removed one copy
A14: Duplicate IDs with differing data | B14: ID, Order_ID | C14: 2 (IDs 142, 175) | D14: Validated against Quantity × Price; kept the correct record — an automated "remove duplicates" would have retained corrupted data
A15: Negative values | B15: Quantity (-2, -5), Price (-100) | C15: 3 | D15: Logically impossible but technically valid; flagged for client review, not altered
A16: Outlier price (10,000) | B16: Price | C16: 1 | D16: Flagged for review (10-20× typical range)
A17: Total ≠ Quantity × Price | B17: Total | C17: 3 (IDs 115, 151, 185) | D17: Exactly 70% of calculated value — consistent pattern suggesting an unrecorded discount; flagged, not overwritten
A18: Recoverable Total | B18: Total | C18: 1 | D18: Recalculated from Quantity × Price where inputs were clean

Sheet 99_Reference_Formulas
A1: ID | B1: Customer_Name | C1: Order_ID | D1: Order_Date | E1: Product | F1: Category | G1: Quantity | H1: Price | I1: Payment_Method | J1: Status | K1: Total | N1: =ISNUMBER('01_Raw'!D2) -> FALSE | P1: =LEFT('01_Raw'!D2, FIND("/",'01_Raw'!D2) - 1) -> 11 | Q1: =IFERROR(RIGHT('01_Raw'!D2,4),"Invalid") -> 2024 | R1: =MID('01_Raw'!D2,FIND("/",'01_Raw'!D2) + 1,FIND("/",'01_Raw'!D2,FIND("/",'01_Raw'!D2)+1)-FIND("/",'01_Raw'!D2)-1) -> 22 | S1: =IFERROR(DATE(Q1,P1,R1),"Invalid") -> 45618 | U1: =IFERROR(VALUE(SUBSTITUTE(SUBSTITUTE('01_Raw'!H2,"$",""), ".",",")),"Invalid") -> 38 | V1: =IFERROR(VALUE('01_Raw'!G2), "Invalid") -> 3 | X1: =IF(ISBLANK('01_Raw'!H2),"Missing", IFERROR(VALUE(SUBSTITUTE(SUBSTITUTE('01_Raw'!H2,"$",""), ".",",")),"Invalid")) -> 38 | Y1: =IF(LEN(TRIM('01_Raw'!H2)) = 0, "Missing",IFERROR(VALUE(SUBSTITUTE(SUBSTITUTE('01_Raw'!H2,"$",""), ".",",")),"Invalid")) -> 38 | AA1: =IF(LEN(TRIM('01_Raw'!G2)) = 0, "Missing",IFERROR(VALUE(SUBSTITUTE(SUBSTITUTE('01_Raw'!G2,"$",""), ".",",")),"Invalid")) -> 3 | AC1: =COUNTIF($A$2:$A$103,A2) -> 1 | AE1: =COUNTIF(messy_ecommerce_sales_data__2[Order_ID],'01_Raw'!C2) -> 1 | AG1: =IFERROR(AA1*Y1,"Cannot Calculate") -> 114 | AH1: =IF(AG1='01_Raw'!K2,"OK","Mismatch") -> Mismatch | AJ1: =IF(LEN(TRIM(AG1)) = 0, "Missing",IFERROR(VALUE(SUBSTITUTE(SUBSTITUTE(AG1,"$",""), ".",",")),"Invalid")) -> 114 | AK1: =IF(AJ1=AG1,"OK","Mismatch") -> OK
A2: ='01_Raw'!A2 -> 100 | B2: =TRIM('01_Raw'!B2) -> Customer_100 | D2: =IFERROR(DATE(Q1,P1,R1),"Invalid") -> 45618 | E2: =TRIM('01_Raw'!E2) -> Blender | F2: =IF(PROPER(TRIM('01_Raw'!F2))="Electronic","Electronics",PROPER(TRIM('01_Raw'!F2))) -> Home | I2: =TRIM('01_Raw'!I2) -> Cash on Delivery | J2: =TRIM('01_Raw'!J2) -> Shipped | N2: =ISNUMBER('01_Raw'!D3) -> FALSE | P2: =LEFT('01_Raw'!D3, FIND("/",'01_Raw'!D3) - 1) -> 7 | Q2: =IFERROR(RIGHT('01_Raw'!D3,4),"Invalid") -> 2025 | R2: =MID('01_Raw'!D3,FIND("/",'01_Raw'!D3) + 1,FIND("/",'01_Raw'!D3,FIND("/",'01_Raw'!D3)+1)-FIND("/",'01_Raw'!D3)-1) -> 5 | S2: =IFERROR(DATE(Q2,P2,R2),"Invalid") -> 45843 | U2: =IFERROR(VALUE(SUBSTITUTE(SUBSTITUTE('01_Raw'!H3,"$",""), ".",",")),"Invalid") -> Invalid | V2: =IFERROR(VALUE('01_Raw'!G3), "Invalid") -> 2 | X2: =IF(ISBLANK('01_Raw'!H3),"Missing", IFERROR(VALUE(SUBSTITUTE(SUBSTITUTE('01_Raw'!H3,"$",""), ".",",")),"Invalid")) -> Invalid | Y2: =IF(LEN(TRIM('01_Raw'!H3)) = 0, "Missing",IFERROR(VALUE(SUBSTITUTE(SUBSTITUTE('01_Raw'!H3,"$",""), ".",",")),"Invalid")) -> Invalid | AA2: =IF(LEN(TRIM('01_Raw'!G3)) = 0, "Missing",IFERROR(VALUE(SUBSTITUTE(SUBSTITUTE('01_Raw'!G3,"$",""), ".",",")),"Invalid")) -> 2 | AC2: =COUNTIF($A$2:$A$103,A3) -> 1 | AE2: =COUNTIF(messy_ecommerce_sales_data__2[Order_ID],'01_Raw'!C3) -> 1 | AG2: =IFERROR(AA2*Y2,"Cannot Calculate") -> Cannot Calculate | AH2: =IF(AG2='01_Raw'!K3,"OK","Mismatch") -> Mismatch | AJ2: =IF(LEN(TRIM(AG2)) = 0, "Missing",IFERROR(VALUE(SUBSTITUTE(SUBSTITUTE(AG2,"$",""), ".",",")),"Invalid")) -> Invalid | AK2: =IF(AJ2=AG2,"OK","Mismatch") -> Mismatch
A3: ='01_Raw'!A3 -> 101 | B3: =TRIM('01_Raw'!B3) -> Customer_101 | D3: =IFERROR(DATE(Q2,P2,R2),"Invalid") -> 45843 | E3: =TRIM('01_Raw'!E3) -> Smartphone | F3: =IF(PROPER(TRIM('01_Raw'!F3))="Electronic","Electronics",PROPER(TRIM('01_Raw'!F3))) -> Electronics | I3: =TRIM('01_Raw'!I3) -> PayPal | J3: =TRIM('01_Raw'!J3) -> Processing | N3: =ISNUMBER('01_Raw'!D4) -> FALSE | P3: =LEFT('01_Raw'!D4, FIND("/",'01_Raw'!D4) - 1) -> 12 | Q3: =IFERROR(RIGHT('01_Raw'!D4,4),"Invalid") -> 2024 | R3: =MID('01_Raw'!D4,FIND("/",'01_Raw'!D4) + 1,FIND("/",'01_Raw'!D4,FIND("/",'01_Raw'!D4)+1)-FIND("/",'01_Raw'!D4)-1) -> 23 | S3: =IFERROR(DATE(Q3,P3,R3),"Invalid") -> 45649 | U3: =IFERROR(VALUE(SUBSTITUTE(SUBSTITUTE('01_Raw'!H4,"$",""), ".",",")),"Invalid") -> 389.05 | V3: =IFERROR(VALUE('01_Raw'!G4), "Invalid") -> 1 | X3: =IF(ISBLANK('01_Raw'!H4),"Missing", IFERROR(VALUE(SUBSTITUTE(SUBSTITUTE('01_Raw'!H4,"$",""), ".",",")),"Invalid")) -> 389.05 | Y3: =IF(LEN(TRIM('01_Raw'!H4)) = 0, "Missing",IFERROR(VALUE(SUBSTITUTE(SUBSTITUTE('01_Raw'!H4,"$",""), ".",",")),"Invalid")) -> 389.05 | AA3: =IF(LEN(TRIM('01_Raw'!G4)) = 0, "Missing",IFERROR(VALUE(SUBSTITUTE(SUBSTITUTE('01_Raw'!G4,"$",""), ".",",")),"Invalid")) -> 1 | AC3: =COUNTIF($A$2:$A$103,A4) -> 1 | AE3: =COUNTIF(messy_ecommerce_sales_data__2[Order_ID],'01_Raw'!C4) -> 1 | AG3: =IFERROR(AA3*Y3,"Cannot Calculate") -> 389.05 | AH3: =IF(AG3='01_Raw'!K4,"OK","Mismatch") -> Mismatch | AJ3: =IF(LEN(TRIM(AG3)) = 0, "Missing",IFERROR(VALUE(SUBSTITUTE(SUBSTITUTE(AG3,"$",""), ".",",")),"Invalid")) -> 389.05 | AK3: =IF(AJ3=AG3,"OK","Mismatch") -> OK
A4: ='01_Raw'!A4 -> 102 | B4: =TRIM('01_Raw'!B4) -> Customer_102 | D4: =IFERROR(DATE(Q3,P3,R3),"Invalid") -> 45649 | E4: =TRIM('01_Raw'!E4) -> Tennis Racket | F4: =IF(PROPER(TRIM('01_Raw'!F4))="Electronic","Electronics",PROPER(TRIM('01_Raw'!F4))) -> Sports | I4: =TRIM('01_Raw'!I4) -> PayPal | J4: =TRIM('01_Raw'!J4) -> Delivered | N4: =ISNUMBER('01_Raw'!D5) -> FALSE | P4: =LEFT('01_Raw'!D5, FIND("/",'01_Raw'!D5) - 1) -> 3 | Q4: =IFERROR(RIGHT('01_Raw'!D5,4),"Invalid") -> 2025 | R4: =MID('01_Raw'!D5,FIND("/",'01_Raw'!D5) + 1,FIND("/",'01_Raw'!D5,FIND("/",'01_Raw'!D5)+1)-FIND("/",'01_Raw'!D5)-1) -> 19 | S4: =IFERROR(DATE(Q4,P4,R4),"Invalid") -> 45735 | U4: =IFERROR(VALUE(SUBSTITUTE(SUBSTITUTE('01_Raw'!H5,"$",""), ".",",")),"Invalid") -> 233.92 | V4: =IFERROR(VALUE('01_Raw'!G5), "Invalid") -> 5 | X4: =IF(ISBLANK('01_Raw'!H5),"Missing", IFERROR(VALUE(SUBSTITUTE(SUBSTITUTE('01_Raw'!H5,"$",""), ".",",")),"Invalid")) -> 233.92 | Y4: =IF(LEN(TRIM('01_Raw'!H5)) = 0, "Missing",IFERROR(VALUE(SUBSTITUTE(SUBSTITUTE('01_Raw'!H5,"$",""), ".",",")),"Invalid")) -> 233.92 | AA4: =IF(LEN(TRIM('01_Raw'!G5)) = 0, "Missing",IFERROR(VALUE(SUBSTITUTE(SUBSTITUTE('01_Raw'!G5,"$",""), ".",",")),"Invalid")) -> 5 | AC4: =COUNTIF($A$2:$A$103,A5) -> 1 | AE4: =COUNTIF(messy_ecommerce_sales_data__2[Order_ID],'01_Raw'!C5) -> 1 | AG4: =IFERROR(AA4*Y4,"Cannot Calculate") -> 1169.6 | AH4: =IF(AG4='01_Raw'!K5,"OK","Mismatch") -> Mismatch | AJ4: =IF(LEN(TRIM(AG4)) = 0, "Missing",IFERROR(VALUE(SUBSTITUTE(SUBSTITUTE(AG4,"$",""), ".",",")),"Invalid")) -> 1169.6 | AK4: =IF(AJ4=AG4,"OK","Mismatch") -> OK
A5: ='01_Raw'!A5 -> 103 | B5: =TRIM('01_Raw'!B5) -> Customer_103 | D5: =IFERROR(DATE(Q4,P4,R4),"Invalid") -> 45735 | E5: =TRIM('01_Raw'!E5) -> Science | F5: =IF(PROPER(TRIM('01_Raw'!F5))="Electronic","Electronics",PROPER(TRIM('01_Raw'!F5))) -> Books | I5: =TRIM('01_Raw'!I5) -> PayPal | J5: =TRIM('01_Raw'!J5) -> Processing | N5: =ISNUMBER('01_Raw'!D6) -> FALSE | P5: =LEFT('01_Raw'!D6, FIND("/",'01_Raw'!D6) - 1) -> 10 | Q5: =IFERROR(RIGHT('01_Raw'!D6,4),"Invalid") -> 2025 | R5: =MID('01_Raw'!D6,FIND("/",'01_Raw'!D6) + 1,FIND("/",'01_Raw'!D6,FIND("/",'01_Raw'!D6)+1)-FIND("/",'01_Raw'!D6)-1) -> 20 | S5: =IFERROR(DATE(Q5,P5,R5),"Invalid") -> 45950 | U5: =IFERROR(VALUE(SUBSTITUTE(SUBSTITUTE('01_Raw'!H6,"$",""), ".",",")),"Invalid") -> 552.51 | V5: =IFERROR(VALUE('01_Raw'!G6), "Invalid") -> 1 | X5: =IF(ISBLANK('01_Raw'!H6),"Missing", IFERROR(VALUE(SUBSTITUTE(SUBSTITUTE('01_Raw'!H6,"$",""), ".",",")),"Invalid")) -> 552.51 | Y5: =IF(LEN(TRIM('01_Raw'!H6)) = 0, "Missing",IFERROR(VALUE(SUBSTITUTE(SUBSTITUTE('01_Raw'!H6,"$",""), ".",",")),"Invalid")) -> 552.51 | AA5: =IF(LEN(TRIM('01_Raw'!G6)) = 0, "Missing",IFERROR(VALUE(SUBSTITUTE(SUBSTITUTE('01_Raw'!G6,"$",""), ".",",")),"Invalid")) -> 1 | AC5: =COUNTIF($A$2:$A$103,A6) -> 1 | AE5: =COUNTIF(messy_ecommerce_sales_data__2[Order_ID],'01_Raw'!C6) -> 1 | AG5: =IFERROR(AA5*Y5,"Cannot Calculate") -> 552.51 | AH5: =IF(AG5='01_Raw'!K6,"OK","Mismatch") -> Mismatch | AJ5: =IF(LEN(TRIM(AG5)) = 0, "Missing",IFERROR(VALUE(SUBSTITUTE(SUBSTITUTE(AG5,"$",""), ".",",")),"Invalid")) -> 552.51 | AK5: =IF(AJ5=AG5,"OK","Mismatch") -> OK
A6: ='01_Raw'!A6 -> 104 | B6: =TRIM('01_Raw'!B6) -> Customer_104 | D6: =IFERROR(DATE(Q5,P5,R5),"Invalid") -> 45950 | E6: =TRIM('01_Raw'!E6) -> Biography | F6: =IF(PROPER(TRIM('01_Raw'!F6))="Electronic","Electronics",PROPER(TRIM('01_Raw'!F6))) -> Books | I6: =TRIM('01_Raw'!I6) -> Cash on Delivery | J6: =TRIM('01_Raw'!J6) -> Processing | N6: =ISNUMBER('01_Raw'!D7) -> FALSE | P6: =LEFT('01_Raw'!D7, FIND("/",'01_Raw'!D7) - 1) -> 11 | Q6: =IFERROR(RIGHT('01_Raw'!D7,4),"Invalid") -> 2024 | R6: =MID('01_Raw'!D7,FIND("/",'01_Raw'!D7) + 1,FIND("/",'01_Raw'!D7,FIND("/",'01_Raw'!D7)+1)-FIND("/",'01_Raw'!D7)-1) -> 20 | S6: =IFERROR(DATE(Q6,P6,R6),"Invalid") -> 45616 | U6: =IFERROR(VALUE(SUBSTITUTE(SUBSTITUTE('01_Raw'!H7,"$",""), ".",",")),"Invalid") -> 122.06 | V6: =IFERROR(VALUE('01_Raw'!G7), "Invalid") -> 3 | X6: =IF(ISBLANK('01_Raw'!H7),"Missing", IFERROR(VALUE(SUBSTITUTE(SUBSTITUTE('01_Raw'!H7,"$",""), ".",",")),"Invalid")) -> 122.06 | Y6: =IF(LEN(TRIM('01_Raw'!H7)) = 0, "Missing",IFERROR(VALUE(SUBSTITUTE(SUBSTITUTE('01_Raw'!H7,"$",""), ".",",")),"Invalid")) -> 122.06 | AA6: =IF(LEN(TRIM('01_Raw'!G7)) = 0, "Missing",IFERROR(VALUE(SUBSTITUTE(SUBSTITUTE('01_Raw'!G7,"$",""), ".",",")),"Invalid")) -> 3 | AC6: =COUNTIF($A$2:$A$103,A7) -> 1 | AE6: =COUNTIF(messy_ecommerce_sales_data__2[Order_ID],'01_Raw'!C7) -> 1 | AG6: =IFERROR(AA6*Y6,"Cannot Calculate") -> 366.18 | AH6: =IF(AG6='01_Raw'!K7,"OK","Mismatch") -> Mismatch | AJ6: =IF(LEN(TRIM(AG6)) = 0, "Missing",IFERROR(VALUE(SUBSTITUTE(SUBSTITUTE(AG6,"$",""), ".",",")),"Invalid")) -> 366.18 | AK6: =IF(AJ6=AG6,"OK","Mismatch") -> OK
A7: ='01_Raw'!A7 -> 105 | B7: =TRIM('01_Raw'!B7) -> Customer_105 | D7: =IFERROR(DATE(Q6,P6,R6),"Invalid") -> 45616 | E7: =TRIM('01_Raw'!E7) -> Tennis Racket | F7: =IF(PROPER(TRIM('01_Raw'!F7))="Electronic","Electronics",PROPER(TRIM('01_Raw'!F7))) -> Sports | I7: =TRIM('01_Raw'!I7) -> Cash on Delivery | J7: =TRIM('01_Raw'!J7) -> Cancelled | N7: =ISNUMBER('01_Raw'!D8) -> FALSE | P7: =LEFT('01_Raw'!D8, FIND("/",'01_Raw'!D8) - 1) -> 2 | Q7: =IFERROR(RIGHT('01_Raw'!D8,4),"Invalid") -> 2025 | R7: =MID('01_Raw'!D8,FIND("/",'01_Raw'!D8) + 1,FIND("/",'01_Raw'!D8,FIND("/",'01_Raw'!D8)+1)-FIND("/",'01_Raw'!D8)-1) -> 2 | S7: =IFERROR(DATE(Q7,P7,R7),"Invalid") -> 45690 | U7: =IFERROR(VALUE(SUBSTITUTE(SUBSTITUTE('01_Raw'!H8,"$",""), ".",",")),"Invalid") -> 978.63 | V7: =IFERROR(VALUE('01_Raw'!G8), "Invalid") -> Invalid | X7: =IF(ISBLANK('01_Raw'!H8),"Missing", IFERROR(VALUE(SUBSTITUTE(SUBSTITUTE('01_Raw'!H8,"$",""), ".",",")),"Invalid")) -> 978.63 | Y7: =IF(LEN(TRIM('01_Raw'!H8)) = 0, "Missing",IFERROR(VALUE(SUBSTITUTE(SUBSTITUTE('01_Raw'!H8,"$",""), ".",",")),"Invalid")) -> 978.63 | AA7: =IF(LEN(TRIM('01_Raw'!G8)) = 0, "Missing",IFERROR(VALUE(SUBSTITUTE(SUBSTITUTE('01_Raw'!G8,"$",""), ".",",")),"Invalid")) -> Missing | AC7: =COUNTIF($A$2:$A$103,A8) -> 1 | AE7: =COUNTIF(messy_ecommerce_sales_data__2[Order_ID],'01_Raw'!C8) -> 1 | AG7: =IFERROR(AA7*Y7,"Cannot Calculate") -> Cannot Calculate | AH7: =IF(AG7='01_Raw'!K8,"OK","Mismatch") -> Mismatch | AJ7: =IF(LEN(TRIM(AG7)) = 0, "Missing",IFERROR(VALUE(SUBSTITUTE(SUBSTITUTE(AG7,"$",""), ".",",")),"Invalid")) -> Invalid | AK7: =IF(AJ7=AG7,"OK","Mismatch") -> Mismatch
A8: ='01_Raw'!A8 -> 106 | B8: =TRIM('01_Raw'!B8) -> Customer_106 | D8: =IFERROR(DATE(Q7,P7,R7),"Invalid") -> 45690 | E8: =TRIM('01_Raw'!E8) -> Blender | F8: =IF(PROPER(TRIM('01_Raw'!F8))="Electronic","Electronics",PROPER(TRIM('01_Raw'!F8))) -> Home | I8: =TRIM('01_Raw'!I8) -> Bank Transfer | J8: =TRIM('01_Raw'!J8) -> Processing | N8: =ISNUMBER('01_Raw'!D9) -> FALSE | P8: =LEFT('01_Raw'!D9, FIND("/",'01_Raw'!D9) - 1) -> 1 | Q8: =IFERROR(RIGHT('01_Raw'!D9,4),"Invalid") -> 2025 | R8: =MID('01_Raw'!D9,FIND("/",'01_Raw'!D9) + 1,FIND("/",'01_Raw'!D9,FIND("/",'01_Raw'!D9)+1)-FIND("/",'01_Raw'!D9)-1) -> 3 | S8: =IFERROR(DATE(Q8,P8,R8),"Invalid") -> 45660 | U8: =IFERROR(VALUE(SUBSTITUTE(SUBSTITUTE('01_Raw'!H9,"$",""), ".",",")),"Invalid") -> 587.68 | V8: =IFERROR(VALUE('01_Raw'!G9), "Invalid") -> 5 | X8: =IF(ISBLANK('01_Raw'!H9),"Missing", IFERROR(VALUE(SUBSTITUTE(SUBSTITUTE('01_Raw'!H9,"$",""), ".",",")),"Invalid")) -> 587.68 | Y8: =IF(LEN(TRIM('01_Raw'!H9)) = 0, "Missing",IFERROR(VALUE(SUBSTITUTE(SUBSTITUTE('01_Raw'!H9,"$",""), ".",",")),"Invalid")) -> 587.68 | AA8: =IF(LEN(TRIM('01_Raw'!G9)) = 0, "Missing",IFERROR(VALUE(SUBSTITUTE(SUBSTITUTE('01_Raw'!G9,"$",""), ".",",")),"Invalid")) -> 5 | AC8: =COUNTIF($A$2:$A$103,A9) -> 1 | AE8: =COUNTIF(messy_ecommerce_sales_data__2[Order_ID],'01_Raw'!C9) -> 1 | AG8: =IFERROR(AA8*Y8,"Cannot Calculate") -> 2938.4 | AH8: =IF(AG8='01_Raw'!K9,"OK","Mismatch") -> Mismatch | AJ8: =IF(LEN(TRIM(AG8)) = 0, "Missing",IFERROR(VALUE(SUBSTITUTE(SUBSTITUTE(AG8,"$",""), ".",",")),"Invalid")) -> 2938.4 | AK8: =IF(AJ8=AG8,"OK","Mismatch") -> OK
A9: ='01_Raw'!A9 -> 107 | B9: =TRIM('01_Raw'!B9) -> Customer_107 | D9: =IFERROR(DATE(Q8,P8,R8),"Invalid") -> 45660 | E9: =TRIM('01_Raw'!E9) -> Biography | F9: =IF(PROPER(TRIM('01_Raw'!F9))="Electronic","Electronics",PROPER(TRIM('01_Raw'!F9))) -> Books | I9: =TRIM('01_Raw'!I9) -> PayPal | J9: =TRIM('01_Raw'!J9) -> Returned | N9: =ISNUMBER('01_Raw'!D10) -> FALSE | P9: =LEFT('01_Raw'!D10, FIND("/",'01_Raw'!D10) - 1) -> 10 | Q9: =IFERROR(RIGHT('01_Raw'!D10,4),"Invalid") -> 2025 | R9: =MID('01_Raw'!D10,FIND("/",'01_Raw'!D10) + 1,FIND("/",'01_Raw'!D10,FIND("/",'01_Raw'!D10)+1)-FIND("/",'01_Raw'!D10)-1) -> 23 | S9: =IFERROR(DATE(Q9,P9,R9),"Invalid") -> 45953 | U9: =IFERROR(VALUE(SUBSTITUTE(SUBSTITUTE('01_Raw'!H10,"$",""), ".",",")),"Invalid") -> 600.29 | V9: =IFERROR(VALUE('01_Raw'!G10), "Invalid") -> 1 | X9: =IF(ISBLANK('01_Raw'!H10),"Missing", IFERROR(VALUE(SUBSTITUTE(SUBSTITUTE('01_Raw'!H10,"$",""), ".",",")),"Invalid")) -> 600.29 | Y9: =IF(LEN(TRIM('01_Raw'!H10)) = 0, "Missing",IFERROR(VALUE(SUBSTITUTE(SUBSTITUTE('01_Raw'!H10,"$",""), ".",",")),"Invalid")) -> 600.29 | AA9: =IF(LEN(TRIM('01_Raw'!G10)) = 0, "Missing",IFERROR(VALUE(SUBSTITUTE(SUBSTITUTE('01_Raw'!G10,"$",""), ".",",")),"Invalid")) -> 1 | AC9: =COUNTIF($A$2:$A$103,A10) -> 1 | AE9: =COUNTIF(messy_ecommerce_sales_data__2[Order_ID],'01_Raw'!C10) -> 1 | AG9: =IFERROR(AA9*Y9,"Cannot Calculate") -> 600.29 | AH9: =IF(AG9='01_Raw'!K10,"OK","Mismatch") -> Mismatch | AJ9: =IF(LEN(TRIM(AG9)) = 0, "Missing",IFERROR(VALUE(SUBSTITUTE(SUBSTITUTE(AG9,"$",""), ".",",")),"Invalid")) -> 600.29 | AK9: =IF(AJ9=AG9,"OK","Mismatch") -> OK
A10: ='01_Raw'!A10 -> 108 | B10: =TRIM('01_Raw'!B10) -> Customer_108 | D10: =IFERROR(DATE(Q9,P9,R9),"Invalid") -> 45953 | E10: =TRIM('01_Raw'!E10) -> Science | F10: =IF(PROPER(TRIM('01_Raw'!F10))="Electronic","Electronics",PROPER(TRIM('01_Raw'!F10))) -> Books | I10: =TRIM('01_Raw'!I10) -> Cash on Delivery | J10: =TRIM('01_Raw'!J10) -> Processing | N10: =ISNUMBER('01_Raw'!D11) -> FALSE | P10: =LEFT('01_Raw'!D11, FIND("/",'01_Raw'!D11) - 1) -> 5 | Q10: =IFERROR(RIGHT('01_Raw'!D11,4),"Invalid") -> 2025 | R10: =MID('01_Raw'!D11,FIND("/",'01_Raw'!D11) + 1,FIND("/",'01_Raw'!D11,FIND("/",'01_Raw'!D11)+1)-FIND("/",'01_Raw'!D11)-1) -> 3 | S10: =IFERROR(DATE(Q10,P10,R10),"Invalid") -> 45780 | U10: =IFERROR(VALUE(SUBSTITUTE(SUBSTITUTE('01_Raw'!H11,"$",""), ".",",")),"Invalid") -> 168.34 | V10: =IFERROR(VALUE('01_Raw'!G11), "Invalid") -> 5 | X10: =IF(ISBLANK('01_Raw'!H11),"Missing", IFERROR(VALUE(SUBSTITUTE(SUBSTITUTE('01_Raw'!H11,"$",""), ".",",")),"Invalid")) -> 168.34 | Y10: =IF(LEN(TRIM('01_Raw'!H11)) = 0, "Missing",IFERROR(VALUE(SUBSTITUTE(SUBSTITUTE('01_Raw'!H11,"$",""), ".",",")),"Invalid")) -> 168.34 | AA10: =IF(LEN(TRIM('01_Raw'!G11)) = 0, "Missing",IFERROR(VALUE(SUBSTITUTE(SUBSTITUTE('01_Raw'!G11,"$",""), ".",",")),"Invalid")) -> 5 | AC10: =COUNTIF($A$2:$A$103,A11) -> 1 | AE10: =COUNTIF(messy_ecommerce_sales_data__2[Order_ID],'01_Raw'!C11) -> 1 | AG10: =IFERROR(AA10*Y10,"Cannot Calculate") -> 841.7 | AH10: =IF(AG10='01_Raw'!K11,"OK","Mismatch") -> Mismatch | AJ10: =IF(LEN(TRIM(AG10)) = 0, "Missing",IFERROR(VALUE(SUBSTITUTE(SUBSTITUTE(AG10,"$",""), ".",",")),"Invalid")) -> 841.7 | AK10: =IF(AJ10=AG10,"OK","Mismatch") -> OK
A11: ='01_Raw'!A11 -> 109 | B11: =TRIM('01_Raw'!B11) -> Customer_109 | D11: =IFERROR(DATE(Q10,P10,R10),"Invalid") -> 45780 | E11: =TRIM('01_Raw'!E11) -> Tennis Racket | F11: =IF(PROPER(TRIM('01_Raw'!F11))="Electronic","Electronics",PROPER(TRIM('01_Raw'!F11))) -> Sports | I11: =TRIM('01_Raw'!I11) -> Credit Card | J11: =TRIM('01_Raw'!J11) -> Shipped | N11: =ISNUMBER('01_Raw'!D12) -> FALSE | P11: =LEFT('01_Raw'!D12, FIND("/",'01_Raw'!D12) - 1) -> 9 | Q11: =IFERROR(RIGHT('01_Raw'!D12,4),"Invalid") -> 2025 | R11: =MID('01_Raw'!D12,FIND("/",'01_Raw'!D12) + 1,FIND("/",'01_Raw'!D12,FIND("/",'01_Raw'!D12)+1)-FIND("/",'01_Raw'!D12)-1) -> 26 | S11: =IFERROR(DATE(Q11,P11,R11),"Invalid") -> 45926 | U11: =IFERROR(VALUE(SUBSTITUTE(SUBSTITUTE('01_Raw'!H12,"$",""), ".",",")),"Invalid") -> Invalid | V11: =IFERROR(VALUE('01_Raw'!G12), "Invalid") -> 5 | X11: =IF(ISBLANK('01_Raw'!H12),"Missing", IFERROR(VALUE(SUBSTITUTE(SUBSTITUTE('01_Raw'!H12,"$",""), ".",",")),"Invalid")) -> Invalid | Y11: =IF(LEN(TRIM('01_Raw'!H12)) = 0, "Missing",IFERROR(VALUE(SUBSTITUTE(SUBSTITUTE('01_Raw'!H12,"$",""), ".",",")),"Invalid")) -> Invalid | AA11: =IF(LEN(TRIM('01_Raw'!G12)) = 0, "Missing",IFERROR(VALUE(SUBSTITUTE(SUBSTITUTE('01_Raw'!G12,"$",""), ".",",")),"Invalid")) -> 5 | AC11: =COUNTIF($A$2:$A$103,A12) -> 1 | AE11: =COUNTIF(messy_ecommerce_sales_data__2[Order_ID],'01_Raw'!C12) -> 1 | AG11: =IFERROR(AA11*Y11,"Cannot Calculate") -> Cannot Calculate | AH11: =IF(AG11='01_Raw'!K12,"OK","Mismatch") -> Mismatch | AJ11: =IF(LEN(TRIM(AG11)) = 0, "Missing",IFERROR(VALUE(SUBSTITUTE(SUBSTITUTE(AG11,"$",""), ".",",")),"Invalid")) -> Invalid | AK11: =IF(AJ11=AG11,"OK","Mismatch") -> Mismatch
A12: ='01_Raw'!A12 -> 110 | B12: =TRIM('01_Raw'!B12) -> Customer_110 | D12: =IFERROR(DATE(Q11,P11,R11),"Invalid") -> 45926 | E12: =TRIM('01_Raw'!E12) -> Basketball | F12: =IF(PROPER(TRIM('01_Raw'!F12))="Electronic","Electronics",PROPER(TRIM('01_Raw'!F12))) -> Sports | I12: =TRIM('01_Raw'!I12) -> Cash on Delivery | J12: =TRIM('01_Raw'!J12) -> Cancelled | N12: =ISNUMBER('01_Raw'!D13) -> FALSE | P12: =LEFT('01_Raw'!D13, FIND("/",'01_Raw'!D13) - 1) -> 10 | Q12: =IFERROR(RIGHT('01_Raw'!D13,4),"Invalid") -> 2025 | R12: =MID('01_Raw'!D13,FIND("/",'01_Raw'!D13) + 1,FIND("/",'01_Raw'!D13,FIND("/",'01_Raw'!D13)+1)-FIND("/",'01_Raw'!D13)-1) -> 22 | S12: =IFERROR(DATE(Q12,P12,R12),"Invalid") -> 45952 | U12: =IFERROR(VALUE(SUBSTITUTE(SUBSTITUTE('01_Raw'!H13,"$",""), ".",",")),"Invalid") -> 865.77 | V12: =IFERROR(VALUE('01_Raw'!G13), "Invalid") -> 2 | X12: =IF(ISBLANK('01_Raw'!H13),"Missing", IFERROR(VALUE(SUBSTITUTE(SUBSTITUTE('01_Raw'!H13,"$",""), ".",",")),"Invalid")) -> 865.77 | Y12: =IF(LEN(TRIM('01_Raw'!H13)) = 0, "Missing",IFERROR(VALUE(SUBSTITUTE(SUBSTITUTE('01_Raw'!H13,"$",""), ".",",")),"Invalid")) -> 865.77 | AA12: =IF(LEN(TRIM('01_Raw'!G13)) = 0, "Missing",IFERROR(VALUE(SUBSTITUTE(SUBSTITUTE('01_Raw'!G13,"$",""), ".",",")),"Invalid")) -> 2 | AC12: =COUNTIF($A$2:$A$103,A13) -> 1 | AE12: =COUNTIF(messy_ecommerce_sales_data__2[Order_ID],'01_Raw'!C13) -> 1 | AG12: =IFERROR(AA12*Y12,"Cannot Calculate") -> 1731.54 | AH12: =IF(AG12='01_Raw'!K13,"OK","Mismatch") -> Mismatch | AJ12: =IF(LEN(TRIM(AG12)) = 0, "Missing",IFERROR(VALUE(SUBSTITUTE(SUBSTITUTE(AG12,"$",""), ".",",")),"Invalid")) -> 1731.54 | AK12: =IF(AJ12=AG12,"OK","Mismatch") -> OK
A13: ='01_Raw'!A13 -> 111 | B13: =TRIM('01_Raw'!B13) -> Customer_111 | D13: =IFERROR(DATE(Q12,P12,R12),"Invalid") -> 45952 | E13: =TRIM('01_Raw'!E13) -> Comics | F13: =IF(PROPER(TRIM('01_Raw'!F13))="Electronic","Electronics",PROPER(TRIM('01_Raw'!F13))) -> Books | I13: =TRIM('01_Raw'!I13) -> Credit Card | J13: =TRIM('01_Raw'!J13) -> Returned | N13: =ISNUMBER('01_Raw'!D14) -> FALSE | P13: =LEFT('01_Raw'!D14, FIND("/",'01_Raw'!D14) - 1) -> 3 | Q13: =IFERROR(RIGHT('01_Raw'!D14,4),"Invalid") -> 2025 | R13: =MID('01_Raw'!D14,FIND("/",'01_Raw'!D14) + 1,FIND("/",'01_Raw'!D14,FIND("/",'01_Raw'!D14)+1)-FIND("/",'01_Raw'!D14)-1) -> 2 | S13: =IFERROR(DATE(Q13,P13,R13),"Invalid") -> 45718 | U13: =IFERROR(VALUE(SUBSTITUTE(SUBSTITUTE('01_Raw'!H14,"$",""), ".",",")),"Invalid") -> 752.13 | V13: =IFERROR(VALUE('01_Raw'!G14), "Invalid") -> 4 | X13: =IF(ISBLANK('01_Raw'!H14),"Missing", IFERROR(VALUE(SUBSTITUTE(SUBSTITUTE('01_Raw'!H14,"$",""), ".",",")),"Invalid")) -> 752.13 | Y13: =IF(LEN(TRIM('01_Raw'!H14)) = 0, "Missing",IFERROR(VALUE(SUBSTITUTE(SUBSTITUTE('01_Raw'!H14,"$",""), ".",",")),"Invalid")) -> 752.13 | AA13: =IF(LEN(TRIM('01_Raw'!G14)) = 0, "Missing",IFERROR(VALUE(SUBSTITUTE(SUBSTITUTE('01_Raw'!G14,"$",""), ".",",")),"Invalid")) -> 4 | AC13: =COUNTIF($A$2:$A$103,A14) -> 1 | AE13: =COUNTIF(messy_ecommerce_sales_data__2[Order_ID],'01_Raw'!C14) -> 1 | AG13: =IFERROR(AA13*Y13,"Cannot Calculate") -> 3008.52 | AH13: =IF(AG13='01_Raw'!K14,"OK","Mismatch") -> Mismatch | AJ13: =IF(LEN(TRIM(AG13)) = 0, "Missing",IFERROR(VALUE(SUBSTITUTE(SUBSTITUTE(AG13,"$",""), ".",",")),"Invalid")) -> 3008.52 | AK13: =IF(AJ13=AG13,"OK","Mismatch") -> OK
... A42: ='01_Raw'!A42 -> 140 | B42: =TRIM('01_Raw'!B42) -> Customer_140 | D42: =IFERROR(DATE(Q41,P41,R41),"Invalid") -> 45714 | E42: =TRIM('01_Raw'!E42) -> Fiction | F42: =IF(PROPER(TRIM('01_Raw'!F42))="Electronic","Electronics",PROPER(TRIM('01_Raw'!F42))) -> Books | I42: =TRIM('01_Raw'!I42) -> Credit Card | J42: =TRIM('01_Raw'!J42) -> Returned | N42: =ISNUMBER('01_Raw'!D43) -> FALSE | P42: =LEFT('01_Raw'!D43, FIND("/",'01_Raw'!D43) - 1) -> 2 | Q42: =IFERROR(RIGHT('01_Raw'!D43,4),"Invalid") -> 2025 | R42: =MID('01_Raw'!D43,FIND("/",'01_Raw'!D43) + 1,FIND("/",'01_Raw'!D43,FIND("/",'01_Raw'!D43)+1)-FIND("/",'01_Raw'!D43)-1) -> 13 | S42: =IFERROR(DATE(Q42,P42,R42),"Invalid") -> 45701 | U42: =IFERROR(VALUE(SUBSTITUTE(SUBSTITUTE('01_Raw'!H43,"$",""), ".",",")),"Invalid") -> 546.04 | V42: =IFERROR(VALUE('01_Raw'!G43), "Invalid") -> 3 | X42: =IF(ISBLANK('01_Raw'!H43),"Missing", IFERROR(VALUE(SUBSTITUTE(SUBSTITUTE('01_Raw'!H43,"$",""), ".",",")),"Invalid")) -> 546.04 | Y42: =IF(LEN(TRIM('01_Raw'!H43)) = 0, "Missing",IFERROR(VALUE(SUBSTITUTE(SUBSTITUTE('01_Raw'!H43,"$",""), ".",",")),"Invalid")) -> 546.04 | AA42: =IF(LEN(TRIM('01_Raw'!G43)) = 0, "Missing",IFERROR(VALUE(SUBSTITUTE(SUBSTITUTE('01_Raw'!G43,"$",""), ".",",")),"Invalid")) -> 3 | AC42: =COUNTIF($A$2:$A$103,A43) -> 1 | AE42: =COUNTIF(messy_ecommerce_sales_data__2[Order_ID],'01_Raw'!C43) -> 1 | AG42: =IFERROR(AA42*Y42,"Cannot Calculate") -> 1638.12 | AH42: =IF(AG42='01_Raw'!K43,"OK","Mismatch") -> Mismatch | AJ42: =IF(LEN(TRIM(AG42)) = 0, "Missing",IFERROR(VALUE(SUBSTITUTE(SUBSTITUTE(AG42,"$",""), ".",",")),"Invalid")) -> 1638.12 | AK42: =IF(AJ42=AG42,"OK","Mismatch") -> OK
A43: ='01_Raw'!A43 -> 141 | B43: =TRIM('01_Raw'!B43) -> Customer_141 | D43: =IFERROR(DATE(Q42,P42,R42),"Invalid") -> 45701 | E43: =TRIM('01_Raw'!E43) -> Fiction | F43: =IF(PROPER(TRIM('01_Raw'!F43))="Electronic","Electronics",PROPER(TRIM('01_Raw'!F43))) -> Books | I43: =TRIM('01_Raw'!I43) -> Cash on Delivery | J43: =TRIM('01_Raw'!J43) -> Returned | N43: =ISNUMBER('01_Raw'!D44) -> FALSE | P43: =LEFT('01_Raw'!D44, FIND("/",'01_Raw'!D44) - 1) -> 10 | Q43: =IFERROR(RIGHT('01_Raw'!D44,4),"Invalid") -> 2025 | R43: =MID('01_Raw'!D44,FIND("/",'01_Raw'!D44) + 1,FIND("/",'01_Raw'!D44,FIND("/",'01_Raw'!D44)+1)-FIND("/",'01_Raw'!D44)-1) -> 30 | S43: =IFERROR(DATE(Q43,P43,R43),"Invalid") -> 45960 | U43: =IFERROR(VALUE(SUBSTITUTE(SUBSTITUTE('01_Raw'!H44,"$",""), ".",",")),"Invalid") -> 645.26 | V43: =IFERROR(VALUE('01_Raw'!G44), "Invalid") -> 5 | X43: =IF(ISBLANK('01_Raw'!H44),"Missing", IFERROR(VALUE(SUBSTITUTE(SUBSTITUTE('01_Raw'!H44,"$",""), ".",",")),"Invalid")) -> 645.26 | Y43: =IF(LEN(TRIM('01_Raw'!H44)) = 0, "Missing",IFERROR(VALUE(SUBSTITUTE(SUBSTITUTE('01_Raw'!H44,"$",""), ".",",")),"Invalid")) -> 645.26 | AA43: =IF(LEN(TRIM('01_Raw'!G44)) = 0, "Missing",IFERROR(VALUE(SUBSTITUTE(SUBSTITUTE('01_Raw'!G44,"$",""), ".",",")),"Invalid")) -> 5 | AC43: =COUNTIF($A$2:$A$103,#REF!) -> 0 | AE43: =COUNTIF(messy_ecommerce_sales_data__2[Order_ID],'01_Raw'!C44) -> 2 | AG43: =IFERROR(AA43*Y43,"Cannot Calculate") -> 3226.3 | AH43: =IF(AG43='01_Raw'!K44,"OK","Mismatch") -> Mismatch | AJ43: =IF(LEN(TRIM(AG43)) = 0, "Missing",IFERROR(VALUE(SUBSTITUTE(SUBSTITUTE(AG43,"$",""), ".",",")),"Invalid")) -> 3226.3 | AK43: =IF(AJ43=AG43,"OK","Mismatch") -> OK
A44: ='01_Raw'!A45 -> 143 | B44: =TRIM('01_Raw'!B45) -> Customer_143 | D44: =IFERROR(DATE(Q43,P43,R43),"Invalid") -> 45960 | E44: =TRIM('01_Raw'!E45) -> T-shirt | F44: =IF(PROPER(TRIM('01_Raw'!F45))="Electronic","Electronics",PROPER(TRIM('01_Raw'!F45))) -> Clothing | I44: =TRIM('01_Raw'!I45) -> Bank Transfer | J44: =TRIM('01_Raw'!J45) -> Cancelled | N44: =ISNUMBER('01_Raw'!D46) -> FALSE | P44: =LEFT('01_Raw'!D46, FIND("/",'01_Raw'!D46) - 1) -> 1 | Q44: =IFERROR(RIGHT('01_Raw'!D46,4),"Invalid") -> 2025 | R44: =MID('01_Raw'!D46,FIND("/",'01_Raw'!D46) + 1,FIND("/",'01_Raw'!D46,FIND("/",'01_Raw'!D46)+1)-FIND("/",'01_Raw'!D46)-1) -> 27 | S44: =IFERROR(DATE(Q44,P44,R44),"Invalid") -> 45684 | U44: =IFERROR(VALUE(SUBSTITUTE(SUBSTITUTE('01_Raw'!H46,"$",""), ".",",")),"Invalid") -> 849.07 | V44: =IFERROR(VALUE('01_Raw'!G46), "Invalid") -> 5 | X44: =IF(ISBLANK('01_Raw'!H46),"Missing", IFERROR(VALUE(SUBSTITUTE(SUBSTITUTE('01_Raw'!H46,"$",""), ".",",")),"Invalid")) -> 849.07 | Y44: =IF(LEN(TRIM('01_Raw'!H46)) = 0, "Missing",IFERROR(VALUE(SUBSTITUTE(SUBSTITUTE('01_Raw'!H46,"$",""), ".",",")),"Invalid")) -> 849.07 | AA44: =IF(LEN(TRIM('01_Raw'!G46)) = 0, "Missing",IFERROR(VALUE(SUBSTITUTE(SUBSTITUTE('01_Raw'!G46,"$",""), ".",",")),"Invalid")) -> 5 | AC44: =COUNTIF($A$2:$A$103,A45) -> 1 | AE44: =COUNTIF(messy_ecommerce_sales_data__2[Order_ID],'01_Raw'!C46) -> 1 | AG44: =IFERROR(AA44*Y44,"Cannot Calculate") -> 4245.35 | AH44: =IF(AG44='01_Raw'!K45,"OK","Mismatch") -> Mismatch | AJ44: =IF(LEN(TRIM(AG44)) = 0, "Missing",IFERROR(VALUE(SUBSTITUTE(SUBSTITUTE(AG44,"$",""), ".",",")),"Invalid")) -> 4245.35 | AK44: =IF(AJ44=AG44,"OK","Mismatch") -> OK
A45: ='01_Raw'!A46 -> 144 | B45: =TRIM('01_Raw'!B46) -> Customer_144 | D45: =IFERROR(DATE(Q44,P44,R44),"Invalid") -> 45684 | E45: =TRIM('01_Raw'!E46) -> Football | F45: =IF(PROPER(TRIM('01_Raw'!F46))="Electronic","Electronics",PROPER(TRIM('01_Raw'!F46))) -> Sports | I45: =TRIM('01_Raw'!I46) -> Bank Transfer | J45: =TRIM('01_Raw'!J46) -> Processing | N45: =ISNUMBER('01_Raw'!D47) -> FALSE | P45: =LEFT('01_Raw'!D47, FIND("/",'01_Raw'!D47) - 1) -> 5 | Q45: =IFERROR(RIGHT('01_Raw'!D47,4),"Invalid") -> 2023 | R45: =MID('01_Raw'!D47,FIND("/",'01_Raw'!D47) + 1,FIND("/",'01_Raw'!D47,FIND("/",'01_Raw'!D47)+1)-FIND("/",'01_Raw'!D47)-1) -> 1 | S45: =IFERROR(DATE(Q45,P45,R45),"Invalid") -> 45047 | U45: =IFERROR(VALUE(SUBSTITUTE(SUBSTITUTE('01_Raw'!H47,"$",""), ".",",")),"Invalid") -> 860.99 | V45: =IFERROR(VALUE('01_Raw'!G47), "Invalid") -> 2 | X45: =IF(ISBLANK('01_Raw'!H47),"Missing", IFERROR(VALUE(SUBSTITUTE(SUBSTITUTE('01_Raw'!H47,"$",""), ".",",")),"Invalid")) -> 860.99 | Y45: =IF(LEN(TRIM('01_Raw'!H47)) = 0, "Missing",IFERROR(VALUE(SUBSTITUTE(SUBSTITUTE('01_Raw'!H47,"$",""), ".",",")),"Invalid")) -> 860.99 | AA45: =IF(LEN(TRIM('01_Raw'!G47)) = 0, "Missing",IFERROR(VALUE(SUBSTITUTE(SUBSTITUTE('01_Raw'!G47,"$",""), ".",",")),"Invalid")) -> 2 | AC45: =COUNTIF($A$2:$A$103,A46) -> 1 | AE45: =COUNTIF(messy_ecommerce_sales_data__2[Order_ID],'01_Raw'!C47) -> 1 | AG45: =IFERROR(AA45*Y45,"Cannot Calculate") -> 1721.98 | AH45: =IF(AG45='01_Raw'!K46,"OK","Mismatch") -> Mismatch | AJ45: =IF(LEN(TRIM(AG45)) = 0, "Missing",IFERROR(VALUE(SUBSTITUTE(SUBSTITUTE(AG45,"$",""), ".",",")),"Invalid")) -> 1721.98 | AK45: =IF(AJ45=AG45,"OK","Mismatch") -> OK
A46: ='01_Raw'!A47 -> 145 | B46: =TRIM('01_Raw'!B47) -> Customer_145 | D46: =IFERROR(DATE(Q45,P45,R45),"Invalid") -> 45047 | E46: =TRIM('01_Raw'!E47) -> Laptop | F46: =IF(PROPER(TRIM('01_Raw'!F47))="Electronic","Electronics",PROPER(TRIM('01_Raw'!F47))) -> Electronics | I46: =TRIM('01_Raw'!I47) -> Bank Transfer | J46: =TRIM('01_Raw'!J47) -> Returned | N46: =ISNUMBER('01_Raw'!D48) -> FALSE | P46: =LEFT('01_Raw'!D48, FIND("/",'01_Raw'!D48) - 1) -> 7 | Q46: =IFERROR(RIGHT('01_Raw'!D48,4),"Invalid") -> 2025 | R46: =MID('01_Raw'!D48,FIND("/",'01_Raw'!D48) + 1,FIND("/",'01_Raw'!D48,FIND("/",'01_Raw'!D48)+1)-FIND("/",'01_Raw'!D48)-1) -> 9 | S46: =IFERROR(DATE(Q46,P46,R46),"Invalid") -> 45847 | U46: =IFERROR(VALUE(SUBSTITUTE(SUBSTITUTE('01_Raw'!H48,"$",""), ".",",")),"Invalid") -> 705.42 | V46: =IFERROR(VALUE('01_Raw'!G48), "Invalid") -> 2 | X46: =IF(ISBLANK('01_Raw'!H48),"Missing", IFERROR(VALUE(SUBSTITUTE(SUBSTITUTE('01_Raw'!H48,"$",""), ".",",")),"Invalid")) -> 705.42 | Y46: =IF(LEN(TRIM('01_Raw'!H48)) = 0, "Missing",IFERROR(VALUE(SUBSTITUTE(SUBSTITUTE('01_Raw'!H48,"$",""), ".",",")),"Invalid")) -> 705.42 | AA46: =IF(LEN(TRIM('01_Raw'!G48)) = 0, "Missing",IFERROR(VALUE(SUBSTITUTE(SUBSTITUTE('01_Raw'!G48,"$",""), ".",",")),"Invalid")) -> 2 | AC46: =COUNTIF($A$2:$A$103,A47) -> 2 | AE46: =COUNTIF(messy_ecommerce_sales_data__2[Order_ID],'01_Raw'!C48) -> 2 | AG46: =IFERROR(AA46*Y46,"Cannot Calculate") -> 1410.84 | AH46: =IF(AG46='01_Raw'!K47,"OK","Mismatch") -> Mismatch | AJ46: =IF(LEN(TRIM(AG46)) = 0, "Missing",IFERROR(VALUE(SUBSTITUTE(SUBSTITUTE(AG46,"$",""), ".",",")),"Invalid")) -> 1410.84 | AK46: =IF(AJ46=AG46,"OK","Mismatch") -> OK
A47: ='01_Raw'!A48 -> 146 | B47: =TRIM('01_Raw'!B48) -> Customer_146 | D47: =IFERROR(DATE(Q46,P46,R46),"Invalid") -> 45847 | E47: =TRIM('01_Raw'!E48) -> Basketball | F47: =IF(PROPER(TRIM('01_Raw'!F48))="Electronic","Electronics",PROPER(TRIM('01_Raw'!F48))) -> Electronics | I47: =TRIM('01_Raw'!I48) -> Bank Transfer | J47: =TRIM('01_Raw'!J48) -> Processing | N47: =ISNUMBER('01_Raw'!D49) -> FALSE | P47: =LEFT('01_Raw'!D49, FIND("/",'01_Raw'!D49) - 1) -> 5 | Q47: =IFERROR(RIGHT('01_Raw'!D49,4),"Invalid") -> 2025 | R47: =MID('01_Raw'!D49,FIND("/",'01_Raw'!D49) + 1,FIND("/",'01_Raw'!D49,FIND("/",'01_Raw'!D49)+1)-FIND("/",'01_Raw'!D49)-1) -> 1 | S47: =IFERROR(DATE(Q47,P47,R47),"Invalid") -> 45778 | U47: =IFERROR(VALUE(SUBSTITUTE(SUBSTITUTE('01_Raw'!H49,"$",""), ".",",")),"Invalid") -> 596.15 | V47: =IFERROR(VALUE('01_Raw'!G49), "Invalid") -> 4 | X47: =IF(ISBLANK('01_Raw'!H49),"Missing", IFERROR(VALUE(SUBSTITUTE(SUBSTITUTE('01_Raw'!H49,"$",""), ".",",")),"Invalid")) -> 596.15 | Y47: =IF(LEN(TRIM('01_Raw'!H49)) = 0, "Missing",IFERROR(VALUE(SUBSTITUTE(SUBSTITUTE('01_Raw'!H49,"$",""), ".",",")),"Invalid")) -> 596.15 | AA47: =IF(LEN(TRIM('01_Raw'!G49)) = 0, "Missing",IFERROR(VALUE(SUBSTITUTE(SUBSTITUTE('01_Raw'!G49,"$",""), ".",",")),"Invalid")) -> 4 | AC47: =COUNTIF($A$2:$A$103,A48) -> 1 | AE47: =COUNTIF(messy_ecommerce_sales_data__2[Order_ID],'01_Raw'!C49) -> 1 | AG47: =IFERROR(AA47*Y47,"Cannot Calculate") -> 2384.6 | AH47: =IF(AG47='01_Raw'!K48,"OK","Mismatch") -> Mismatch | AJ47: =IF(LEN(TRIM(AG47)) = 0, "Missing",IFERROR(VALUE(SUBSTITUTE(SUBSTITUTE(AG47,"$",""), ".",",")),"Invalid")) -> 2384.6 | AK47: =IF(AJ47=AG47,"OK","Mismatch") -> OK
A48: ='01_Raw'!A49 -> 147 | B48: =TRIM('01_Raw'!B49) -> Customer_147 | D48: =IFERROR(DATE(Q47,P47,R47),"Invalid") -> 45778 | E48: =TRIM('01_Raw'!E49) -> Jacket | F48: =IF(PROPER(TRIM('01_Raw'!F49))="Electronic","Electronics",PROPER(TRIM('01_Raw'!F49))) -> Clothing | I48: =TRIM('01_Raw'!I49) -> Cash on Delivery | J48: =TRIM('01_Raw'!J49) -> Shipped | N48: =ISNUMBER('01_Raw'!D50) -> FALSE | P48: =LEFT('01_Raw'!D50, FIND("/",'01_Raw'!D50) - 1) -> 3 | Q48: =IFERROR(RIGHT('01_Raw'!D50,4),"Invalid") -> 2025 | R48: =MID('01_Raw'!D50,FIND("/",'01_Raw'!D50) + 1,FIND("/",'01_Raw'!D50,FIND("/",'01_Raw'!D50)+1)-FIND("/",'01_Raw'!D50)-1) -> 13 | S48: =IFERROR(DATE(Q48,P48,R48),"Invalid") -> 45729 | U48: =IFERROR(VALUE(SUBSTITUTE(SUBSTITUTE('01_Raw'!H50,"$",""), ".",",")),"Invalid") -> 660.98 | V48: =IFERROR(VALUE('01_Raw'!G50), "Invalid") -> 1 | X48: =IF(ISBLANK('01_Raw'!H50),"Missing", IFERROR(VALUE(SUBSTITUTE(SUBSTITUTE('01_Raw'!H50,"$",""), ".",",")),"Invalid")) -> 660.98 | Y48: =IF(LEN(TRIM('01_Raw'!H50)) = 0, "Missing",IFERROR(VALUE(SUBSTITUTE(SUBSTITUTE('01_Raw'!H50,"$",""), ".",",")),"Invalid")) -> 660.98 | AA48: =IF(LEN(TRIM('01_Raw'!G50)) = 0, "Missing",IFERROR(VALUE(SUBSTITUTE(SUBSTITUTE('01_Raw'!G50,"$",""), ".",",")),"Invalid")) -> 1 | AC48: =COUNTIF($A$2:$A$103,A49) -> 1 | AE48: =COUNTIF(messy_ecommerce_sales_data__2[Order_ID],'01_Raw'!C50) -> 1 | AG48: =IFERROR(AA48*Y48,"Cannot Calculate") -> 660.98 | AH48: =IF(AG48='01_Raw'!K49,"OK","Mismatch") -> Mismatch | AJ48: =IF(LEN(TRIM(AG48)) = 0, "Missing",IFERROR(VALUE(SUBSTITUTE(SUBSTITUTE(AG48,"$",""), ".",",")),"Invalid")) -> 660.98 | AK48: =IF(AJ48=AG48,"OK","Mismatch") -> OK
A49: ='01_Raw'!A50 -> 148 | B49: =TRIM('01_Raw'!B50) -> Customer_148 | D49: =IFERROR(DATE(Q48,P48,R48),"Invalid") -> 45729 | E49: =TRIM('01_Raw'!E50) -> Tennis Racket | F49: =IF(PROPER(TRIM('01_Raw'!F50))="Electronic","Electronics",PROPER(TRIM('01_Raw'!F50))) -> Sports | I49: =TRIM('01_Raw'!I50) -> Cash on Delivery | J49: =TRIM('01_Raw'!J50) -> Returned | N49: =ISNUMBER('01_Raw'!D51) -> FALSE | P49: =LEFT('01_Raw'!D51, FIND("/",'01_Raw'!D51) - 1) -> 6 | Q49: =IFERROR(RIGHT('01_Raw'!D51,4),"Invalid") -> 2025 | R49: =MID('01_Raw'!D51,FIND("/",'01_Raw'!D51) + 1,FIND("/",'01_Raw'!D51,FIND("/",'01_Raw'!D51)+1)-FIND("/",'01_Raw'!D51)-1) -> 29 | S49: =IFERROR(DATE(Q49,P49,R49),"Invalid") -> 45837 | U49: =IFERROR(VALUE(SUBSTITUTE(SUBSTITUTE('01_Raw'!H51,"$",""), ".",",")),"Invalid") -> 896.38 | V49: =IFERROR(VALUE('01_Raw'!G51), "Invalid") -> 5 | X49: =IF(ISBLANK('01_Raw'!H51),"Missing", IFERROR(VALUE(SUBSTITUTE(SUBSTITUTE('01_Raw'!H51,"$",""), ".",",")),"Invalid")) -> 896.38 | Y49: =IF(LEN(TRIM('01_Raw'!H51)) = 0, "Missing",IFERROR(VALUE(SUBSTITUTE(SUBSTITUTE('01_Raw'!H51,"$",""), ".",",")),"Invalid")) -> 896.38 | AA49: =IF(LEN(TRIM('01_Raw'!G51)) = 0, "Missing",IFERROR(VALUE(SUBSTITUTE(SUBSTITUTE('01_Raw'!G51,"$",""), ".",",")),"Invalid")) -> 5 | AC49: =COUNTIF($A$2:$A$103,A50) -> 1 | AE49: =COUNTIF(messy_ecommerce_sales_data__2[Order_ID],'01_Raw'!C51) -> 1 | AG49: =IFERROR(AA49*Y49,"Cannot Calculate") -> 4481.9 | AH49: =IF(AG49='01_Raw'!K50,"OK","Mismatch") -> Mismatch | AJ49: =IF(LEN(TRIM(AG49)) = 0, "Missing",IFERROR(VALUE(SUBSTITUTE(SUBSTITUTE(AG49,"$",""), ".",",")),"Invalid")) -> 4481.9 | AK49: =IF(AJ49=AG49,"OK","Mismatch") -> OK
A50: ='01_Raw'!A51 -> 149 | B50: =TRIM('01_Raw'!B51) -> Customer_149 | D50: =IFERROR(DATE(Q49,P49,R49),"Invalid") -> 45837 | E50: =TRIM('01_Raw'!E51) -> Comics | F50: =IF(PROPER(TRIM('01_Raw'!F51))="Electronic","Electronics",PROPER(TRIM('01_Raw'!F51))) -> Books | I50: =TRIM('01_Raw'!I51) -> Bank Transfer | J50: =TRIM('01_Raw'!J51) -> Cancelled | N50: =ISNUMBER('01_Raw'!D52) -> FALSE | P50: =LEFT('01_Raw'!D52, FIND("/",'01_Raw'!D52) - 1) -> 11 | Q50: =IFERROR(RIGHT('01_Raw'!D52,4),"Invalid") -> 2024 | R50: =MID('01_Raw'!D52,FIND("/",'01_Raw'!D52) + 1,FIND("/",'01_Raw'!D52,FIND("/",'01_Raw'!D52)+1)-FIND("/",'01_Raw'!D52)-1) -> 27 | S50: =IFERROR(DATE(Q50,P50,R50),"Invalid") -> 45623 | U50: =IFERROR(VALUE(SUBSTITUTE(SUBSTITUTE('01_Raw'!H52,"$",""), ".",",")),"Invalid") -> 206.19 | V50: =IFERROR(VALUE('01_Raw'!G52), "Invalid") -> 1 | X50: =IF(ISBLANK('01_Raw'!H52),"Missing", IFERROR(VALUE(SUBSTITUTE(SUBSTITUTE('01_Raw'!H52,"$",""), ".",",")),"Invalid")) -> 206.19 | Y50: =IF(LEN(TRIM('01_Raw'!H52)) = 0, "Missing",IFERROR(VALUE(SUBSTITUTE(SUBSTITUTE('01_Raw'!H52,"$",""), ".",",")),"Invalid")) -> 206.19 | AA50: =IF(LEN(TRIM('01_Raw'!G52)) = 0, "Missing",IFERROR(VALUE(SUBSTITUTE(SUBSTITUTE('01_Raw'!G52,"$",""), ".",",")),"Invalid")) -> 1 | AC50: =COUNTIF($A$2:$A$103,A51) -> 1 | AE50: =COUNTIF(messy_ecommerce_sales_data__2[Order_ID],'01_Raw'!C52) -> 1 | AG50: =IFERROR(AA50*Y50,"Cannot Calculate") -> 206.19 | AH50: =IF(AG50='01_Raw'!K51,"OK","Mismatch") -> Mismatch | AJ50: =IF(LEN(TRIM(AG50)) = 0, "Missing",IFERROR(VALUE(SUBSTITUTE(SUBSTITUTE(AG50,"$",""), ".",",")),"Invalid")) -> 206.19 | AK50: =IF(AJ50=AG50,"OK","Mismatch") -> OK
A51: ='01_Raw'!A52 -> 150 | B51: =TRIM('01_Raw'!B52) -> Customer_150 | D51: =IFERROR(DATE(Q50,P50,R50),"Invalid") -> 45623 | E51: =TRIM('01_Raw'!E52) -> Yoga Mat | F51: =IF(PROPER(TRIM('01_Raw'!F52))="Electronic","Electronics",PROPER(TRIM('01_Raw'!F52))) -> Sports | I51: =TRIM('01_Raw'!I52) -> Credit Card | J51: =TRIM('01_Raw'!J52) -> Returned | N51: =ISNUMBER('01_Raw'!D53) -> FALSE | P51: =LEFT('01_Raw'!D53, FIND("/",'01_Raw'!D53) - 1) -> 7 | Q51: =IFERROR(RIGHT('01_Raw'!D53,4),"Invalid") -> 2025 | R51: =MID('01_Raw'!D53,FIND("/",'01_Raw'!D53) + 1,FIND("/",'01_Raw'!D53,FIND("/",'01_Raw'!D53)+1)-FIND("/",'01_Raw'!D53)-1) -> 1 | S51: =IFERROR(DATE(Q51,P51,R51),"Invalid") -> 45839 | U51: =IFERROR(VALUE(SUBSTITUTE(SUBSTITUTE('01_Raw'!H53,"$",""), ".",",")),"Invalid") -> 457.16 | V51: =IFERROR(VALUE('01_Raw'!G53), "Invalid") -> 2 | X51: =IF(ISBLANK('01_Raw'!H53),"Missing", IFERROR(VALUE(SUBSTITUTE(SUBSTITUTE('01_Raw'!H53,"$",""), ".",",")),"Invalid")) -> 457.16 | Y51: =IF(LEN(TRIM('01_Raw'!H53)) = 0, "Missing",IFERROR(VALUE(SUBSTITUTE(SUBSTITUTE('01_Raw'!H53,"$",""), ".",",")),"Invalid")) -> 457.16 | AA51: =IF(LEN(TRIM('01_Raw'!G53)) = 0, "Missing",IFERROR(VALUE(SUBSTITUTE(SUBSTITUTE('01_Raw'!G53,"$",""), ".",",")),"Invalid")) -> 2 | AC51: =COUNTIF($A$2:$A$103,A52) -> 1 | AE51: =COUNTIF(messy_ecommerce_sales_data__2[Order_ID],'01_Raw'!C53) -> 1 | AG51: =IFERROR(AA51*Y51,"Cannot Calculate") -> 914.32 | AH51: =IF(AG51='01_Raw'!K52,"OK","Mismatch") -> Mismatch | AJ51: =IF(LEN(TRIM(AG51)) = 0, "Missing",IFERROR(VALUE(SUBSTITUTE(SUBSTITUTE(AG51,"$",""), ".",",")),"Invalid")) -> 914.32 | AK51: =IF(AJ51=AG51,"OK","Mismatch") -> OK
A52: ='01_Raw'!A53 -> 151 | B52: =TRIM('01_Raw'!B53) -> Customer_151 | D52: =IFERROR(DATE(Q51,P51,R51),"Invalid") -> 45839 | E52: =TRIM('01_Raw'!E53) -> Comics | F52: =IF(PROPER(TRIM('01_Raw'!F53))="Electronic","Electronics",PROPER(TRIM('01_Raw'!F53))) -> Books | I52: =TRIM('01_Raw'!I53) -> PayPal | J52: =TRIM('01_Raw'!J53) -> Processing | N52: =ISNUMBER('01_Raw'!D54) -> FALSE | P52: =LEFT('01_Raw'!D54, FIND("/",'01_Raw'!D54) - 1) -> 9 | Q52: =IFERROR(RIGHT('01_Raw'!D54,4),"Invalid") -> 2025 | R52: =MID('01_Raw'!D54,FIND("/",'01_Raw'!D54) + 1,FIND("/",'01_Raw'!D54,FIND("/",'01_Raw'!D54)+1)-FIND("/",'01_Raw'!D54)-1) -> 22 | S52: =IFERROR(DATE(Q52,P52,R52),"Invalid") -> 45922 | U52: =IFERROR(VALUE(SUBSTITUTE(SUBSTITUTE('01_Raw'!H54,"$",""), ".",",")),"Invalid") -> 233.11 | V52: =IFERROR(VALUE('01_Raw'!G54), "Invalid") -> 3 | X52: =IF(ISBLANK('01_Raw'!H54),"Missing", IFERROR(VALUE(SUBSTITUTE(SUBSTITUTE('01_Raw'!H54,"$",""), ".",",")),"Invalid")) -> 233.11 | Y52: =IF(LEN(TRIM('01_Raw'!H54)) = 0, "Missing",IFERROR(VALUE(SUBSTITUTE(SUBSTITUTE('01_Raw'!H54,"$",""), ".",",")),"Invalid")) -> 233.11 | AA52: =IF(LEN(TRIM('01_Raw'!G54)) = 0, "Missing",IFERROR(VALUE(SUBSTITUTE(SUBSTITUTE('01_Raw'!G54,"$",""), ".",",")),"Invalid")) -> 3 | AC52: =COUNTIF($A$2:$A$103,A53) -> 1 | AE52: =COUNTIF(messy_ecommerce_sales_data__2[Order_ID],'01_Raw'!C54) -> 1 | AG52: =IFERROR(AA52*Y52,"Cannot Calculate") -> 699.33 | AH52: =IF(AG52='01_Raw'!K53,"OK","Mismatch") -> Mismatch | AJ52: =IF(LEN(TRIM(AG52)) = 0, "Missing",IFERROR(VALUE(SUBSTITUTE(SUBSTITUTE(AG52,"$",""), ".",",")),"Invalid")) -> 699.33 | AK52: =IF(AJ52=AG52,"OK","Mismatch") -> OK
A53: ='01_Raw'!A54 -> 152 | B53: =TRIM('01_Raw'!B54) -> Customer_152 | D53: =IFERROR(DATE(Q52,P52,R52),"Invalid") -> 45922 | E53: =TRIM('01_Raw'!E54) -> Lamp | F53: =IF(PROPER(TRIM('01_Raw'!F54))="Electronic","Electronics",PROPER(TRIM('01_Raw'!F54))) -> Home | I53: =TRIM('01_Raw'!I54) -> PayPal | J53: =TRIM('01_Raw'!J54) -> Returned | N53: =ISNUMBER('01_Raw'!D55) -> FALSE | P53: =LEFT('01_Raw'!D55, FIND("/",'01_Raw'!D55) - 1) -> 7 | Q53: =IFERROR(RIGHT('01_Raw'!D55,4),"Invalid") -> 2025 | R53: =MID('01_Raw'!D55,FIND("/",'01_Raw'!D55) + 1,FIND("/",'01_Raw'!D55,FIND("/",'01_Raw'!D55)+1)-FIND("/",'01_Raw'!D55)-1) -> 16 | S53: =IFERROR(DATE(Q53,P53,R53),"Invalid") -> 45854 | U53: =IFERROR(VALUE(SUBSTITUTE(SUBSTITUTE('01_Raw'!H55,"$",""), ".",",")),"Invalid") -> 278.9 | V53: =IFERROR(VALUE('01_Raw'!G55), "Invalid") -> 4 | X53: =IF(ISBLANK('01_Raw'!H55),"Missing", IFERROR(VALUE(SUBSTITUTE(SUBSTITUTE('01_Raw'!H55,"$",""), ".",",")),"Invalid")) -> 278.9 | Y53: =IF(LEN(TRIM('01_Raw'!H55)) = 0, "Missing",IFERROR(VALUE(SUBSTITUTE(SUBSTITUTE('01_Raw'!H55,"$",""), ".",",")),"Invalid")) -> 278.9 | AA53: =IF(LEN(TRIM('01_Raw'!G55)) = 0, "Missing",IFERROR(VALUE(SUBSTITUTE(SUBSTITUTE('01_Raw'!G55,"$",""), ".",",")),"Invalid")) -> 4 | AC53: =COUNTIF($A$2:$A$103,A54) -> 1 | AE53: =COUNTIF(messy_ecommerce_sales_data__2[Order_ID],'01_Raw'!C55) -> 1 | AG53: =IFERROR(AA53*Y53,"Cannot Calculate") -> 1115.6 | AH53: =IF(AG53='01_Raw'!K54,"OK","Mismatch") -> Mismatch | AJ53: =IF(LEN(TRIM(AG53)) = 0, "Missing",IFERROR(VALUE(SUBSTITUTE(SUBSTITUTE(AG53,"$",""), ".",",")),"Invalid")) -> 1115.6 | AK53: =IF(AJ53=AG53,"OK","Mismatch") -> OK
A54: ='01_Raw'!A55 -> 153 | B54: =TRIM('01_Raw'!B55) -> Customer_153 | D54: =IFERROR(DATE(Q53,P53,R53),"Invalid") -> 45854 | E54: =TRIM('01_Raw'!E55) -> Yoga Mat | F54: =IF(PROPER(TRIM('01_Raw'!F55))="Electronic","Electronics",PROPER(TRIM('01_Raw'!F55))) -> Sports | I54: =TRIM('01_Raw'!I55) -> Cash on Delivery | J54: =TRIM('01_Raw'!J55) -> Processing | N54: =ISNUMBER('01_Raw'!D56) -> FALSE | P54: =LEFT('01_Raw'!D56, FIND("/",'01_Raw'!D56) - 1) -> 2 | Q54: =IFERROR(RIGHT('01_Raw'!D56,4),"Invalid") -> 2025 | R54: =MID('01_Raw'!D56,FIND("/",'01_Raw'!D56) + 1,FIND("/",'01_Raw'!D56,FIND("/",'01_Raw'!D56)+1)-FIND("/",'01_Raw'!D56)-1) -> 21 | S54: =IFERROR(DATE(Q54,P54,R54),"Invalid") -> 45709 | U54: =IFERROR(VALUE(SUBSTITUTE(SUBSTITUTE('01_Raw'!H56,"$",""), ".",",")),"Invalid") -> 789.64 | V54: =IFERROR(VALUE('01_Raw'!G56), "Invalid") -> 5 | X54: =IF(ISBLANK('01_Raw'!H56),"Missing", IFERROR(VALUE(SUBSTITUTE(SUBSTITUTE('01_Raw'!H56,"$",""), ".",",")),"Invalid")) -> 789.64 | Y54: =IF(LEN(TRIM('01_Raw'!H56)) = 0, "Missing",IFERROR(VALUE(SUBSTITUTE(SUBSTITUTE('01_Raw'!H56,"$",""), ".",",")),"Invalid")) -> 789.64 | AA54: =IF(LEN(TRIM('01_Raw'!G56)) = 0, "Missing",IFERROR(VALUE(SUBSTITUTE(SUBSTITUTE('01_Raw'!G56,"$",""), ".",",")),"Invalid")) -> 5 | AC54: =COUNTIF($A$2:$A$103,A55) -> 1 | AE54: =COUNTIF(messy_ecommerce_sales_data__2[Order_ID],'01_Raw'!C56) -> 1 | AG54: =IFERROR(AA54*Y54,"Cannot Calculate") -> 3948.2 | AH54: =IF(AG54='01_Raw'!K55,"OK","Mismatch") -> Mismatch | AJ54: =IF(LEN(TRIM(AG54)) = 0, "Missing",IFERROR(VALUE(SUBSTITUTE(SUBSTITUTE(AG54,"$",""), ".",",")),"Invalid")) -> 3948.2 | AK54: =IF(AJ54=AG54,"OK","Mismatch") -> OK
A55: ='01_Raw'!A56 -> 154 | B55: =TRIM('01_Raw'!B56) -> Customer_154 | D55: =IFERROR(DATE(Q54,P54,R54),"Invalid") -> 45709 | E55: =TRIM('01_Raw'!E56) -> Blender | F55: =IF(PROPER(TRIM('01_Raw'!F56))="Electronic","Electronics",PROPER(TRIM('01_Raw'!F56))) -> Home | I55: =TRIM('01_Raw'!I56) -> Cash on Delivery | J55: =TRIM('01_Raw'!J56) -> Cancelled | N55: =ISNUMBER('01_Raw'!D57) -> FALSE | P55: =LEFT('01_Raw'!D57, FIND("/",'01_Raw'!D57) - 1) -> 5 | Q55: =IFERROR(RIGHT('01_Raw'!D57,4),"Invalid") -> 2025 | R55: =MID('01_Raw'!D57,FIND("/",'01_Raw'!D57) + 1,FIND("/",'01_Raw'!D57,FIND("/",'01_Raw'!D57)+1)-FIND("/",'01_Raw'!D57)-1) -> 1 | S55: =IFERROR(DATE(Q55,P55,R55),"Invalid") -> 45778 | U55: =IFERROR(VALUE(SUBSTITUTE(SUBSTITUTE('01_Raw'!H57,"$",""), ".",",")),"Invalid") -> 40.95 | V55: =IFERROR(VALUE('01_Raw'!G57), "Invalid") -> 1 | X55: =IF(ISBLANK('01_Raw'!H57),"Missing", IFERROR(VALUE(SUBSTITUTE(SUBSTITUTE('01_Raw'!H57,"$",""), ".",",")),"Invalid")) -> 40.95 | Y55: =IF(LEN(TRIM('01_Raw'!H57)) = 0, "Missing",IFERROR(VALUE(SUBSTITUTE(SUBSTITUTE('01_Raw'!H57,"$",""), ".",",")),"Invalid")) -> 40.95 | AA55: =IF(LEN(TRIM('01_Raw'!G57)) = 0, "Missing",IFERROR(VALUE(SUBSTITUTE(SUBSTITUTE('01_Raw'!G57,"$",""), ".",",")),"Invalid")) -> 1 | AC55: =COUNTIF($A$2:$A$103,A56) -> 1 | AE55: =COUNTIF(messy_ecommerce_sales_data__2[Order_ID],'01_Raw'!C57) -> 1 | AG55: =IFERROR(AA55*Y55,"Cannot Calculate") -> 40.95 | AH55: =IF(AG55='01_Raw'!K56,"OK","Mismatch") -> Mismatch | AJ55: =IF(LEN(TRIM(AG55)) = 0, "Missing",IFERROR(VALUE(SUBSTITUTE(SUBSTITUTE(AG55,"$",""), ".",",")),"Invalid")) -> 40.95 | AK55: =IF(AJ55=AG55,"OK","Mismatch") -> OK
... A102: ='01_Raw'!A103 -> 142 | B102: =TRIM('01_Raw'!B103) -> Customer_142 | D102: =IFERROR(DATE(Q101,P101,R101),"Invalid") -> 45960 | E102: =TRIM('01_Raw'!E103) -> Shoes | F102: =IF(PROPER(TRIM('01_Raw'!F103))="Electronic","Electronics",PROPER(TRIM('01_Raw'!F103))) -> Clothing | I102: =TRIM('01_Raw'!I103) -> Credit Card | J102: =TRIM('01_Raw'!J103) -> Shipped | N102: =ISNUMBER('01_Raw'!D104) -> FALSE | P102: =LEFT('01_Raw'!D104, FIND("/",'01_Raw'!D104) - 1) -> 7 | Q102: =IFERROR(RIGHT('01_Raw'!D104,4),"Invalid") -> 2025 | R102: =MID('01_Raw'!D104,FIND("/",'01_Raw'!D104) + 1,FIND("/",'01_Raw'!D104,FIND("/",'01_Raw'!D104)+1)-FIND("/",'01_Raw'!D104)-1) -> 9 | S102: =IFERROR(DATE(Q102,P102,R102),"Invalid") -> 45847 | U102: =IFERROR(VALUE(SUBSTITUTE(SUBSTITUTE('01_Raw'!H104,"$",""), ".",",")),"Invalid") -> 705.42 | V102: =IFERROR(VALUE('01_Raw'!G104), "Invalid") -> 2 | X102: =IF(ISBLANK('01_Raw'!H104),"Missing", IFERROR(VALUE(SUBSTITUTE(SUBSTITUTE('01_Raw'!H104,"$",""), ".",",")),"Invalid")) -> 705.42 | Y102: =IF(LEN(TRIM('01_Raw'!H104)) = 0, "Missing",IFERROR(VALUE(SUBSTITUTE(SUBSTITUTE('01_Raw'!H104,"$",""), ".",",")),"Invalid")) -> 705.42 | AA102: =IF(LEN(TRIM('01_Raw'!G104)) = 0, "Missing",IFERROR(VALUE(SUBSTITUTE(SUBSTITUTE('01_Raw'!G104,"$",""), ".",",")),"Invalid")) -> 2 | AC102: =COUNTIF($A$2:$A$103,A103) -> 2 | AE102: =COUNTIF(messy_ecommerce_sales_data__2[Order_ID],'01_Raw'!C104) -> 2 | AG102: =IFERROR(AA102*Y102,"Cannot Calculate") -> 1410.84 | AH102: =IF(AG102='01_Raw'!K103,"OK","Mismatch") -> Mismatch | AJ102: =IF(LEN(TRIM(AG102)) = 0, "Missing",IFERROR(VALUE(SUBSTITUTE(SUBSTITUTE(AG102,"$",""), ".",",")),"Invalid")) -> 1410.84 | AK102: =IF(AJ102=AG102,"OK","Mismatch") -> OK
A103: ='01_Raw'!A104 -> 146 | B103: =TRIM('01_Raw'!B104) -> Customer_146 | D103: =IFERROR(DATE(Q102,P102,R102),"Invalid") -> 45847 | E103: =TRIM('01_Raw'!E104) -> Basketball | F103: =IF(PROPER(TRIM('01_Raw'!F104))="Electronic","Electronics",PROPER(TRIM('01_Raw'!F104))) -> Electronics | I103: =TRIM('01_Raw'!I104) -> Bank Transfer | J103: =TRIM('01_Raw'!J104) -> Processing | N103: =ISNUMBER('01_Raw'!D105) -> FALSE | P103: =LEFT('01_Raw'!D105, FIND("/",'01_Raw'!D105) - 1) -> #VALUE! | Q103: =IFERROR(RIGHT('01_Raw'!D105,4),"Invalid") | R103: =MID('01_Raw'!D105,FIND("/",'01_Raw'!D105) + 1,FIND("/",'01_Raw'!D105,FIND("/",'01_Raw'!D105)+1)-FIND("/",'01_Raw'!D105)-1) -> #VALUE! | S103: =IFERROR(DATE(Q103,P103,R103),"Invalid") -> Invalid | U103: =IFERROR(VALUE(SUBSTITUTE(SUBSTITUTE('01_Raw'!H105,"$",""), ".",",")),"Invalid") -> Invalid | V103: =IFERROR(VALUE('01_Raw'!G105), "Invalid") -> 0 | X103: =IF(ISBLANK('01_Raw'!H105),"Missing", IFERROR(VALUE(SUBSTITUTE(SUBSTITUTE('01_Raw'!H105,"$",""), ".",",")),"Invalid")) -> Missing | Y103: =IF(LEN(TRIM('01_Raw'!H105)) = 0, "Missing",IFERROR(VALUE(SUBSTITUTE(SUBSTITUTE('01_Raw'!H105,"$",""), ".",",")),"Invalid")) -> Missing | AA103: =IF(LEN(TRIM('01_Raw'!G105)) = 0, "Missing",IFERROR(VALUE(SUBSTITUTE(SUBSTITUTE('01_Raw'!G105,"$",""), ".",",")),"Invalid")) -> Missing | AC103: =COUNTIF($A$2:$A$103,A104) -> 0 | AE103: =COUNTIF(messy_ecommerce_sales_data__2[Order_ID],'01_Raw'!C105) -> 0

Sheet 03_Clean_Formulas.
A1: ID | B1: Customer_Name | C1: Order_ID | D1: Order_Date | E1: Product | F1: Category | G1: Quantity | H1: Price | I1: Payment_Method | J1: Status | K1: Total | M1: Category_Clean | N1: Date_Clean | O1: Quantity_Clean | P1: Price_Clean | Q1: Total_Clean | R1: Total_calc | S1: Check
A2: 100 | B2: Customer_100 | C2: ORD-41285 | D2: 11/22/2024 | E2: Blender | F2: Home | G2: 3 | H2: 38 | I2: Cash on Delivery | J2: Shipped | K2: 114 | M2: =IF(OR(F2="",F2="Nan"),"Missing",IF(PROPER(TRIM(messy_ecommerce_sales_data__27[[#This Row],[ Category]]))="Electronic","Electronics",PROPER(TRIM(messy_ecommerce_sales_data__27[[#This Row],[ Category]])))) -> Home | N2: 45618 | O2: =IF(LEN(TRIM(messy_ecommerce_sales_data__27[[#This Row],[Quantity]])) = 0, "Missing",IFERROR(VALUE(messy_ecommerce_sales_data__27[[#This Row],[Quantity]]),"Invalid")) -> 3 | P2: =IFERROR(VALUE(SUBSTITUTE(SUBSTITUTE(H2,"$",""), ".",",")),"Invalid") -> 38 | Q2: =IF(LEN(TRIM(messy_ecommerce_sales_data__27[[#This Row],[Total]])) = 0, "Missing",IFERROR(VALUE(SUBSTITUTE(SUBSTITUTE(messy_ecommerce_sales_data__27[[#This Row],[Total]],"$",""), ".",",")),"Invalid")) -> 114 | R2: =IFERROR(O2*P2, "Cannot Calculate") -> 114 | S2: =IF(AND(ISNUMBER(R2),ISNUMBER(Q2)),IF(ROUND(R2,2)=ROUND(Q2,2),"OK","Mismatch"),"No Data") -> OK
A3: 101 | B3: Customer_101 | C3: ORD-35783 | D3: 7/5/2025 | E3: Smartphone | F3: Electronics | G3: 2 | H3: abd | I3: PayPal | J3: Processing | M3: =IF(OR(F3="",F3="Nan"),"Missing",IF(PROPER(TRIM(messy_ecommerce_sales_data__27[[#This Row],[ Category]]))="Electronic","Electronics",PROPER(TRIM(messy_ecommerce_sales_data__27[[#This Row],[ Category]])))) -> Electronics | N3: 45843 | O3: =IF(LEN(TRIM(messy_ecommerce_sales_data__27[[#This Row],[Quantity]])) = 0, "Missing",IFERROR(VALUE(messy_ecommerce_sales_data__27[[#This Row],[Quantity]]),"Invalid")) -> 2 | P3: =IFERROR(VALUE(SUBSTITUTE(SUBSTITUTE(H3,"$",""), ".",",")),"Invalid") -> Invalid | Q3: =IF(LEN(TRIM(messy_ecommerce_sales_data__27[[#This Row],[Total]])) = 0, "Missing",IFERROR(VALUE(SUBSTITUTE(SUBSTITUTE(messy_ecommerce_sales_data__27[[#This Row],[Total]],"$",""), ".",",")),"Invalid")) -> Missing | R3: =IFERROR(O3*P3, "Cannot Calculate") -> Cannot Calculate | S3: =IF(AND(ISNUMBER(R3),ISNUMBER(Q3)),IF(ROUND(R3,2)=ROUND(Q3,2),"OK","Mismatch"),"No Data") -> No Data
A4: 102 | B4: Customer_102 | C4: ORD-84355 | D4: 12/23/2024 | E4: Tennis Racket | F4: Sports | G4: 1 | H4: 389.05 | I4: PayPal | J4: Delivered | K4: 389.05 | M4: =IF(OR(F4="",F4="Nan"),"Missing",IF(PROPER(TRIM(messy_ecommerce_sales_data__27[[#This Row],[ Category]]))="Electronic","Electronics",PROPER(TRIM(messy_ecommerce_sales_data__27[[#This Row],[ Category]])))) -> Sports | N4: 45649 | O4: =IF(LEN(TRIM(messy_ecommerce_sales_data__27[[#This Row],[Quantity]])) = 0, "Missing",IFERROR(VALUE(messy_ecommerce_sales_data__27[[#This Row],[Quantity]]),"Invalid")) -> 1 | P4: =IFERROR(VALUE(SUBSTITUTE(SUBSTITUTE(H4,"$",""), ".",",")),"Invalid") -> 389.05 | Q4: =IF(LEN(TRIM(messy_ecommerce_sales_data__27[[#This Row],[Total]])) = 0, "Missing",IFERROR(VALUE(SUBSTITUTE(SUBSTITUTE(messy_ecommerce_sales_data__27[[#This Row],[Total]],"$",""), ".",",")),"Invalid")) -> 389.05 | R4: =IFERROR(O4*P4, "Cannot Calculate") -> 389.05 | S4: =IF(AND(ISNUMBER(R4),ISNUMBER(Q4)),IF(ROUND(R4,2)=ROUND(Q4,2),"OK","Mismatch"),"No Data") -> OK
A5: 103 | B5: Customer_103 | C5: ORD-57811 | D5: 3/19/2025 | E5: Science | F5: Books | G5: 5 | H5: 233.92 | I5: PayPal | J5: Processing | K5: 1169.6 | M5: =IF(OR(F5="",F5="Nan"),"Missing",IF(PROPER(TRIM(messy_ecommerce_sales_data__27[[#This Row],[ Category]]))="Electronic","Electronics",PROPER(TRIM(messy_ecommerce_sales_data__27[[#This Row],[ Category]])))) -> Books | N5: 45735 | O5: =IF(LEN(TRIM(messy_ecommerce_sales_data__27[[#This Row],[Quantity]])) = 0, "Missing",IFERROR(VALUE(messy_ecommerce_sales_data__27[[#This Row],[Quantity]]),"Invalid")) -> 5 | P5: =IFERROR(VALUE(SUBSTITUTE(SUBSTITUTE(H5,"$",""), ".",",")),"Invalid") -> 233.92 | Q5: =IF(LEN(TRIM(messy_ecommerce_sales_data__27[[#This Row],[Total]])) = 0, "Missing",IFERROR(VALUE(SUBSTITUTE(SUBSTITUTE(messy_ecommerce_sales_data__27[[#This Row],[Total]],"$",""), ".",",")),"Invalid")) -> 1169.6 | R5: =IFERROR(O5*P5, "Cannot Calculate") -> 1169.6 | S5: =IF(AND(ISNUMBER(R5),ISNUMBER(Q5)),IF(ROUND(R5,2)=ROUND(Q5,2),"OK","Mismatch"),"No Data") -> OK
A6: 104 | B6: Customer_104 | C6: ORD-93614 | D6: 10/20/2025 | E6: Biography | F6: Books | G6: 1 | H6: 552.51 | I6: Cash on Delivery | J6: Processing | K6: 552.51 | M6: =IF(OR(F6="",F6="Nan"),"Missing",IF(PROPER(TRIM(messy_ecommerce_sales_data__27[[#This Row],[ Category]]))="Electronic","Electronics",PROPER(TRIM(messy_ecommerce_sales_data__27[[#This Row],[ Category]])))) -> Books | N6: 45950 | O6: =IF(LEN(TRIM(messy_ecommerce_sales_data__27[[#This Row],[Quantity]])) = 0, "Missing",IFERROR(VALUE(messy_ecommerce_sales_data__27[[#This Row],[Quantity]]),"Invalid")) -> 1 | P6: =IFERROR(VALUE(SUBSTITUTE(SUBSTITUTE(H6,"$",""), ".",",")),"Invalid") -> 552.51 | Q6: =IF(LEN(TRIM(messy_ecommerce_sales_data__27[[#This Row],[Total]])) = 0, "Missing",IFERROR(VALUE(SUBSTITUTE(SUBSTITUTE(messy_ecommerce_sales_data__27[[#This Row],[Total]],"$",""), ".",",")),"Invalid")) -> 552.51 | R6: =IFERROR(O6*P6, "Cannot Calculate") -> 552.51 | S6: =IF(AND(ISNUMBER(R6),ISNUMBER(Q6)),IF(ROUND(R6,2)=ROUND(Q6,2),"OK","Mismatch"),"No Data") -> OK
A7: 105 | B7: Customer_105 | C7: ORD-22442 | D7: 11/20/2024 | E7: Tennis Racket | F7: Sports | G7: 3 | H7: 122.06 | I7: Cash on Delivery | J7: Cancelled | K7: 366.18 | M7: =IF(OR(F7="",F7="Nan"),"Missing",IF(PROPER(TRIM(messy_ecommerce_sales_data__27[[#This Row],[ Category]]))="Electronic","Electronics",PROPER(TRIM(messy_ecommerce_sales_data__27[[#This Row],[ Category]])))) -> Sports | N7: 45616 | O7: =IF(LEN(TRIM(messy_ecommerce_sales_data__27[[#This Row],[Quantity]])) = 0, "Missing",IFERROR(VALUE(messy_ecommerce_sales_data__27[[#This Row],[Quantity]]),"Invalid")) -> 3 | P7: =IFERROR(VALUE(SUBSTITUTE(SUBSTITUTE(H7,"$",""), ".",",")),"Invalid") -> 122.06 | Q7: =IF(LEN(TRIM(messy_ecommerce_sales_data__27[[#This Row],[Total]])) = 0, "Missing",IFERROR(VALUE(SUBSTITUTE(SUBSTITUTE(messy_ecommerce_sales_data__27[[#This Row],[Total]],"$",""), ".",",")),"Invalid")) -> 366.18 | R7: =IFERROR(O7*P7, "Cannot Calculate") -> 366.18 | S7: =IF(AND(ISNUMBER(R7),ISNUMBER(Q7)),IF(ROUND(R7,2)=ROUND(Q7,2),"OK","Mismatch"),"No Data") -> OK
A8: 106 | B8: Customer_106 | C8: ORD-25885 | D8: 2/2/2025 | E8: Blender | F8: Home | H8: 978.63 | I8: Bank Transfer | J8: Processing | M8: =IF(OR(F8="",F8="Nan"),"Missing",IF(PROPER(TRIM(messy_ecommerce_sales_data__27[[#This Row],[ Category]]))="Electronic","Electronics",PROPER(TRIM(messy_ecommerce_sales_data__27[[#This Row],[ Category]])))) -> Home | N8: 45690 | O8: =IF(LEN(TRIM(messy_ecommerce_sales_data__27[[#This Row],[Quantity]])) = 0, "Missing",IFERROR(VALUE(messy_ecommerce_sales_data__27[[#This Row],[Quantity]]),"Invalid")) -> Missing | P8: =IFERROR(VALUE(SUBSTITUTE(SUBSTITUTE(H8,"$",""), ".",",")),"Invalid") -> 978.63 | Q8: =IF(LEN(TRIM(messy_ecommerce_sales_data__27[[#This Row],[Total]])) = 0, "Missing",IFERROR(VALUE(SUBSTITUTE(SUBSTITUTE(messy_ecommerce_sales_data__27[[#This Row],[Total]],"$",""), ".",",")),"Invalid")) -> Missing | R8: =IFERROR(O8*P8, "Cannot Calculate") -> Cannot Calculate | S8: =IF(AND(ISNUMBER(R8),ISNUMBER(Q8)),IF(ROUND(R8,2)=ROUND(Q8,2),"OK","Mismatch"),"No Data") -> No Data
A9: 107 | B9: Customer_107 | C9: ORD-89122 | D9: 1/3/2025 | E9: Biography | F9: Books | G9: 5 | H9: 587.68 | I9: PayPal | J9: Returned | K9: 2938.4 | M9: =IF(OR(F9="",F9="Nan"),"Missing",IF(PROPER(TRIM(messy_ecommerce_sales_data__27[[#This Row],[ Category]]))="Electronic","Electronics",PROPER(TRIM(messy_ecommerce_sales_data__27[[#This Row],[ Category]])))) -> Books | N9: 45660 | O9: =IF(LEN(TRIM(messy_ecommerce_sales_data__27[[#This Row],[Quantity]])) = 0, "Missing",IFERROR(VALUE(messy_ecommerce_sales_data__27[[#This Row],[Quantity]]),"Invalid")) -> 5 | P9: =IFERROR(VALUE(SUBSTITUTE(SUBSTITUTE(H9,"$",""), ".",",")),"Invalid") -> 587.68 | Q9: =IF(LEN(TRIM(messy_ecommerce_sales_data__27[[#This Row],[Total]])) = 0, "Missing",IFERROR(VALUE(SUBSTITUTE(SUBSTITUTE(messy_ecommerce_sales_data__27[[#This Row],[Total]],"$",""), ".",",")),"Invalid")) -> 2938.4 | R9: =IFERROR(O9*P9, "Cannot Calculate") -> 2938.4 | S9: =IF(AND(ISNUMBER(R9),ISNUMBER(Q9)),IF(ROUND(R9,2)=ROUND(Q9,2),"OK","Mismatch"),"No Data") -> OK
A10: 108 | B10: Customer_108 | C10: ORD-64400 | D10: 10/23/2025 | E10: Science | F10: Books | G10: 1 | H10: 600.29 | I10: Cash on Delivery | J10: Processing | K10: 600.29 | M10: =IF(OR(F10="",F10="Nan"),"Missing",IF(PROPER(TRIM(messy_ecommerce_sales_data__27[[#This Row],[ Category]]))="Electronic","Electronics",PROPER(TRIM(messy_ecommerce_sales_data__27[[#This Row],[ Category]])))) -> Books | N10: 45953 | O10: =IF(LEN(TRIM(messy_ecommerce_sales_data__27[[#This Row],[Quantity]])) = 0, "Missing",IFERROR(VALUE(messy_ecommerce_sales_data__27[[#This Row],[Quantity]]),"Invalid")) -> 1 | P10: =IFERROR(VALUE(SUBSTITUTE(SUBSTITUTE(H10,"$",""), ".",",")),"Invalid") -> 600.29 | Q10: =IF(LEN(TRIM(messy_ecommerce_sales_data__27[[#This Row],[Total]])) = 0, "Missing",IFERROR(VALUE(SUBSTITUTE(SUBSTITUTE(messy_ecommerce_sales_data__27[[#This Row],[Total]],"$",""), ".",",")),"Invalid")) -> 600.29 | R10: =IFERROR(O10*P10, "Cannot Calculate") -> 600.29 | S10: =IF(AND(ISNUMBER(R10),ISNUMBER(Q10)),IF(ROUND(R10,2)=ROUND(Q10,2),"OK","Mismatch"),"No Data") -> OK
A11: 109 | B11: Customer_109 | C11: ORD-18512 | D11: 5/3/2025 | E11: Tennis Racket | F11: Sports | G11: 5 | H11: 168.34 | I11: Credit Card | J11: Shipped | K11: 841.7 | M11: =IF(OR(F11="",F11="Nan"),"Missing",IF(PROPER(TRIM(messy_ecommerce_sales_data__27[[#This Row],[ Category]]))="Electronic","Electronics",PROPER(TRIM(messy_ecommerce_sales_data__27[[#This Row],[ Category]])))) -> Sports | N11: 45780 | O11: =IF(LEN(TRIM(messy_ecommerce_sales_data__27[[#This Row],[Quantity]])) = 0, "Missing",IFERROR(VALUE(messy_ecommerce_sales_data__27[[#This Row],[Quantity]]),"Invalid")) -> 5 | P11: =IFERROR(VALUE(SUBSTITUTE(SUBSTITUTE(H11,"$",""), ".",",")),"Invalid") -> 168.34 | Q11: =IF(LEN(TRIM(messy_ecommerce_sales_data__27[[#This Row],[Total]])) = 0, "Missing",IFERROR(VALUE(SUBSTITUTE(SUBSTITUTE(messy_ecommerce_sales_data__27[[#This Row],[Total]],"$",""), ".",",")),"Invalid")) -> 841.7 | R11: =IFERROR(O11*P11, "Cannot Calculate") -> 841.7 | S11: =IF(AND(ISNUMBER(R11),ISNUMBER(Q11)),IF(ROUND(R11,2)=ROUND(Q11,2),"OK","Mismatch"),"No Data") -> OK
A12: 110 | B12: Customer_110 | C12: ORD-61020 | D12: 9/26/2025 | E12: Basketball | F12: sports | G12: 5 | H12: four hundred | I12: Cash on Delivery | J12: Cancelled | M12: =IF(OR(F12="",F12="Nan"),"Missing",IF(PROPER(TRIM(messy_ecommerce_sales_data__27[[#This Row],[ Category]]))="Electronic","Electronics",PROPER(TRIM(messy_ecommerce_sales_data__27[[#This Row],[ Category]])))) -> Sports | N12: 45926 | O12: =IF(LEN(TRIM(messy_ecommerce_sales_data__27[[#This Row],[Quantity]])) = 0, "Missing",IFERROR(VALUE(messy_ecommerce_sales_data__27[[#This Row],[Quantity]]),"Invalid")) -> 5 | P12: =IFERROR(VALUE(SUBSTITUTE(SUBSTITUTE(H12,"$",""), ".",",")),"Invalid") -> Invalid | Q12: =IF(LEN(TRIM(messy_ecommerce_sales_data__27[[#This Row],[Total]])) = 0, "Missing",IFERROR(VALUE(SUBSTITUTE(SUBSTITUTE(messy_ecommerce_sales_data__27[[#This Row],[Total]],"$",""), ".",",")),"Invalid")) -> Missing | R12: =IFERROR(O12*P12, "Cannot Calculate") -> Cannot Calculate | S12: =IF(AND(ISNUMBER(R12),ISNUMBER(Q12)),IF(ROUND(R12,2)=ROUND(Q12,2),"OK","Mismatch"),"No Data") -> No Data
A13: 111 | B13: Customer_111 | C13: ORD-72349 | D13: 10/22/2025 | E13: Comics | F13: Books | G13: 2 | H13: 865.77 | I13: Credit Card | J13: Returned | K13: 1731.54 | M13: =IF(OR(F13="",F13="Nan"),"Missing",IF(PROPER(TRIM(messy_ecommerce_sales_data__27[[#This Row],[ Category]]))="Electronic","Electronics",PROPER(TRIM(messy_ecommerce_sales_data__27[[#This Row],[ Category]])))) -> Books | N13: 45952 | O13: =IF(LEN(TRIM(messy_ecommerce_sales_data__27[[#This Row],[Quantity]])) = 0, "Missing",IFERROR(VALUE(messy_ecommerce_sales_data__27[[#This Row],[Quantity]]),"Invalid")) -> 2 | P13: =IFERROR(VALUE(SUBSTITUTE(SUBSTITUTE(H13,"$",""), ".",",")),"Invalid") -> 865.77 | Q13: =IF(LEN(TRIM(messy_ecommerce_sales_data__27[[#This Row],[Total]])) = 0, "Missing",IFERROR(VALUE(SUBSTITUTE(SUBSTITUTE(messy_ecommerce_sales_data__27[[#This Row],[Total]],"$",""), ".",",")),"Invalid")) -> 1731.54 | R13: =IFERROR(O13*P13, "Cannot Calculate") -> 1731.54 | S13: =IF(AND(ISNUMBER(R13),ISNUMBER(Q13)),IF(ROUND(R13,2)=ROUND(Q13,2),"OK","Mismatch"),"No Data") -> OK
A14: 112 | B14: Customer_112 | C14: ORD-80867 | D14: 3/2/2025 | E14: Shoes | F14: Clothing | G14: 4 | H14: 752.13 | I14: Bank Transfer | J14: Delivered | K14: 3008.52 | M14: =IF(OR(F14="",F14="Nan"),"Missing",IF(PROPER(TRIM(messy_ecommerce_sales_data__27[[#This Row],[ Category]]))="Electronic","Electronics",PROPER(TRIM(messy_ecommerce_sales_data__27[[#This Row],[ Category]])))) -> Clothing | N14: 45718 | O14: =IF(LEN(TRIM(messy_ecommerce_sales_data__27[[#This Row],[Quantity]])) = 0, "Missing",IFERROR(VALUE(messy_ecommerce_sales_data__27[[#This Row],[Quantity]]),"Invalid")) -> 4 | P14: =IFERROR(VALUE(SUBSTITUTE(SUBSTITUTE(H14,"$",""), ".",",")),"Invalid") -> 752.13 | Q14: =IF(LEN(TRIM(messy_ecommerce_sales_data__27[[#This Row],[Total]])) = 0, "Missing",IFERROR(VALUE(SUBSTITUTE(SUBSTITUTE(messy_ecommerce_sales_data__27[[#This Row],[Total]],"$",""), ".",",")),"Invalid")) -> 3008.52 | R14: =IFERROR(O14*P14, "Cannot Calculate") -> 3008.52 | S14: =IF(AND(ISNUMBER(R14),ISNUMBER(Q14)),IF(ROUND(R14,2)=ROUND(Q14,2),"OK","Mismatch"),"No Data") -> OK
A15: 113 | B15: Customer_113 | C15: ORD-23994 | D15: 7/24/2025 | E15: Fiction | F15: Books | G15: 1 | H15: 411.81 | I15: Credit Card | J15: Processing | K15: 411.81 | M15: =IF(OR(F15="",F15="Nan"),"Missing",IF(PROPER(TRIM(messy_ecommerce_sales_data__27[[#This Row],[ Category]]))="Electronic","Electronics",PROPER(TRIM(messy_ecommerce_sales_data__27[[#This Row],[ Category]])))) -> Books | N15: 45862 | O15: =IF(LEN(TRIM(messy_ecommerce_sales_data__27[[#This Row],[Quantity]])) = 0, "Missing",IFERROR(VALUE(messy_ecommerce_sales_data__27[[#This Row],[Quantity]]),"Invalid")) -> 1 | P15: =IFERROR(VALUE(SUBSTITUTE(SUBSTITUTE(H15,"$",""), ".",",")),"Invalid") -> 411.81 | Q15: =IF(LEN(TRIM(messy_ecommerce_sales_data__27[[#This Row],[Total]])) = 0, "Missing",IFERROR(VALUE(SUBSTITUTE(SUBSTITUTE(messy_ecommerce_sales_data__27[[#This Row],[Total]],"$",""), ".",",")),"Invalid")) -> 411.81 | R15: =IFERROR(O15*P15, "Cannot Calculate") -> 411.81 | S15: =IF(AND(ISNUMBER(R15),ISNUMBER(Q15)),IF(ROUND(R15,2)=ROUND(Q15,2),"OK","Mismatch"),"No Data") -> OK
A16: 114 | B16: Customer_114 | C16: ORD-77417 | D16: Jan 5 2023 | E16: Smartphone | F16: Electronics | G16: 2 | H16: 413.13 | I16: Cash on Delivery | J16: Shipped | K16: 826.26 | M16: =IF(OR(F16="",F16="Nan"),"Missing",IF(PROPER(TRIM(messy_ecommerce_sales_data__27[[#This Row],[ Category]]))="Electronic","Electronics",PROPER(TRIM(messy_ecommerce_sales_data__27[[#This Row],[ Category]])))) -> Electronics | N16: Invalid | O16: =IF(LEN(TRIM(messy_ecommerce_sales_data__27[[#This Row],[Quantity]])) = 0, "Missing",IFERROR(VALUE(messy_ecommerce_sales_data__27[[#This Row],[Quantity]]),"Invalid")) -> 2 | P16: =IFERROR(VALUE(SUBSTITUTE(SUBSTITUTE(H16,"$",""), ".",",")),"Invalid") -> 413.13 | Q16: =IF(LEN(TRIM(messy_ecommerce_sales_data__27[[#This Row],[Total]])) = 0, "Missing",IFERROR(VALUE(SUBSTITUTE(SUBSTITUTE(messy_ecommerce_sales_data__27[[#This Row],[Total]],"$",""), ".",",")),"Invalid")) -> 826.26 | R16: =IFERROR(O16*P16, "Cannot Calculate") -> 826.26 | S16: =IF(AND(ISNUMBER(R16),ISNUMBER(Q16)),IF(ROUND(R16,2)=ROUND(Q16,2),"OK","Mismatch"),"No Data") -> OK
A17: 115 | B17: Customer_115 | C17: ORD-72778 | D17: 1/10/2025 | E17: Fiction | F17: Books | G17: 2 | H17: 796.84 | I17: Cash on Delivery | J17: Returned | K17: 1115.576 | M17: =IF(OR(F17="",F17="Nan"),"Missing",IF(PROPER(TRIM(messy_ecommerce_sales_data__27[[#This Row],[ Category]]))="Electronic","Electronics",PROPER(TRIM(messy_ecommerce_sales_data__27[[#This Row],[ Category]])))) -> Books | N17: 45667 | O17: =IF(LEN(TRIM(messy_ecommerce_sales_data__27[[#This Row],[Quantity]])) = 0, "Missing",IFERROR(VALUE(messy_ecommerce_sales_data__27[[#This Row],[Quantity]]),"Invalid")) -> 2 | P17: =IFERROR(VALUE(SUBSTITUTE(SUBSTITUTE(H17,"$",""), ".",",")),"Invalid") -> 796.84 | Q17: =IF(LEN(TRIM(messy_ecommerce_sales_data__27[[#This Row],[Total]])) = 0, "Missing",IFERROR(VALUE(SUBSTITUTE(SUBSTITUTE(messy_ecommerce_sales_data__27[[#This Row],[Total]],"$",""), ".",",")),"Invalid")) -> 1115.576 | R17: =IFERROR(O17*P17, "Cannot Calculate") -> 1593.68 | S17: =IF(AND(ISNUMBER(R17),ISNUMBER(Q17)),IF(ROUND(R17,2)=ROUND(Q17,2),"OK","Mismatch"),"No Data") -> Mismatch
A18: 116 | B18: Customer_116 | C18: ORD-63660 | D18: 10/30/2025 | E18: Microwave | F18: Home | G18: 4 | I18: Cash on Delivery | J18: Processing | M18: =IF(OR(F18="",F18="Nan"),"Missing",IF(PROPER(TRIM(messy_ecommerce_sales_data__27[[#This Row],[ Category]]))="Electronic","Electronics",PROPER(TRIM(messy_ecommerce_sales_data__27[[#This Row],[ Category]])))) -> Home | N18: 45960 | O18: =IF(LEN(TRIM(messy_ecommerce_sales_data__27[[#This Row],[Quantity]])) = 0, "Missing",IFERROR(VALUE(messy_ecommerce_sales_data__27[[#This Row],[Quantity]]),"Invalid")) -> 4 | P18: =IFERROR(VALUE(SUBSTITUTE(SUBSTITUTE(H18,"$",""), ".",",")),"Invalid") -> Invalid | Q18: =IF(LEN(TRIM(messy_ecommerce_sales_data__27[[#This Row],[Total]])) = 0, "Missing",IFERROR(VALUE(SUBSTITUTE(SUBSTITUTE(messy_ecommerce_sales_data__27[[#This Row],[Total]],"$",""), ".",",")),"Invalid")) -> Missing | R18: =IFERROR(O18*P18, "Cannot Calculate") -> Cannot Calculate | S18: =IF(AND(ISNUMBER(R18),ISNUMBER(Q18)),IF(ROUND(R18,2)=ROUND(Q18,2),"OK","Mismatch"),"No Data") -> No Data
A19: 117 | B19: Customer_117 | C19: ORD-72751 | D19: 2/12/2025 | E19: Blender | F19: electronic | G19: -2 | H19: 10000 | I19: Cash on Delivery | J19: Processing | K19: -20000 | M19: =IF(OR(F19="",F19="Nan"),"Missing",IF(PROPER(TRIM(messy_ecommerce_sales_data__27[[#This Row],[ Category]]))="Electronic","Electronics",PROPER(TRIM(messy_ecommerce_sales_data__27[[#This Row],[ Category]])))) -> Electronics | N19: 45700 | O19: =IF(LEN(TRIM(messy_ecommerce_sales_data__27[[#This Row],[Quantity]])) = 0, "Missing",IFERROR(VALUE(messy_ecommerce_sales_data__27[[#This Row],[Quantity]]),"Invalid")) -> -2 | P19: =IFERROR(VALUE(SUBSTITUTE(SUBSTITUTE(H19,"$",""), ".",",")),"Invalid") -> 10000 | Q19: =IF(LEN(TRIM(messy_ecommerce_sales_data__27[[#This Row],[Total]])) = 0, "Missing",IFERROR(VALUE(SUBSTITUTE(SUBSTITUTE(messy_ecommerce_sales_data__27[[#This Row],[Total]],"$",""), ".",",")),"Invalid")) -> -20000 | R19: =IFERROR(O19*P19, "Cannot Calculate") -> -20000 | S19: =IF(AND(ISNUMBER(R19),ISNUMBER(Q19)),IF(ROUND(R19,2)=ROUND(Q19,2),"OK","Mismatch"),"No Data") -> OK
A20: 118 | B20: Customer_118 | C20: ORD-96061 | D20: 5/31/2025 | E20: Science | F20: Books | G20: 5 | H20: 247.82 | I20: PayPal | J20: Processing | K20: 1239.1 | M20: =IF(OR(F20="",F20="Nan"),"Missing",IF(PROPER(TRIM(messy_ecommerce_sales_data__27[[#This Row],[ Category]]))="Electronic","Electronics",PROPER(TRIM(messy_ecommerce_sales_data__27[[#This Row],[ Category]])))) -> Books | N20: 45808 | O20: =IF(LEN(TRIM(messy_ecommerce_sales_data__27[[#This Row],[Quantity]])) = 0, "Missing",IFERROR(VALUE(messy_ecommerce_sales_data__27[[#This Row],[Quantity]]),"Invalid")) -> 5 | P20: =IFERROR(VALUE(SUBSTITUTE(SUBSTITUTE(H20,"$",""), ".",",")),"Invalid") -> 247.82 | Q20: =IF(LEN(TRIM(messy_ecommerce_sales_data__27[[#This Row],[Total]])) = 0, "Missing",IFERROR(VALUE(SUBSTITUTE(SUBSTITUTE(messy_ecommerce_sales_data__27[[#This Row],[Total]],"$",""), ".",",")),"Invalid")) -> 1239.1 | R20: =IFERROR(O20*P20, "Cannot Calculate") -> 1239.1 | S20: =IF(AND(ISNUMBER(R20),ISNUMBER(Q20)),IF(ROUND(R20,2)=ROUND(Q20,2),"OK","Mismatch"),"No Data") -> OK
A21: 119 | B21: Customer_119 | C21: ORD-76016 | D21: 12/19/2024 | E21: Basketball | F21: Sports | G21: 4 | H21: 438.19 | I21: Cash on Delivery | J21: Processing | K21: 1752.76 | M21: =IF(OR(F21="",F21="Nan"),"Missing",IF(PROPER(TRIM(messy_ecommerce_sales_data__27[[#This Row],[ Category]]))="Electronic","Electronics",PROPER(TRIM(messy_ecommerce_sales_data__27[[#This Row],[ Category]])))) -> Sports | N21: 45645 | O21: =IF(LEN(TRIM(messy_ecommerce_sales_data__27[[#This Row],[Quantity]])) = 0, "Missing",IFERROR(VALUE(messy_ecommerce_sales_data__27[[#This Row],[Quantity]]),"Invalid")) -> 4 | P21: =IFERROR(VALUE(SUBSTITUTE(SUBSTITUTE(H21,"$",""), ".",",")),"Invalid") -> 438.19 | Q21: =IF(LEN(TRIM(messy_ecommerce_sales_data__27[[#This Row],[Total]])) = 0, "Missing",IFERROR(VALUE(SUBSTITUTE(SUBSTITUTE(messy_ecommerce_sales_data__27[[#This Row],[Total]],"$",""), ".",",")),"Invalid")) -> 1752.76 | R21: =IFERROR(O21*P21, "Cannot Calculate") -> 1752.76 | S21: =IF(AND(ISNUMBER(R21),ISNUMBER(Q21)),IF(ROUND(R21,2)=ROUND(Q21,2),"OK","Mismatch"),"No Data") -> OK
A22: 120 | B22: Customer_120 | C22: ORD-14659 | D22: 6/13/2025 | E22: Yoga Mat | F22: ELECTRONICS | G22: 5 | H22: 300$ | I22: Credit Card | J22: Cancelled | M22: =IF(OR(F22="",F22="Nan"),"Missing",IF(PROPER(TRIM(messy_ecommerce_sales_data__27[[#This Row],[ Category]]))="Electronic","Electronics",PROPER(TRIM(messy_ecommerce_sales_data__27[[#This Row],[ Category]])))) -> Electronics | N22: 45821 | O22: =IF(LEN(TRIM(messy_ecommerce_sales_data__27[[#This Row],[Quantity]])) = 0, "Missing",IFERROR(VALUE(messy_ecommerce_sales_data__27[[#This Row],[Quantity]]),"Invalid")) -> 5 | P22: =IFERROR(VALUE(SUBSTITUTE(SUBSTITUTE(H22,"$",""), ".",",")),"Invalid") -> 300 | Q22: =IF(LEN(TRIM(messy_ecommerce_sales_data__27[[#This Row],[Total]])) = 0, "Missing",IFERROR(VALUE(SUBSTITUTE(SUBSTITUTE(messy_ecommerce_sales_data__27[[#This Row],[Total]],"$",""), ".",",")),"Invalid")) -> Missing | R22: =IFERROR(O22*P22, "Cannot Calculate") -> 1500 | S22: =IF(AND(ISNUMBER(R22),ISNUMBER(Q22)),IF(ROUND(R22,2)=ROUND(Q22,2),"OK","Mismatch"),"No Data") -> No Data
A23: 121 | B23: Customer_121 | C23: ORD-80067 | D23: 10/11/2025 | E23: Basketball | F23: Sports | G23: 4 | H23: 523.01 | I23: Credit Card | J23: Delivered | K23: 2092.04 | M23: =IF(OR(F23="",F23="Nan"),"Missing",IF(PROPER(TRIM(messy_ecommerce_sales_data__27[[#This Row],[ Category]]))="Electronic","Electronics",PROPER(TRIM(messy_ecommerce_sales_data__27[[#This Row],[ Category]])))) -> Sports | N23: 45941 | O23: =IF(LEN(TRIM(messy_ecommerce_sales_data__27[[#This Row],[Quantity]])) = 0, "Missing",IFERROR(VALUE(messy_ecommerce_sales_data__27[[#This Row],[Quantity]]),"Invalid")) -> 4 | P23: =IFERROR(VALUE(SUBSTITUTE(SUBSTITUTE(H23,"$",""), ".",",")),"Invalid") -> 523.01 | Q23: =IF(LEN(TRIM(messy_ecommerce_sales_data__27[[#This Row],[Total]])) = 0, "Missing",IFERROR(VALUE(SUBSTITUTE(SUBSTITUTE(messy_ecommerce_sales_data__27[[#This Row],[Total]],"$",""), ".",",")),"Invalid")) -> 2092.04 | R23: =IFERROR(O23*P23, "Cannot Calculate") -> 2092.04 | S23: =IF(AND(ISNUMBER(R23),ISNUMBER(Q23)),IF(ROUND(R23,2)=ROUND(Q23,2),"OK","Mismatch"),"No Data") -> OK
A24: 122 | B24: Customer_122 | C24: ORD-21443 | D24: 5/16/2025 | E24: Microwave | F24: Home | G24: 2 | H24: 556.93 | I24: PayPal | J24: Shipped | K24: 1113.86 | M24: =IF(OR(F24="",F24="Nan"),"Missing",IF(PROPER(TRIM(messy_ecommerce_sales_data__27[[#This Row],[ Category]]))="Electronic","Electronics",PROPER(TRIM(messy_ecommerce_sales_data__27[[#This Row],[ Category]])))) -> Home | N24: 45793 | O24: =IF(LEN(TRIM(messy_ecommerce_sales_data__27[[#This Row],[Quantity]])) = 0, "Missing",IFERROR(VALUE(messy_ecommerce_sales_data__27[[#This Row],[Quantity]]),"Invalid")) -> 2 | P24: =IFERROR(VALUE(SUBSTITUTE(SUBSTITUTE(H24,"$",""), ".",",")),"Invalid") -> 556.93 | Q24: =IF(LEN(TRIM(messy_ecommerce_sales_data__27[[#This Row],[Total]])) = 0, "Missing",IFERROR(VALUE(SUBSTITUTE(SUBSTITUTE(messy_ecommerce_sales_data__27[[#This Row],[Total]],"$",""), ".",",")),"Invalid")) -> 1113.86 | R24: =IFERROR(O24*P24, "Cannot Calculate") -> 1113.86 | S24: =IF(AND(ISNUMBER(R24),ISNUMBER(Q24)),IF(ROUND(R24,2)=ROUND(Q24,2),"OK","Mismatch"),"No Data") -> OK
A25: 123 | B25: Customer_123 | C25: ORD-11314 | D25: 10/6/2025 | E25: Vacuum | F25: electronic | G25: 3 | H25: 615.91 | I25: Cash on Delivery | J25: Cancelled | K25: 1847.73 | M25: =IF(OR(F25="",F25="Nan"),"Missing",IF(PROPER(TRIM(messy_ecommerce_sales_data__27[[#This Row],[ Category]]))="Electronic","Electronics",PROPER(TRIM(messy_ecommerce_sales_data__27[[#This Row],[ Category]])))) -> Electronics | N25: 45936 | O25: =IF(LEN(TRIM(messy_ecommerce_sales_data__27[[#This Row],[Quantity]])) = 0, "Missing",IFERROR(VALUE(messy_ecommerce_sales_data__27[[#This Row],[Quantity]]),"Invalid")) -> 3 | P25: =IFERROR(VALUE(SUBSTITUTE(SUBSTITUTE(H25,"$",""), ".",",")),"Invalid") -> 615.91 | Q25: =IF(LEN(TRIM(messy_ecommerce_sales_data__27[[#This Row],[Total]])) = 0, "Missing",IFERROR(VALUE(SUBSTITUTE(SUBSTITUTE(messy_ecommerce_sales_data__27[[#This Row],[Total]],"$",""), ".",",")),"Invalid")) -> 1847.73 | R25: =IFERROR(O25*P25, "Cannot Calculate") -> 1847.73 | S25: =IF(AND(ISNUMBER(R25),ISNUMBER(Q25)),IF(ROUND(R25,2)=ROUND(Q25,2),"OK","Mismatch"),"No Data") -> OK
A26: 124 | B26: Customer_124 | C26: ORD-46136 | D26: 5/31/2025 | E26: Comics | F26: Books | G26: 5 | I26: PayPal | J26: Cancelled | M26: =IF(OR(F26="",F26="Nan"),"Missing",IF(PROPER(TRIM(messy_ecommerce_sales_data__27[[#This Row],[ Category]]))="Electronic","Electronics",PROPER(TRIM(messy_ecommerce_sales_data__27[[#This Row],[ Category]])))) -> Books | N26: 45808 | O26: =IF(LEN(TRIM(messy_ecommerce_sales_data__27[[#This Row],[Quantity]])) = 0, "Missing",IFERROR(VALUE(messy_ecommerce_sales_data__27[[#This Row],[Quantity]]),"Invalid")) -> 5 | P26: =IFERROR(VALUE(SUBSTITUTE(SUBSTITUTE(H26,"$",""), ".",",")),"Invalid") -> Invalid | Q26: =IF(LEN(TRIM(messy_ecommerce_sales_data__27[[#This Row],[Total]])) = 0, "Missing",IFERROR(VALUE(SUBSTITUTE(SUBSTITUTE(messy_ecommerce_sales_data__27[[#This Row],[Total]],"$",""), ".",",")),"Invalid")) -> Missing | R26: =IFERROR(O26*P26, "Cannot Calculate") -> Cannot Calculate | S26: =IF(AND(ISNUMBER(R26),ISNUMBER(Q26)),IF(ROUND(R26,2)=ROUND(Q26,2),"OK","Mismatch"),"No Data") -> No Data
A27: 125 | B27: Customer_125 | C27: ORD-23202 | D27: 2/9/2025 | E27: Comics | F27: Books | G27: 4 | H27: 765.69 | I27: PayPal | J27: Shipped | K27: 3062.76 | M27: =IF(OR(F27="",F27="Nan"),"Missing",IF(PROPER(TRIM(messy_ecommerce_sales_data__27[[#This Row],[ Category]]))="Electronic","Electronics",PROPER(TRIM(messy_ecommerce_sales_data__27[[#This Row],[ Category]])))) -> Books | N27: 45697 | O27: =IF(LEN(TRIM(messy_ecommerce_sales_data__27[[#This Row],[Quantity]])) = 0, "Missing",IFERROR(VALUE(messy_ecommerce_sales_data__27[[#This Row],[Quantity]]),"Invalid")) -> 4 | P27: =IFERROR(VALUE(SUBSTITUTE(SUBSTITUTE(H27,"$",""), ".",",")),"Invalid") -> 765.69 | Q27: =IF(LEN(TRIM(messy_ecommerce_sales_data__27[[#This Row],[Total]])) = 0, "Missing",IFERROR(VALUE(SUBSTITUTE(SUBSTITUTE(messy_ecommerce_sales_data__27[[#This Row],[Total]],"$",""), ".",",")),"Invalid")) -> 3062.76 | R27: =IFERROR(O27*P27, "Cannot Calculate") -> 3062.76 | S27: =IF(AND(ISNUMBER(R27),ISNUMBER(Q27)),IF(ROUND(R27,2)=ROUND(Q27,2),"OK","Mismatch"),"No Data") -> OK
A28: 126 | B28: Customer_126 | C28: ORD-11261 | D28: 5/18/2025 | E28: Shoes | F28: Clothing | G28: 4 | H28: 836.8 | I28: Bank Transfer | J28: Cancelled | K28: 3347.2 | M28: =IF(OR(F28="",F28="Nan"),"Missing",IF(PROPER(TRIM(messy_ecommerce_sales_data__27[[#This Row],[ Category]]))="Electronic","Electronics",PROPER(TRIM(messy_ecommerce_sales_data__27[[#This Row],[ Category]])))) -> Clothing | N28: 45795 | O28: =IF(LEN(TRIM(messy_ecommerce_sales_data__27[[#This Row],[Quantity]])) = 0, "Missing",IFERROR(VALUE(messy_ecommerce_sales_data__27[[#This Row],[Quantity]]),"Invalid")) -> 4 | P28: =IFERROR(VALUE(SUBSTITUTE(SUBSTITUTE(H28,"$",""), ".",",")),"Invalid") -> 836.8 | Q28: =IF(LEN(TRIM(messy_ecommerce_sales_data__27[[#This Row],[Total]])) = 0, "Missing",IFERROR(VALUE(SUBSTITUTE(SUBSTITUTE(messy_ecommerce_sales_data__27[[#This Row],[Total]],"$",""), ".",",")),"Invalid")) -> 3347.2 | R28: =IFERROR(O28*P28, "Cannot Calculate") -> 3347.2 | S28: =IF(AND(ISNUMBER(R28),ISNUMBER(Q28)),IF(ROUND(R28,2)=ROUND(Q28,2),"OK","Mismatch"),"No Data") -> OK
A29: 127 | B29: Customer_127 | C29: ORD-65482 | D29: 5/12/2025 | E29: Blender | F29: Home | G29: 5 | H29: 336.02 | I29: Bank Transfer | J29: Returned | K29: 1680.1 | M29: =IF(OR(F29="",F29="Nan"),"Missing",IF(PROPER(TRIM(messy_ecommerce_sales_data__27[[#This Row],[ Category]]))="Electronic","Electronics",PROPER(TRIM(messy_ecommerce_sales_data__27[[#This Row],[ Category]])))) -> Home | N29: 45789 | O29: =IF(LEN(TRIM(messy_ecommerce_sales_data__27[[#This Row],[Quantity]])) = 0, "Missing",IFERROR(VALUE(messy_ecommerce_sales_data__27[[#This Row],[Quantity]]),"Invalid")) -> 5 | P29: =IFERROR(VALUE(SUBSTITUTE(SUBSTITUTE(H29,"$",""), ".",",")),"Invalid") -> 336.02 | Q29: =IF(LEN(TRIM(messy_ecommerce_sales_data__27[[#This Row],[Total]])) = 0, "Missing",IFERROR(VALUE(SUBSTITUTE(SUBSTITUTE(messy_ecommerce_sales_data__27[[#This Row],[Total]],"$",""), ".",",")),"Invalid")) -> 1680.1 | R29: =IFERROR(O29*P29, "Cannot Calculate") -> 1680.1 | S29: =IF(AND(ISNUMBER(R29),ISNUMBER(Q29)),IF(ROUND(R29,2)=ROUND(Q29,2),"OK","Mismatch"),"No Data") -> OK
A30: 128 | B30: Customer_128 | C30: ORD-12270 | D30: 11/10/2024 | E30: Lamp | F30: electronics | G30: 3 | H30: 898.69 | I30: Bank Transfer | J30: Delivered | K30: 2696.07 | M30: =IF(OR(F30="",F30="Nan"),"Missing",IF(PROPER(TRIM(messy_ecommerce_sales_data__27[[#This Row],[ Category]]))="Electronic","Electronics",PROPER(TRIM(messy_ecommerce_sales_data__27[[#This Row],[ Category]])))) -> Electronics | N30: 45606 | O30: =IF(LEN(TRIM(messy_ecommerce_sales_data__27[[#This Row],[Quantity]])) = 0, "Missing",IFERROR(VALUE(messy_ecommerce_sales_data__27[[#This Row],[Quantity]]),"Invalid")) -> 3 | P30: =IFERROR(VALUE(SUBSTITUTE(SUBSTITUTE(H30,"$",""), ".",",")),"Invalid") -> 898.69 | Q30: =IF(LEN(TRIM(messy_ecommerce_sales_data__27[[#This Row],[Total]])) = 0, "Missing",IFERROR(VALUE(SUBSTITUTE(SUBSTITUTE(messy_ecommerce_sales_data__27[[#This Row],[Total]],"$",""), ".",",")),"Invalid")) -> 2696.07 | R30: =IFERROR(O30*P30, "Cannot Calculate") -> 2696.07 | S30: =IF(AND(ISNUMBER(R30),ISNUMBER(Q30)),IF(ROUND(R30,2)=ROUND(Q30,2),"OK","Mismatch"),"No Data") -> OK
A31: 129 | B31: Customer_129 | C31: ORD-48863 | D31: 6/22/2025 | E31: Science | F31: Books | G31: 4 | H31: 736.71 | I31: Bank Transfer | J31: Returned | K31: 2946.84 | M31: =IF(OR(F31="",F31="Nan"),"Missing",IF(PROPER(TRIM(messy_ecommerce_sales_data__27[[#This Row],[ Category]]))="Electronic","Electronics",PROPER(TRIM(messy_ecommerce_sales_data__27[[#This Row],[ Category]])))) -> Books | N31: 45830 | O31: =IF(LEN(TRIM(messy_ecommerce_sales_data__27[[#This Row],[Quantity]])) = 0, "Missing",IFERROR(VALUE(messy_ecommerce_sales_data__27[[#This Row],[Quantity]]),"Invalid")) -> 4 | P31: =IFERROR(VALUE(SUBSTITUTE(SUBSTITUTE(H31,"$",""), ".",",")),"Invalid") -> 736.71 | Q31: =IF(LEN(TRIM(messy_ecommerce_sales_data__27[[#This Row],[Total]])) = 0, "Missing",IFERROR(VALUE(SUBSTITUTE(SUBSTITUTE(messy_ecommerce_sales_data__27[[#This Row],[Total]],"$",""), ".",",")),"Invalid")) -> 2946.84 | R31: =IFERROR(O31*P31, "Cannot Calculate") -> 2946.84 | S31: =IF(AND(ISNUMBER(R31),ISNUMBER(Q31)),IF(ROUND(R31,2)=ROUND(Q31,2),"OK","Mismatch"),"No Data") -> OK
A32: 130 | B32: Customer_130 | C32: ORD-34007 | D32: 8/15/2025 | E32: Tennis Racket | F32: Sports | G32: 2 | I32: Bank Transfer | J32: Processing | M32: =IF(OR(F32="",F32="Nan"),"Missing",IF(PROPER(TRIM(messy_ecommerce_sales_data__27[[#This Row],[ Category]]))="Electronic","Electronics",PROPER(TRIM(messy_ecommerce_sales_data__27[[#This Row],[ Category]])))) -> Sports | N32: 45884 | O32: =IF(LEN(TRIM(messy_ecommerce_sales_data__27[[#This Row],[Quantity]])) = 0, "Missing",IFERROR(VALUE(messy_ecommerce_sales_data__27[[#This Row],[Quantity]]),"Invalid")) -> 2 | P32: =IFERROR(VALUE(SUBSTITUTE(SUBSTITUTE(H32,"$",""), ".",",")),"Invalid") -> Invalid | Q32: =IF(LEN(TRIM(messy_ecommerce_sales_data__27[[#This Row],[Total]])) = 0, "Missing",IFERROR(VALUE(SUBSTITUTE(SUBSTITUTE(messy_ecommerce_sales_data__27[[#This Row],[Total]],"$",""), ".",",")),"Invalid")) -> Missing | R32: =IFERROR(O32*P32, "Cannot Calculate") -> Cannot Calculate | S32: =IF(AND(ISNUMBER(R32),ISNUMBER(Q32)),IF(ROUND(R32,2)=ROUND(Q32,2),"OK","Mismatch"),"No Data") -> No Data
A33: 131 | B33: Customer_131 | C33: ORD-91396 | D33: 6/11/2025 | E33: Lamp | F33: Home | G33: 5 | H33: 616.63 | I33: PayPal | J33: Shipped | K33: 3083.15 | M33: =IF(OR(F33="",F33="Nan"),"Missing",IF(PROPER(TRIM(messy_ecommerce_sales_data__27[[#This Row],[ Category]]))="Electronic","Electronics",PROPER(TRIM(messy_ecommerce_sales_data__27[[#This Row],[ Category]])))) -> Home | N33: 45819 | O33: =IF(LEN(TRIM(messy_ecommerce_sales_data__27[[#This Row],[Quantity]])) = 0, "Missing",IFERROR(VALUE(messy_ecommerce_sales_data__27[[#This Row],[Quantity]]),"Invalid")) -> 5 | P33: =IFERROR(VALUE(SUBSTITUTE(SUBSTITUTE(H33,"$",""), ".",",")),"Invalid") -> 616.63 | Q33: =IF(LEN(TRIM(messy_ecommerce_sales_data__27[[#This Row],[Total]])) = 0, "Missing",IFERROR(VALUE(SUBSTITUTE(SUBSTITUTE(messy_ecommerce_sales_data__27[[#This Row],[Total]],"$",""), ".",",")),"Invalid")) -> 3083.15 | R33: =IFERROR(O33*P33, "Cannot Calculate") -> 3083.15 | S33: =IF(AND(ISNUMBER(R33),ISNUMBER(Q33)),IF(ROUND(R33,2)=ROUND(Q33,2),"OK","Mismatch"),"No Data") -> OK
A34: 132 | B34: Customer_132 | C34: ORD-40186 | D34: 4/2/2025 | E34: Yoga Mat | F34: ELECTRONICS | G34: 1 | H34: 266.7 | I34: PayPal | J34: Delivered | K34: 266.7 | M34: =IF(OR(F34="",F34="Nan"),"Missing",IF(PROPER(TRIM(messy_ecommerce_sales_data__27[[#This Row],[ Category]]))="Electronic","Electronics",PROPER(TRIM(messy_ecommerce_sales_data__27[[#This Row],[ Category]])))) -> Electronics | N34: 45749 | O34: =IF(LEN(TRIM(messy_ecommerce_sales_data__27[[#This Row],[Quantity]])) = 0, "Missing",IFERROR(VALUE(messy_ecommerce_sales_data__27[[#This Row],[Quantity]]),"Invalid")) -> 1 | P34: =IFERROR(VALUE(SUBSTITUTE(SUBSTITUTE(H34,"$",""), ".",",")),"Invalid") -> 266.7 | Q34: =IF(LEN(TRIM(messy_ecommerce_sales_data__27[[#This Row],[Total]])) = 0, "Missing",IFERROR(VALUE(SUBSTITUTE(SUBSTITUTE(messy_ecommerce_sales_data__27[[#This Row],[Total]],"$",""), ".",",")),"Invalid")) -> 266.7 | R34: =IFERROR(O34*P34, "Cannot Calculate") -> 266.7 | S34: =IF(AND(ISNUMBER(R34),ISNUMBER(Q34)),IF(ROUND(R34,2)=ROUND(Q34,2),"OK","Mismatch"),"No Data") -> OK
A35: 133 | B35: Customer_133 | C35: ORD-68182 | D35: 12/5/2024 | E35: Biography | F35: nan | G35: 5 | H35: 343.24 | I35: Credit Card | J35: Shipped | K35: 1716.2 | M35: =IF(OR(F35="",F35="Nan"),"Missing",IF(PROPER(TRIM(messy_ecommerce_sales_data__27[[#This Row],[ Category]]))="Electronic","Electronics",PROPER(TRIM(messy_ecommerce_sales_data__27[[#This Row],[ Category]])))) -> Missing | N35: 45631 | O35: =IF(LEN(TRIM(messy_ecommerce_sales_data__27[[#This Row],[Quantity]])) = 0, "Missing",IFERROR(VALUE(messy_ecommerce_sales_data__27[[#This Row],[Quantity]]),"Invalid")) -> 5 | P35: =IFERROR(VALUE(SUBSTITUTE(SUBSTITUTE(H35,"$",""), ".",",")),"Invalid") -> 343.24 | Q35: =IF(LEN(TRIM(messy_ecommerce_sales_data__27[[#This Row],[Total]])) = 0, "Missing",IFERROR(VALUE(SUBSTITUTE(SUBSTITUTE(messy_ecommerce_sales_data__27[[#This Row],[Total]],"$",""), ".",",")),"Invalid")) -> 1716.2 | R35: =IFERROR(O35*P35, "Cannot Calculate") -> 1716.2 | S35: =IF(AND(ISNUMBER(R35),ISNUMBER(Q35)),IF(ROUND(R35,2)=ROUND(Q35,2),"OK","Mismatch"),"No Data") -> OK
A36: 134 | B36: Customer_134 | C36: ORD-16585 | D36: 10/4/2025 | E36: T-shirt | F36: Clothing | G36: -5 | H36: 591.53 | I36: PayPal | J36: Shipped | K36: -2957.65 | M36: =IF(OR(F36="",F36="Nan"),"Missing",IF(PROPER(TRIM(messy_ecommerce_sales_data__27[[#This Row],[ Category]]))="Electronic","Electronics",PROPER(TRIM(messy_ecommerce_sales_data__27[[#This Row],[ Category]])))) -> Clothing | N36: 45934 | O36: =IF(LEN(TRIM(messy_ecommerce_sales_data__27[[#This Row],[Quantity]])) = 0, "Missing",IFERROR(VALUE(messy_ecommerce_sales_data__27[[#This Row],[Quantity]]),"Invalid")) -> -5 | P36: =IFERROR(VALUE(SUBSTITUTE(SUBSTITUTE(H36,"$",""), ".",",")),"Invalid") -> 591.53 | Q36: =IF(LEN(TRIM(messy_ecommerce_sales_data__27[[#This Row],[Total]])) = 0, "Missing",IFERROR(VALUE(SUBSTITUTE(SUBSTITUTE(messy_ecommerce_sales_data__27[[#This Row],[Total]],"$",""), ".",",")),"Invalid")) -> -2957.65 | R36: =IFERROR(O36*P36, "Cannot Calculate") -> -2957.65 | S36: =IF(AND(ISNUMBER(R36),ISNUMBER(Q36)),IF(ROUND(R36,2)=ROUND(Q36,2),"OK","Mismatch"),"No Data") -> OK
A37: 135 | B37: Customer_135 | C37: ORD-33656 | D37: 2/9/2025 | E37: Smartwatch | F37: electronics | G37: 4 | H37: 446.19 | I37: Cash on Delivery | J37: Cancelled | K37: 1784.76 | M37: =IF(OR(F37="",F37="Nan"),"Missing",IF(PROPER(TRIM(messy_ecommerce_sales_data__27[[#This Row],[ Category]]))="Electronic","Electronics",PROPER(TRIM(messy_ecommerce_sales_data__27[[#This Row],[ Category]])))) -> Electronics | N37: 45697 | O37: =IF(LEN(TRIM(messy_ecommerce_sales_data__27[[#This Row],[Quantity]])) = 0, "Missing",IFERROR(VALUE(messy_ecommerce_sales_data__27[[#This Row],[Quantity]]),"Invalid")) -> 4 | P37: =IFERROR(VALUE(SUBSTITUTE(SUBSTITUTE(H37,"$",""), ".",",")),"Invalid") -> 446.19 | Q37: =IF(LEN(TRIM(messy_ecommerce_sales_data__27[[#This Row],[Total]])) = 0, "Missing",IFERROR(VALUE(SUBSTITUTE(SUBSTITUTE(messy_ecommerce_sales_data__27[[#This Row],[Total]],"$",""), ".",",")),"Invalid")) -> 1784.76 | R37: =IFERROR(O37*P37, "Cannot Calculate") -> 1784.76 | S37: =IF(AND(ISNUMBER(R37),ISNUMBER(Q37)),IF(ROUND(R37,2)=ROUND(Q37,2),"OK","Mismatch"),"No Data") -> OK
A38: 136 | B38: Customer_136 | C38: ORD-20985 | D38: 6/12/2025 | E38: Headphones | G38: 1 | H38: 696.71 | I38: Credit Card | J38: Delivered | K38: 696.71 | M38: =IF(OR(F38="",F38="Nan"),"Missing",IF(PROPER(TRIM(messy_ecommerce_sales_data__27[[#This Row],[ Category]]))="Electronic","Electronics",PROPER(TRIM(messy_ecommerce_sales_data__27[[#This Row],[ Category]])))) -> Missing | N38: 45820 | O38: =IF(LEN(TRIM(messy_ecommerce_sales_data__27[[#This Row],[Quantity]])) = 0, "Missing",IFERROR(VALUE(messy_ecommerce_sales_data__27[[#This Row],[Quantity]]),"Invalid")) -> 1 | P38: =IFERROR(VALUE(SUBSTITUTE(SUBSTITUTE(H38,"$",""), ".",",")),"Invalid") -> 696.71 | Q38: =IF(LEN(TRIM(messy_ecommerce_sales_data__27[[#This Row],[Total]])) = 0, "Missing",IFERROR(VALUE(SUBSTITUTE(SUBSTITUTE(messy_ecommerce_sales_data__27[[#This Row],[Total]],"$",""), ".",",")),"Invalid")) -> 696.71 | R38: =IFERROR(O38*P38, "Cannot Calculate") -> 696.71 | S38: =IF(AND(ISNUMBER(R38),ISNUMBER(Q38)),IF(ROUND(R38,2)=ROUND(Q38,2),"OK","Mismatch"),"No Data") -> OK
A39: 137 | B39: Customer_137 | C39: ORD-91254 | D39: 2/23/2025 | E39: Vacuum | F39: Home | G39: 3 | H39: -100 | I39: Cash on Delivery | J39: Delivered | K39: -300 | M39: =IF(OR(F39="",F39="Nan"),"Missing",IF(PROPER(TRIM(messy_ecommerce_sales_data__27[[#This Row],[ Category]]))="Electronic","Electronics",PROPER(TRIM(messy_ecommerce_sales_data__27[[#This Row],[ Category]])))) -> Home | N39: 45711 | O39: =IF(LEN(TRIM(messy_ecommerce_sales_data__27[[#This Row],[Quantity]])) = 0, "Missing",IFERROR(VALUE(messy_ecommerce_sales_data__27[[#This Row],[Quantity]]),"Invalid")) -> 3 | P39: =IFERROR(VALUE(SUBSTITUTE(SUBSTITUTE(H39,"$",""), ".",",")),"Invalid") -> -100 | Q39: =IF(LEN(TRIM(messy_ecommerce_sales_data__27[[#This Row],[Total]])) = 0, "Missing",IFERROR(VALUE(SUBSTITUTE(SUBSTITUTE(messy_ecommerce_sales_data__27[[#This Row],[Total]],"$",""), ".",",")),"Invalid")) -> -300 | R39: =IFERROR(O39*P39, "Cannot Calculate") -> -300 | S39: =IF(AND(ISNUMBER(R39),ISNUMBER(Q39)),IF(ROUND(R39,2)=ROUND(Q39,2),"OK","Mismatch"),"No Data") -> OK
A40: 138 | B40: Customer_138 | C40: ORD-34319 | D40: 8/9/2025 | E40: Lamp | F40: Home | G40: 1 | H40: 531.06 | I40: PayPal | J40: Processing | K40: 531.06 | M40: =IF(OR(F40="",F40="Nan"),"Missing",IF(PROPER(TRIM(messy_ecommerce_sales_data__27[[#This Row],[ Category]]))="Electronic","Electronics",PROPER(TRIM(messy_ecommerce_sales_data__27[[#This Row],[ Category]])))) -> Home | N40: 45878 | O40: =IF(LEN(TRIM(messy_ecommerce_sales_data__27[[#This Row],[Quantity]])) = 0, "Missing",IFERROR(VALUE(messy_ecommerce_sales_data__27[[#This Row],[Quantity]]),"Invalid")) -> 1 | P40: =IFERROR(VALUE(SUBSTITUTE(SUBSTITUTE(H40,"$",""), ".",",")),"Invalid") -> 531.06 | Q40: =IF(LEN(TRIM(messy_ecommerce_sales_data__27[[#This Row],[Total]])) = 0, "Missing",IFERROR(VALUE(SUBSTITUTE(SUBSTITUTE(messy_ecommerce_sales_data__27[[#This Row],[Total]],"$",""), ".",",")),"Invalid")) -> 531.06 | R40: =IFERROR(O40*P40, "Cannot Calculate") -> 531.06 | S40: =IF(AND(ISNUMBER(R40),ISNUMBER(Q40)),IF(ROUND(R40,2)=ROUND(Q40,2),"OK","Mismatch"),"No Data") -> OK
A41: 139 | B41: Customer_139 | C41: ORD-38418 | D41: 2/9/2025 | E41: Smartphone | F41: Electronics | G41: 2 | H41: 681.38 | I41: Credit Card | J41: Cancelled | K41: 1362.76 | M41: =IF(OR(F41="",F41="Nan"),"Missing",IF(PROPER(TRIM(messy_ecommerce_sales_data__27[[#This Row],[ Category]]))="Electronic","Electronics",PROPER(TRIM(messy_ecommerce_sales_data__27[[#This Row],[ Category]])))) -> Electronics | N41: 45697 | O41: =IF(LEN(TRIM(messy_ecommerce_sales_data__27[[#This Row],[Quantity]])) = 0, "Missing",IFERROR(VALUE(messy_ecommerce_sales_data__27[[#This Row],[Quantity]]),"Invalid")) -> 2 | P41: =IFERROR(VALUE(SUBSTITUTE(SUBSTITUTE(H41,"$",""), ".",",")),"Invalid") -> 681.38 | Q41: =IF(LEN(TRIM(messy_ecommerce_sales_data__27[[#This Row],[Total]])) = 0, "Missing",IFERROR(VALUE(SUBSTITUTE(SUBSTITUTE(messy_ecommerce_sales_data__27[[#This Row],[Total]],"$",""), ".",",")),"Invalid")) -> 1362.76 | R41: =IFERROR(O41*P41, "Cannot Calculate") -> 1362.76 | S41: =IF(AND(ISNUMBER(R41),ISNUMBER(Q41)),IF(ROUND(R41,2)=ROUND(Q41,2),"OK","Mismatch"),"No Data") -> OK
A42: 140 | B42: Customer_140 | C42: ORD-67096 | D42: 2/26/2025 | E42: Fiction | F42: Books | G42: 4 | H42: 588.98 | I42: Credit Card | J42: Returned | K42: 2355.92 | M42: =IF(OR(F42="",F42="Nan"),"Missing",IF(PROPER(TRIM(messy_ecommerce_sales_data__27[[#This Row],[ Category]]))="Electronic","Electronics",PROPER(TRIM(messy_ecommerce_sales_data__27[[#This Row],[ Category]])))) -> Books | N42: 45714 | O42: =IF(LEN(TRIM(messy_ecommerce_sales_data__27[[#This Row],[Quantity]])) = 0, "Missing",IFERROR(VALUE(messy_ecommerce_sales_data__27[[#This Row],[Quantity]]),"Invalid")) -> 4 | P42: =IFERROR(VALUE(SUBSTITUTE(SUBSTITUTE(H42,"$",""), ".",",")),"Invalid") -> 588.98 | Q42: =IF(LEN(TRIM(messy_ecommerce_sales_data__27[[#This Row],[Total]])) = 0, "Missing",IFERROR(VALUE(SUBSTITUTE(SUBSTITUTE(messy_ecommerce_sales_data__27[[#This Row],[Total]],"$",""), ".",",")),"Invalid")) -> 2355.92 | R42: =IFERROR(O42*P42, "Cannot Calculate") -> 2355.92 | S42: =IF(AND(ISNUMBER(R42),ISNUMBER(Q42)),IF(ROUND(R42,2)=ROUND(Q42,2),"OK","Mismatch"),"No Data") -> OK
A43: 141 | B43: Customer_141 | C43: ORD-45059 | D43: 2/13/2025 | E43: Fiction | F43: Books | G43: 3 | H43: 546.04 | I43: Cash on Delivery | J43: Returned | K43: 1638.12 | M43: =IF(OR(F43="",F43="Nan"),"Missing",IF(PROPER(TRIM(messy_ecommerce_sales_data__27[[#This Row],[ Category]]))="Electronic","Electronics",PROPER(TRIM(messy_ecommerce_sales_data__27[[#This Row],[ Category]])))) -> Books | N43: 45701 | O43: =IF(LEN(TRIM(messy_ecommerce_sales_data__27[[#This Row],[Quantity]])) = 0, "Missing",IFERROR(VALUE(messy_ecommerce_sales_data__27[[#This Row],[Quantity]]),"Invalid")) -> 3 | P43: =IFERROR(VALUE(SUBSTITUTE(SUBSTITUTE(H43,"$",""), ".",",")),"Invalid") -> 546.04 | Q43: =IF(LEN(TRIM(messy_ecommerce_sales_data__27[[#This Row],[Total]])) = 0, "Missing",IFERROR(VALUE(SUBSTITUTE(SUBSTITUTE(messy_ecommerce_sales_data__27[[#This Row],[Total]],"$",""), ".",",")),"Invalid")) -> 1638.12 | R43: =IFERROR(O43*P43, "Cannot Calculate") -> 1638.12 | S43: =IF(AND(ISNUMBER(R43),ISNUMBER(Q43)),IF(ROUND(R43,2)=ROUND(Q43,2),"OK","Mismatch"),"No Data") -> OK
A44: 143 | B44: Customer_143 | C44: ORD-14329 | D44: 7/11/2025 | E44: T-shirt | F44: Clothing | G44: 5 | H44: 826.77 | I44: Bank Transfer | J44: Cancelled | K44: 4133.85 | M44: =IF(OR(F44="",F44="Nan"),"Missing",IF(PROPER(TRIM(messy_ecommerce_sales_data__27[[#This Row],[ Category]]))="Electronic","Electronics",PROPER(TRIM(messy_ecommerce_sales_data__27[[#This Row],[ Category]])))) -> Clothing | N44: 45849 | O44: =IF(LEN(TRIM(messy_ecommerce_sales_data__27[[#This Row],[Quantity]])) = 0, "Missing",IFERROR(VALUE(messy_ecommerce_sales_data__27[[#This Row],[Quantity]]),"Invalid")) -> 5 | P44: =IFERROR(VALUE(SUBSTITUTE(SUBSTITUTE(H44,"$",""), ".",",")),"Invalid") -> 826.77 | Q44: =IF(LEN(TRIM(messy_ecommerce_sales_data__27[[#This Row],[Total]])) = 0, "Missing",IFERROR(VALUE(SUBSTITUTE(SUBSTITUTE(messy_ecommerce_sales_data__27[[#This Row],[Total]],"$",""), ".",",")),"Invalid")) -> 4133.85 | R44: =IFERROR(O44*P44, "Cannot Calculate") -> 4133.85 | S44: =IF(AND(ISNUMBER(R44),ISNUMBER(Q44)),IF(ROUND(R44,2)=ROUND(Q44,2),"OK","Mismatch"),"No Data") -> OK
A45: 144 | B45: Customer_144 | C45: ORD-89452 | D45: 1/27/2025 | E45: Football | F45: Sports | G45: 5 | H45: 849.07 | I45: Bank Transfer | J45: Processing | K45: 4245.35 | M45: =IF(OR(F45="",F45="Nan"),"Missing",IF(PROPER(TRIM(messy_ecommerce_sales_data__27[[#This Row],[ Category]]))="Electronic","Electronics",PROPER(TRIM(messy_ecommerce_sales_data__27[[#This Row],[ Category]])))) -> Sports | N45: 45684 | O45: =IF(LEN(TRIM(messy_ecommerce_sales_data__27[[#This Row],[Quantity]])) = 0, "Missing",IFERROR(VALUE(messy_ecommerce_sales_data__27[[#This Row],[Quantity]]),"Invalid")) -> 5 | P45: =IFERROR(VALUE(SUBSTITUTE(SUBSTITUTE(H45,"$",""), ".",",")),"Invalid") -> 849.07 | Q45: =IF(LEN(TRIM(messy_ecommerce_sales_data__27[[#This Row],[Total]])) = 0, "Missing",IFERROR(VALUE(SUBSTITUTE(SUBSTITUTE(messy_ecommerce_sales_data__27[[#This Row],[Total]],"$",""), ".",",")),"Invalid")) -> 4245.35 | R45: =IFERROR(O45*P45, "Cannot Calculate") -> 4245.35 | S45: =IF(AND(ISNUMBER(R45),ISNUMBER(Q45)),IF(ROUND(R45,2)=ROUND(Q45,2),"OK","Mismatch"),"No Data") -> OK
A46: 145 | B46: Customer_145 | C46: ORD-75314 | D46: 5/1/2023 | E46: Laptop | F46: Electronics | G46: 2 | H46: 860.99 | I46: Bank Transfer | J46: Returned | K46: 1721.98 | M46: =IF(OR(F46="",F46="Nan"),"Missing",IF(PROPER(TRIM(messy_ecommerce_sales_data__27[[#This Row],[ Category]]))="Electronic","Electronics",PROPER(TRIM(messy_ecommerce_sales_data__27[[#This Row],[ Category]])))) -> Electronics | N46: 45047 | O46: =IF(LEN(TRIM(messy_ecommerce_sales_data__27[[#This Row],[Quantity]])) = 0, "Missing",IFERROR(VALUE(messy_ecommerce_sales_data__27[[#This Row],[Quantity]]),"Invalid")) -> 2 | P46: =IFERROR(VALUE(SUBSTITUTE(SUBSTITUTE(H46,"$",""), ".",",")),"Invalid") -> 860.99 | Q46: =IF(LEN(TRIM(messy_ecommerce_sales_data__27[[#This Row],[Total]])) = 0, "Missing",IFERROR(VALUE(SUBSTITUTE(SUBSTITUTE(messy_ecommerce_sales_data__27[[#This Row],[Total]],"$",""), ".",",")),"Invalid")) -> 1721.98 | R46: =IFERROR(O46*P46, "Cannot Calculate") -> 1721.98 | S46: =IF(AND(ISNUMBER(R46),ISNUMBER(Q46)),IF(ROUND(R46,2)=ROUND(Q46,2),"OK","Mismatch"),"No Data") -> OK
A47: 146 | B47: Customer_146 | C47: ORD-32755 | D47: 7/9/2025 | E47: Basketball | F47: electronic | G47: 2 | H47: 705.42 | I47: Bank Transfer | J47: Processing | K47: 1410.84 | M47: =IF(OR(F47="",F47="Nan"),"Missing",IF(PROPER(TRIM(messy_ecommerce_sales_data__27[[#This Row],[ Category]]))="Electronic","Electronics",PROPER(TRIM(messy_ecommerce_sales_data__27[[#This Row],[ Category]])))) -> Electronics | N47: 45847 | O47: =IF(LEN(TRIM(messy_ecommerce_sales_data__27[[#This Row],[Quantity]])) = 0, "Missing",IFERROR(VALUE(messy_ecommerce_sales_data__27[[#This Row],[Quantity]]),"Invalid")) -> 2 | P47: =IFERROR(VALUE(SUBSTITUTE(SUBSTITUTE(H47,"$",""), ".",",")),"Invalid") -> 705.42 | Q47: =IF(LEN(TRIM(messy_ecommerce_sales_data__27[[#This Row],[Total]])) = 0, "Missing",IFERROR(VALUE(SUBSTITUTE(SUBSTITUTE(messy_ecommerce_sales_data__27[[#This Row],[Total]],"$",""), ".",",")),"Invalid")) -> 1410.84 | R47: =IFERROR(O47*P47, "Cannot Calculate") -> 1410.84 | S47: =IF(AND(ISNUMBER(R47),ISNUMBER(Q47)),IF(ROUND(R47,2)=ROUND(Q47,2),"OK","Mismatch"),"No Data") -> OK
A48: 147 | B48: Customer_147 | C48: ORD-80707 | D48: 5/1/2025 | E48: Jacket | F48: Clothing | G48: 4 | H48: 596.15 | I48: Cash on Delivery | J48: Shipped | K48: 2384.6 | M48: =IF(OR(F48="",F48="Nan"),"Missing",IF(PROPER(TRIM(messy_ecommerce_sales_data__27[[#This Row],[ Category]]))="Electronic","Electronics",PROPER(TRIM(messy_ecommerce_sales_data__27[[#This Row],[ Category]])))) -> Clothing | N48: 45778 | O48: =IF(LEN(TRIM(messy_ecommerce_sales_data__27[[#This Row],[Quantity]])) = 0, "Missing",IFERROR(VALUE(messy_ecommerce_sales_data__27[[#This Row],[Quantity]]),"Invalid")) -> 4 | P48: =IFERROR(VALUE(SUBSTITUTE(SUBSTITUTE(H48,"$",""), ".",",")),"Invalid") -> 596.15 | Q48: =IF(LEN(TRIM(messy_ecommerce_sales_data__27[[#This Row],[Total]])) = 0, "Missing",IFERROR(VALUE(SUBSTITUTE(SUBSTITUTE(messy_ecommerce_sales_data__27[[#This Row],[Total]],"$",""), ".",",")),"Invalid")) -> 2384.6 | R48: =IFERROR(O48*P48, "Cannot Calculate") -> 2384.6 | S48: =IF(AND(ISNUMBER(R48),ISNUMBER(Q48)),IF(ROUND(R48,2)=ROUND(Q48,2),"OK","Mismatch"),"No Data") -> OK
A49: 148 | B49: Customer_148 | C49: ORD-38423 | D49: 3/13/2025 | E49: Tennis Racket | F49: Sports | G49: 1 | H49: 660.98 | I49: Cash on Delivery | J49: Returned | K49: 660.98 | M49: =IF(OR(F49="",F49="Nan"),"Missing",IF(PROPER(TRIM(messy_ecommerce_sales_data__27[[#This Row],[ Category]]))="Electronic","Electronics",PROPER(TRIM(messy_ecommerce_sales_data__27[[#This Row],[ Category]])))) -> Sports | N49: 45729 | O49: =IF(LEN(TRIM(messy_ecommerce_sales_data__27[[#This Row],[Quantity]])) = 0, "Missing",IFERROR(VALUE(messy_ecommerce_sales_data__27[[#This Row],[Quantity]]),"Invalid")) -> 1 | P49: =IFERROR(VALUE(SUBSTITUTE(SUBSTITUTE(H49,"$",""), ".",",")),"Invalid") -> 660.98 | Q49: =IF(LEN(TRIM(messy_ecommerce_sales_data__27[[#This Row],[Total]])) = 0, "Missing",IFERROR(VALUE(SUBSTITUTE(SUBSTITUTE(messy_ecommerce_sales_data__27[[#This Row],[Total]],"$",""), ".",",")),"Invalid")) -> 660.98 | R49: =IFERROR(O49*P49, "Cannot Calculate") -> 660.98 | S49: =IF(AND(ISNUMBER(R49),ISNUMBER(Q49)),IF(ROUND(R49,2)=ROUND(Q49,2),"OK","Mismatch"),"No Data") -> OK
A50: 149 | B50: Customer_149 | C50: ORD-95911 | D50: 6/29/2025 | E50: Comics | F50: Books | G50: 5 | H50: 896.38 | I50: Bank Transfer | J50: Cancelled | K50: 4481.9 | M50: =IF(OR(F50="",F50="Nan"),"Missing",IF(PROPER(TRIM(messy_ecommerce_sales_data__27[[#This Row],[ Category]]))="Electronic","Electronics",PROPER(TRIM(messy_ecommerce_sales_data__27[[#This Row],[ Category]])))) -> Books | N50: 45837 | O50: =IF(LEN(TRIM(messy_ecommerce_sales_data__27[[#This Row],[Quantity]])) = 0, "Missing",IFERROR(VALUE(messy_ecommerce_sales_data__27[[#This Row],[Quantity]]),"Invalid")) -> 5 | P50: =IFERROR(VALUE(SUBSTITUTE(SUBSTITUTE(H50,"$",""), ".",",")),"Invalid") -> 896.38 | Q50: =IF(LEN(TRIM(messy_ecommerce_sales_data__27[[#This Row],[Total]])) = 0, "Missing",IFERROR(VALUE(SUBSTITUTE(SUBSTITUTE(messy_ecommerce_sales_data__27[[#This Row],[Total]],"$",""), ".",",")),"Invalid")) -> 4481.9 | R50: =IFERROR(O50*P50, "Cannot Calculate") -> 4481.9 | S50: =IF(AND(ISNUMBER(R50),ISNUMBER(Q50)),IF(ROUND(R50,2)=ROUND(Q50,2),"OK","Mismatch"),"No Data") -> OK
... A56: 155 | B56: Customer_155 | C56: ORD-20182 | D56: 5/1/2025 | E56: Shoes | F56: Clothing | G56: 1 | H56: 40.95 | I56: PayPal | J56: Returned | K56: 40.95 | M56: =IF(OR(F56="",F56="Nan"),"Missing",IF(PROPER(TRIM(messy_ecommerce_sales_data__27[[#This Row],[ Category]]))="Electronic","Electronics",PROPER(TRIM(messy_ecommerce_sales_data__27[[#This Row],[ Category]])))) -> Clothing | N56: 45778 | O56: =IF(LEN(TRIM(messy_ecommerce_sales_data__27[[#This Row],[Quantity]])) = 0, "Missing",IFERROR(VALUE(messy_ecommerce_sales_data__27[[#This Row],[Quantity]]),"Invalid")) -> 1 | P56: =IFERROR(VALUE(SUBSTITUTE(SUBSTITUTE(H56,"$",""), ".",",")),"Invalid") -> 40.95 | Q56: =IF(LEN(TRIM(messy_ecommerce_sales_data__27[[#This Row],[Total]])) = 0, "Missing",IFERROR(VALUE(SUBSTITUTE(SUBSTITUTE(messy_ecommerce_sales_data__27[[#This Row],[Total]],"$",""), ".",",")),"Invalid")) -> 40.95 | R56: =IFERROR(O56*P56, "Cannot Calculate") -> 40.95 | S56: =IF(AND(ISNUMBER(R56),ISNUMBER(Q56)),IF(ROUND(R56,2)=ROUND(Q56,2),"OK","Mismatch"),"No Data") -> OK
A57: 156 | B57: Customer_156 | C57: ORD-34679 | D57: 11/28/2024 | E57: Jeans | F57: Clothing | G57: 2 | I57: Bank Transfer | J57: Shipped | M57: =IF(OR(F57="",F57="Nan"),"Missing",IF(PROPER(TRIM(messy_ecommerce_sales_data__27[[#This Row],[ Category]]))="Electronic","Electronics",PROPER(TRIM(messy_ecommerce_sales_data__27[[#This Row],[ Category]])))) -> Clothing | N57: 45624 | O57: =IF(LEN(TRIM(messy_ecommerce_sales_data__27[[#This Row],[Quantity]])) = 0, "Missing",IFERROR(VALUE(messy_ecommerce_sales_data__27[[#This Row],[Quantity]]),"Invalid")) -> 2 | P57: =IFERROR(VALUE(SUBSTITUTE(SUBSTITUTE(H57,"$",""), ".",",")),"Invalid") -> Invalid | Q57: =IF(LEN(TRIM(messy_ecommerce_sales_data__27[[#This Row],[Total]])) = 0, "Missing",IFERROR(VALUE(SUBSTITUTE(SUBSTITUTE(messy_ecommerce_sales_data__27[[#This Row],[Total]],"$",""), ".",",")),"Invalid")) -> Missing | R57: =IFERROR(O57*P57, "Cannot Calculate") -> Cannot Calculate | S57: =IF(AND(ISNUMBER(R57),ISNUMBER(Q57)),IF(ROUND(R57,2)=ROUND(Q57,2),"OK","Mismatch"),"No Data") -> No Data
A58: 157 | B58: Customer_157 | C58: ORD-34407 | D58: 11/6/2025 | E58: Jacket | F58: Clothing | G58: 4 | H58: 275.1 | I58: Bank Transfer | J58: Processing | K58: 1100.4 | M58: =IF(OR(F58="",F58="Nan"),"Missing",IF(PROPER(TRIM(messy_ecommerce_sales_data__27[[#This Row],[ Category]]))="Electronic","Electronics",PROPER(TRIM(messy_ecommerce_sales_data__27[[#This Row],[ Category]])))) -> Clothing | N58: 45967 | O58: =IF(LEN(TRIM(messy_ecommerce_sales_data__27[[#This Row],[Quantity]])) = 0, "Missing",IFERROR(VALUE(messy_ecommerce_sales_data__27[[#This Row],[Quantity]]),"Invalid")) -> 4 | P58: =IFERROR(VALUE(SUBSTITUTE(SUBSTITUTE(H58,"$",""), ".",",")),"Invalid") -> 275.1 | Q58: =IF(LEN(TRIM(messy_ecommerce_sales_data__27[[#This Row],[Total]])) = 0, "Missing",IFERROR(VALUE(SUBSTITUTE(SUBSTITUTE(messy_ecommerce_sales_data__27[[#This Row],[Total]],"$",""), ".",",")),"Invalid")) -> 1100.4 | R58: =IFERROR(O58*P58, "Cannot Calculate") -> 1100.4 | S58: =IF(AND(ISNUMBER(R58),ISNUMBER(Q58)),IF(ROUND(R58,2)=ROUND(Q58,2),"OK","Mismatch"),"No Data") -> OK
A59: 158 | B59: Customer_158 | C59: ORD-35817 | D59: 4/5/2025 | E59: Smartwatch | F59: Electronics | G59: 1 | H59: 933.58 | I59: Cash on Delivery | J59: Shipped | K59: 933.58 | M59: =IF(OR(F59="",F59="Nan"),"Missing",IF(PROPER(TRIM(messy_ecommerce_sales_data__27[[#This Row],[ Category]]))="Electronic","Electronics",PROPER(TRIM(messy_ecommerce_sales_data__27[[#This Row],[ Category]])))) -> Electronics | N59: 45752 | O59: =IF(LEN(TRIM(messy_ecommerce_sales_data__27[[#This Row],[Quantity]])) = 0, "Missing",IFERROR(VALUE(messy_ecommerce_sales_data__27[[#This Row],[Quantity]]),"Invalid")) -> 1 | P59: =IFERROR(VALUE(SUBSTITUTE(SUBSTITUTE(H59,"$",""), ".",",")),"Invalid") -> 933.58 | Q59: =IF(LEN(TRIM(messy_ecommerce_sales_data__27[[#This Row],[Total]])) = 0, "Missing",IFERROR(VALUE(SUBSTITUTE(SUBSTITUTE(messy_ecommerce_sales_data__27[[#This Row],[Total]],"$",""), ".",",")),"Invalid")) -> 933.58 | R59: =IFERROR(O59*P59, "Cannot Calculate") -> 933.58 | S59: =IF(AND(ISNUMBER(R59),ISNUMBER(Q59)),IF(ROUND(R59,2)=ROUND(Q59,2),"OK","Mismatch"),"No Data") -> OK
A60: 159 | B60: Customer_159 | C60: ORD-98162 | D60: 7/28/2025 | E60: Microwave | F60: Home | G60: 3 | H60: 163.16 | I60: PayPal | J60: Shipped | K60: 489.48 | M60: =IF(OR(F60="",F60="Nan"),"Missing",IF(PROPER(TRIM(messy_ecommerce_sales_data__27[[#This Row],[ Category]]))="Electronic","Electronics",PROPER(TRIM(messy_ecommerce_sales_data__27[[#This Row],[ Category]])))) -> Home | N60: 45866 | O60: =IF(LEN(TRIM(messy_ecommerce_sales_data__27[[#This Row],[Quantity]])) = 0, "Missing",IFERROR(VALUE(messy_ecommerce_sales_data__27[[#This Row],[Quantity]]),"Invalid")) -> 3 | P60: =IFERROR(VALUE(SUBSTITUTE(SUBSTITUTE(H60,"$",""), ".",",")),"Invalid") -> 163.16 | Q60: =IF(LEN(TRIM(messy_ecommerce_sales_data__27[[#This Row],[Total]])) = 0, "Missing",IFERROR(VALUE(SUBSTITUTE(SUBSTITUTE(messy_ecommerce_sales_data__27[[#This Row],[Total]],"$",""), ".",",")),"Invalid")) -> 489.48 | R60: =IFERROR(O60*P60, "Cannot Calculate") -> 489.48 | S60: =IF(AND(ISNUMBER(R60),ISNUMBER(Q60)),IF(ROUND(R60,2)=ROUND(Q60,2),"OK","Mismatch"),"No Data") -> OK
A61: 160 | B61: Customer_160 | C61: ORD-96037 | D61: 1/3/2025 | E61: Science | F61: Books | G61: 5 | H61: 242.52 | I61: Cash on Delivery | J61: Returned | K61: 1212.6 | M61: =IF(OR(F61="",F61="Nan"),"Missing",IF(PROPER(TRIM(messy_ecommerce_sales_data__27[[#This Row],[ Category]]))="Electronic","Electronics",PROPER(TRIM(messy_ecommerce_sales_data__27[[#This Row],[ Category]])))) -> Books | N61: 45660 | O61: =IF(LEN(TRIM(messy_ecommerce_sales_data__27[[#This Row],[Quantity]])) = 0, "Missing",IFERROR(VALUE(messy_ecommerce_sales_data__27[[#This Row],[Quantity]]),"Invalid")) -> 5 | P61: =IFERROR(VALUE(SUBSTITUTE(SUBSTITUTE(H61,"$",""), ".",",")),"Invalid") -> 242.52 | Q61: =IF(LEN(TRIM(messy_ecommerce_sales_data__27[[#This Row],[Total]])) = 0, "Missing",IFERROR(VALUE(SUBSTITUTE(SUBSTITUTE(messy_ecommerce_sales_data__27[[#This Row],[Total]],"$",""), ".",",")),"Invalid")) -> 1212.6 | R61: =IFERROR(O61*P61, "Cannot Calculate") -> 1212.6 | S61: =IF(AND(ISNUMBER(R61),ISNUMBER(Q61)),IF(ROUND(R61,2)=ROUND(Q61,2),"OK","Mismatch"),"No Data") -> OK
A62: 161 | B62: Customer_161 | C62: ORD-27653 | D62: 12/15/2024 | E62: Science | F62: Books | G62: 4 | H62: 209.32 | I62: Bank Transfer | J62: Shipped | K62: 837.28 | M62: =IF(OR(F62="",F62="Nan"),"Missing",IF(PROPER(TRIM(messy_ecommerce_sales_data__27[[#This Row],[ Category]]))="Electronic","Electronics",PROPER(TRIM(messy_ecommerce_sales_data__27[[#This Row],[ Category]])))) -> Books | N62: 45641 | O62: =IF(LEN(TRIM(messy_ecommerce_sales_data__27[[#This Row],[Quantity]])) = 0, "Missing",IFERROR(VALUE(messy_ecommerce_sales_data__27[[#This Row],[Quantity]]),"Invalid")) -> 4 | P62: =IFERROR(VALUE(SUBSTITUTE(SUBSTITUTE(H62,"$",""), ".",",")),"Invalid") -> 209.32 | Q62: =IF(LEN(TRIM(messy_ecommerce_sales_data__27[[#This Row],[Total]])) = 0, "Missing",IFERROR(VALUE(SUBSTITUTE(SUBSTITUTE(messy_ecommerce_sales_data__27[[#This Row],[Total]],"$",""), ".",",")),"Invalid")) -> 837.28 | R62: =IFERROR(O62*P62, "Cannot Calculate") -> 837.28 | S62: =IF(AND(ISNUMBER(R62),ISNUMBER(Q62)),IF(ROUND(R62,2)=ROUND(Q62,2),"OK","Mismatch"),"No Data") -> OK
A63: 162 | B63: Customer_162 | C63: ORD-27743 | D63: 5/19/2025 | E63: Blender | F63: Home | G63: 2 | H63: 155.76 | I63: Credit Card | J63: Returned | K63: 311.52 | M63: =IF(OR(F63="",F63="Nan"),"Missing",IF(PROPER(TRIM(messy_ecommerce_sales_data__27[[#This Row],[ Category]]))="Electronic","Electronics",PROPER(TRIM(messy_ecommerce_sales_data__27[[#This Row],[ Category]])))) -> Home | N63: 45796 | O63: =IF(LEN(TRIM(messy_ecommerce_sales_data__27[[#This Row],[Quantity]])) = 0, "Missing",IFERROR(VALUE(messy_ecommerce_sales_data__27[[#This Row],[Quantity]]),"Invalid")) -> 2 | P63: =IFERROR(VALUE(SUBSTITUTE(SUBSTITUTE(H63,"$",""), ".",",")),"Invalid") -> 155.76 | Q63: =IF(LEN(TRIM(messy_ecommerce_sales_data__27[[#This Row],[Total]])) = 0, "Missing",IFERROR(VALUE(SUBSTITUTE(SUBSTITUTE(messy_ecommerce_sales_data__27[[#This Row],[Total]],"$",""), ".",",")),"Invalid")) -> 311.52 | R63: =IFERROR(O63*P63, "Cannot Calculate") -> 311.52 | S63: =IF(AND(ISNUMBER(R63),ISNUMBER(Q63)),IF(ROUND(R63,2)=ROUND(Q63,2),"OK","Mismatch"),"No Data") -> OK
A64: 163 | B64: Customer_163 | C64: ORD-24378 | D64: 1/5/2023 | E64: Smartwatch | F64: Electronics | G64: 3 | H64: 235.26 | I64: Cash on Delivery | J64: Shipped | K64: 705.78 | M64: =IF(OR(F64="",F64="Nan"),"Missing",IF(PROPER(TRIM(messy_ecommerce_sales_data__27[[#This Row],[ Category]]))="Electronic","Electronics",PROPER(TRIM(messy_ecommerce_sales_data__27[[#This Row],[ Category]])))) -> Electronics | N64: 44931 | O64: =IF(LEN(TRIM(messy_ecommerce_sales_data__27[[#This Row],[Quantity]])) = 0, "Missing",IFERROR(VALUE(messy_ecommerce_sales_data__27[[#This Row],[Quantity]]),"Invalid")) -> 3 | P64: =IFERROR(VALUE(SUBSTITUTE(SUBSTITUTE(H64,"$",""), ".",",")),"Invalid") -> 235.26 | Q64: =IF(LEN(TRIM(messy_ecommerce_sales_data__27[[#This Row],[Total]])) = 0, "Missing",IFERROR(VALUE(SUBSTITUTE(SUBSTITUTE(messy_ecommerce_sales_data__27[[#This Row],[Total]],"$",""), ".",",")),"Invalid")) -> 705.78 | R64: =IFERROR(O64*P64, "Cannot Calculate") -> 705.78 | S64: =IF(AND(ISNUMBER(R64),ISNUMBER(Q64)),IF(ROUND(R64,2)=ROUND(Q64,2),"OK","Mismatch"),"No Data") -> OK
A65: 164 | B65: Customer_164 | C65: ORD-23010 | D65: 2/9/2025 | E65: Tennis Racket | F65: Sports | H65: 587.64 | I65: Credit Card | J65: Returned | M65: =IF(OR(F65="",F65="Nan"),"Missing",IF(PROPER(TRIM(messy_ecommerce_sales_data__27[[#This Row],[ Category]]))="Electronic","Electronics",PROPER(TRIM(messy_ecommerce_sales_data__27[[#This Row],[ Category]])))) -> Sports | N65: 45697 | O65: =IF(LEN(TRIM(messy_ecommerce_sales_data__27[[#This Row],[Quantity]])) = 0, "Missing",IFERROR(VALUE(messy_ecommerce_sales_data__27[[#This Row],[Quantity]]),"Invalid")) -> Missing | P65: =IFERROR(VALUE(SUBSTITUTE(SUBSTITUTE(H65,"$",""), ".",",")),"Invalid") -> 587.64 | Q65: =IF(LEN(TRIM(messy_ecommerce_sales_data__27[[#This Row],[Total]])) = 0, "Missing",IFERROR(VALUE(SUBSTITUTE(SUBSTITUTE(messy_ecommerce_sales_data__27[[#This Row],[Total]],"$",""), ".",",")),"Invalid")) -> Missing | R65: =IFERROR(O65*P65, "Cannot Calculate") -> Cannot Calculate | S65: =IF(AND(ISNUMBER(R65),ISNUMBER(Q65)),IF(ROUND(R65,2)=ROUND(Q65,2),"OK","Mismatch"),"No Data") -> No Data
A66: 165 | B66: Customer_165 | C66: ORD-55695 | D66: 11/8/2024 | E66: Shoes | F66: Clothing | G66: 2 | H66: 443.13 | I66: Credit Card | J66: Delivered | K66: 886.26 | M66: =IF(OR(F66="",F66="Nan"),"Missing",IF(PROPER(TRIM(messy_ecommerce_sales_data__27[[#This Row],[ Category]]))="Electronic","Electronics",PROPER(TRIM(messy_ecommerce_sales_data__27[[#This Row],[ Category]])))) -> Clothing | N66: 45604 | O66: =IF(LEN(TRIM(messy_ecommerce_sales_data__27[[#This Row],[Quantity]])) = 0, "Missing",IFERROR(VALUE(messy_ecommerce_sales_data__27[[#This Row],[Quantity]]),"Invalid")) -> 2 | P66: =IFERROR(VALUE(SUBSTITUTE(SUBSTITUTE(H66,"$",""), ".",",")),"Invalid") -> 443.13 | Q66: =IF(LEN(TRIM(messy_ecommerce_sales_data__27[[#This Row],[Total]])) = 0, "Missing",IFERROR(VALUE(SUBSTITUTE(SUBSTITUTE(messy_ecommerce_sales_data__27[[#This Row],[Total]],"$",""), ".",",")),"Invalid")) -> 886.26 | R66: =IFERROR(O66*P66, "Cannot Calculate") -> 886.26 | S66: =IF(AND(ISNUMBER(R66),ISNUMBER(Q66)),IF(ROUND(R66,2)=ROUND(Q66,2),"OK","Mismatch"),"No Data") -> OK
A67: 166 | B67: Customer_166 | C67: ORD-97756 | D67: 7/3/2025 | E67: T-shirt | F67: electronics | G67: 2 | H67: 569.38 | I67: Cash on Delivery | J67: Shipped | K67: 1138.76 | M67: =IF(OR(F67="",F67="Nan"),"Missing",IF(PROPER(TRIM(messy_ecommerce_sales_data__27[[#This Row],[ Category]]))="Electronic","Electronics",PROPER(TRIM(messy_ecommerce_sales_data__27[[#This Row],[ Category]])))) -> Electronics | N67: 45841 | O67: =IF(LEN(TRIM(messy_ecommerce_sales_data__27[[#This Row],[Quantity]])) = 0, "Missing",IFERROR(VALUE(messy_ecommerce_sales_data__27[[#This Row],[Quantity]]),"Invalid")) -> 2 | P67: =IFERROR(VALUE(SUBSTITUTE(SUBSTITUTE(H67,"$",""), ".",",")),"Invalid") -> 569.38 | Q67: =IF(LEN(TRIM(messy_ecommerce_sales_data__27[[#This Row],[Total]])) = 0, "Missing",IFERROR(VALUE(SUBSTITUTE(SUBSTITUTE(messy_ecommerce_sales_data__27[[#This Row],[Total]],"$",""), ".",",")),"Invalid")) -> 1138.76 | R67: =IFERROR(O67*P67, "Cannot Calculate") -> 1138.76 | S67: =IF(AND(ISNUMBER(R67),ISNUMBER(Q67)),IF(ROUND(R67,2)=ROUND(Q67,2),"OK","Mismatch"),"No Data") -> OK
A68: 167 | B68: Customer_167 | C68: ORD-30329 | D68: 8/7/2025 | E68: Basketball | F68: Sports | H68: 593.93 | I68: Cash on Delivery | J68: Processing | M68: =IF(OR(F68="",F68="Nan"),"Missing",IF(PROPER(TRIM(messy_ecommerce_sales_data__27[[#This Row],[ Category]]))="Electronic","Electronics",PROPER(TRIM(messy_ecommerce_sales_data__27[[#This Row],[ Category]])))) -> Sports | N68: 45876 | O68: =IF(LEN(TRIM(messy_ecommerce_sales_data__27[[#This Row],[Quantity]])) = 0, "Missing",IFERROR(VALUE(messy_ecommerce_sales_data__27[[#This Row],[Quantity]]),"Invalid")) -> Missing | P68: =IFERROR(VALUE(SUBSTITUTE(SUBSTITUTE(H68,"$",""), ".",",")),"Invalid") -> 593.93 | Q68: =IF(LEN(TRIM(messy_ecommerce_sales_data__27[[#This Row],[Total]])) = 0, "Missing",IFERROR(VALUE(SUBSTITUTE(SUBSTITUTE(messy_ecommerce_sales_data__27[[#This Row],[Total]],"$",""), ".",",")),"Invalid")) -> Missing | R68: =IFERROR(O68*P68, "Cannot Calculate") -> Cannot Calculate | S68: =IF(AND(ISNUMBER(R68),ISNUMBER(Q68)),IF(ROUND(R68,2)=ROUND(Q68,2),"OK","Mismatch"),"No Data") -> No Data
A69: 168 | B69: Customer_168 | C69: ORD-53430 | D69: 11/4/2025 | E69: Biography | F69: Books | G69: 2 | H69: 141.49 | I69: PayPal | J69: Cancelled | K69: 282.98 | M69: =IF(OR(F69="",F69="Nan"),"Missing",IF(PROPER(TRIM(messy_ecommerce_sales_data__27[[#This Row],[ Category]]))="Electronic","Electronics",PROPER(TRIM(messy_ecommerce_sales_data__27[[#This Row],[ Category]])))) -> Books | N69: 45965 | O69: =IF(LEN(TRIM(messy_ecommerce_sales_data__27[[#This Row],[Quantity]])) = 0, "Missing",IFERROR(VALUE(messy_ecommerce_sales_data__27[[#This Row],[Quantity]]),"Invalid")) -> 2 | P69: =IFERROR(VALUE(SUBSTITUTE(SUBSTITUTE(H69,"$",""), ".",",")),"Invalid") -> 141.49 | Q69: =IF(LEN(TRIM(messy_ecommerce_sales_data__27[[#This Row],[Total]])) = 0, "Missing",IFERROR(VALUE(SUBSTITUTE(SUBSTITUTE(messy_ecommerce_sales_data__27[[#This Row],[Total]],"$",""), ".",",")),"Invalid")) -> 282.98 | R69: =IFERROR(O69*P69, "Cannot Calculate") -> 282.98 | S69: =IF(AND(ISNUMBER(R69),ISNUMBER(Q69)),IF(ROUND(R69,2)=ROUND(Q69,2),"OK","Mismatch"),"No Data") -> OK
A70: 169 | B70: Customer_169 | C70: ORD-75539 | D70: 8/12/2025 | E70: Basketball | F70: Sports | G70: 1 | H70: 582.13 | I70: Credit Card | J70: Returned | K70: 582.13 | M70: =IF(OR(F70="",F70="Nan"),"Missing",IF(PROPER(TRIM(messy_ecommerce_sales_data__27[[#This Row],[ Category]]))="Electronic","Electronics",PROPER(TRIM(messy_ecommerce_sales_data__27[[#This Row],[ Category]])))) -> Sports | N70: 45881 | O70: =IF(LEN(TRIM(messy_ecommerce_sales_data__27[[#This Row],[Quantity]])) = 0, "Missing",IFERROR(VALUE(messy_ecommerce_sales_data__27[[#This Row],[Quantity]]),"Invalid")) -> 1 | P70: =IFERROR(VALUE(SUBSTITUTE(SUBSTITUTE(H70,"$",""), ".",",")),"Invalid") -> 582.13 | Q70: =IF(LEN(TRIM(messy_ecommerce_sales_data__27[[#This Row],[Total]])) = 0, "Missing",IFERROR(VALUE(SUBSTITUTE(SUBSTITUTE(messy_ecommerce_sales_data__27[[#This Row],[Total]],"$",""), ".",",")),"Invalid")) -> 582.13 | R70: =IFERROR(O70*P70, "Cannot Calculate") -> 582.13 | S70: =IF(AND(ISNUMBER(R70),ISNUMBER(Q70)),IF(ROUND(R70,2)=ROUND(Q70,2),"OK","Mismatch"),"No Data") -> OK
A71: 170 | B71: Customer_170 | C71: ORD-21530 | D71: 10/3/2025 | E71: Jeans | F71: Clothing | G71: 5 | H71: 741.63 | I71: Bank Transfer | J71: Processing | K71: 3708.15 | M71: =IF(OR(F71="",F71="Nan"),"Missing",IF(PROPER(TRIM(messy_ecommerce_sales_data__27[[#This Row],[ Category]]))="Electronic","Electronics",PROPER(TRIM(messy_ecommerce_sales_data__27[[#This Row],[ Category]])))) -> Clothing | N71: 45933 | O71: =IF(LEN(TRIM(messy_ecommerce_sales_data__27[[#This Row],[Quantity]])) = 0, "Missing",IFERROR(VALUE(messy_ecommerce_sales_data__27[[#This Row],[Quantity]]),"Invalid")) -> 5 | P71: =IFERROR(VALUE(SUBSTITUTE(SUBSTITUTE(H71,"$",""), ".",",")),"Invalid") -> 741.63 | Q71: =IF(LEN(TRIM(messy_ecommerce_sales_data__27[[#This Row],[Total]])) = 0, "Missing",IFERROR(VALUE(SUBSTITUTE(SUBSTITUTE(messy_ecommerce_sales_data__27[[#This Row],[Total]],"$",""), ".",",")),"Invalid")) -> 3708.15 | R71: =IFERROR(O71*P71, "Cannot Calculate") -> 3708.15 | S71: =IF(AND(ISNUMBER(R71),ISNUMBER(Q71)),IF(ROUND(R71,2)=ROUND(Q71,2),"OK","Mismatch"),"No Data") -> OK
A72: 171 | B72: Customer_171 | C72: ORD-99790 | D72: 12/6/2024 | E72: Shoes | F72: Clothing | G72: 3 | H72: 688.68 | I72: PayPal | J72: Processing | K72: 2066.04 | M72: =IF(OR(F72="",F72="Nan"),"Missing",IF(PROPER(TRIM(messy_ecommerce_sales_data__27[[#This Row],[ Category]]))="Electronic","Electronics",PROPER(TRIM(messy_ecommerce_sales_data__27[[#This Row],[ Category]])))) -> Clothing | N72: 45632 | O72: =IF(LEN(TRIM(messy_ecommerce_sales_data__27[[#This Row],[Quantity]])) = 0, "Missing",IFERROR(VALUE(messy_ecommerce_sales_data__27[[#This Row],[Quantity]]),"Invalid")) -> 3 | P72: =IFERROR(VALUE(SUBSTITUTE(SUBSTITUTE(H72,"$",""), ".",",")),"Invalid") -> 688.68 | Q72: =IF(LEN(TRIM(messy_ecommerce_sales_data__27[[#This Row],[Total]])) = 0, "Missing",IFERROR(VALUE(SUBSTITUTE(SUBSTITUTE(messy_ecommerce_sales_data__27[[#This Row],[Total]],"$",""), ".",",")),"Invalid")) -> 2066.04 | R72: =IFERROR(O72*P72, "Cannot Calculate") -> 2066.04 | S72: =IF(AND(ISNUMBER(R72),ISNUMBER(Q72)),IF(ROUND(R72,2)=ROUND(Q72,2),"OK","Mismatch"),"No Data") -> OK
A73: 172 | B73: Customer_172 | C73: ORD-48008 | D73: 11/18/2024 | E73: Comics | F73: Books | G73: 2 | H73: 942.76 | I73: Bank Transfer | J73: Returned | K73: 1885.52 | M73: =IF(OR(F73="",F73="Nan"),"Missing",IF(PROPER(TRIM(messy_ecommerce_sales_data__27[[#This Row],[ Category]]))="Electronic","Electronics",PROPER(TRIM(messy_ecommerce_sales_data__27[[#This Row],[ Category]])))) -> Books | N73: 45614 | O73: =IF(LEN(TRIM(messy_ecommerce_sales_data__27[[#This Row],[Quantity]])) = 0, "Missing",IFERROR(VALUE(messy_ecommerce_sales_data__27[[#This Row],[Quantity]]),"Invalid")) -> 2 | P73: =IFERROR(VALUE(SUBSTITUTE(SUBSTITUTE(H73,"$",""), ".",",")),"Invalid") -> 942.76 | Q73: =IF(LEN(TRIM(messy_ecommerce_sales_data__27[[#This Row],[Total]])) = 0, "Missing",IFERROR(VALUE(SUBSTITUTE(SUBSTITUTE(messy_ecommerce_sales_data__27[[#This Row],[Total]],"$",""), ".",",")),"Invalid")) -> 1885.52 | R73: =IFERROR(O73*P73, "Cannot Calculate") -> 1885.52 | S73: =IF(AND(ISNUMBER(R73),ISNUMBER(Q73)),IF(ROUND(R73,2)=ROUND(Q73,2),"OK","Mismatch"),"No Data") -> OK
A74: 173 | B74: Customer_173 | C74: ORD-42171 | D74: 10/11/2025 | E74: Lamp | F74: Home | G74: 5 | H74: 351.89 | I74: Credit Card | J74: Shipped | K74: 1759.45 | M74: =IF(OR(F74="",F74="Nan"),"Missing",IF(PROPER(TRIM(messy_ecommerce_sales_data__27[[#This Row],[ Category]]))="Electronic","Electronics",PROPER(TRIM(messy_ecommerce_sales_data__27[[#This Row],[ Category]])))) -> Home | N74: 45941 | O74: =IF(LEN(TRIM(messy_ecommerce_sales_data__27[[#This Row],[Quantity]])) = 0, "Missing",IFERROR(VALUE(messy_ecommerce_sales_data__27[[#This Row],[Quantity]]),"Invalid")) -> 5 | P74: =IFERROR(VALUE(SUBSTITUTE(SUBSTITUTE(H74,"$",""), ".",",")),"Invalid") -> 351.89 | Q74: =IF(LEN(TRIM(messy_ecommerce_sales_data__27[[#This Row],[Total]])) = 0, "Missing",IFERROR(VALUE(SUBSTITUTE(SUBSTITUTE(messy_ecommerce_sales_data__27[[#This Row],[Total]],"$",""), ".",",")),"Invalid")) -> 1759.45 | R74: =IFERROR(O74*P74, "Cannot Calculate") -> 1759.45 | S74: =IF(AND(ISNUMBER(R74),ISNUMBER(Q74)),IF(ROUND(R74,2)=ROUND(Q74,2),"OK","Mismatch"),"No Data") -> OK
A75: 174 | B75: Customer_174 | C75: ORD-16766 | D75: 9/20/2025 | E75: Microwave | F75: ELECTRONICS | G75: 4 | H75: 187.48 | I75: Credit Card | J75: Returned | K75: 749.92 | M75: =IF(OR(F75="",F75="Nan"),"Missing",IF(PROPER(TRIM(messy_ecommerce_sales_data__27[[#This Row],[ Category]]))="Electronic","Electronics",PROPER(TRIM(messy_ecommerce_sales_data__27[[#This Row],[ Category]])))) -> Electronics | N75: 45920 | O75: =IF(LEN(TRIM(messy_ecommerce_sales_data__27[[#This Row],[Quantity]])) = 0, "Missing",IFERROR(VALUE(messy_ecommerce_sales_data__27[[#This Row],[Quantity]]),"Invalid")) -> 4 | P75: =IFERROR(VALUE(SUBSTITUTE(SUBSTITUTE(H75,"$",""), ".",",")),"Invalid") -> 187.48 | Q75: =IF(LEN(TRIM(messy_ecommerce_sales_data__27[[#This Row],[Total]])) = 0, "Missing",IFERROR(VALUE(SUBSTITUTE(SUBSTITUTE(messy_ecommerce_sales_data__27[[#This Row],[Total]],"$",""), ".",",")),"Invalid")) -> 749.92 | R75: =IFERROR(O75*P75, "Cannot Calculate") -> 749.92 | S75: =IF(AND(ISNUMBER(R75),ISNUMBER(Q75)),IF(ROUND(R75,2)=ROUND(Q75,2),"OK","Mismatch"),"No Data") -> OK
A76: 175 | B76: Customer_175 | C76: ORD-56651 | D76: 2/24/2025 | E76: Headphones | F76: Electronics | G76: 1 | H76: 111.36 | I76: Credit Card | J76: Processing | K76: 111.36 | M76: =IF(OR(F76="",F76="Nan"),"Missing",IF(PROPER(TRIM(messy_ecommerce_sales_data__27[[#This Row],[ Category]]))="Electronic","Electronics",PROPER(TRIM(messy_ecommerce_sales_data__27[[#This Row],[ Category]])))) -> Electronics | N76: 45712 | O76: =IF(LEN(TRIM(messy_ecommerce_sales_data__27[[#This Row],[Quantity]])) = 0, "Missing",IFERROR(VALUE(messy_ecommerce_sales_data__27[[#This Row],[Quantity]]),"Invalid")) -> 1 | P76: =IFERROR(VALUE(SUBSTITUTE(SUBSTITUTE(H76,"$",""), ".",",")),"Invalid") -> 111.36 | Q76: =IF(LEN(TRIM(messy_ecommerce_sales_data__27[[#This Row],[Total]])) = 0, "Missing",IFERROR(VALUE(SUBSTITUTE(SUBSTITUTE(messy_ecommerce_sales_data__27[[#This Row],[Total]],"$",""), ".",",")),"Invalid")) -> 111.36 | R76: =IFERROR(O76*P76, "Cannot Calculate") -> 111.36 | S76: =IF(AND(ISNUMBER(R76),ISNUMBER(Q76)),IF(ROUND(R76,2)=ROUND(Q76,2),"OK","Mismatch"),"No Data") -> OK
A77: 176 | B77: Customer_176 | C77: ORD-95794 | D77: 7/22/2025 | E77: Comics | F77: Books | G77: 5 | H77: 530.52 | I77: Cash on Delivery | J77: Shipped | K77: 2652.6 | M77: =IF(OR(F77="",F77="Nan"),"Missing",IF(PROPER(TRIM(messy_ecommerce_sales_data__27[[#This Row],[ Category]]))="Electronic","Electronics",PROPER(TRIM(messy_ecommerce_sales_data__27[[#This Row],[ Category]])))) -> Books | N77: 45860 | O77: =IF(LEN(TRIM(messy_ecommerce_sales_data__27[[#This Row],[Quantity]])) = 0, "Missing",IFERROR(VALUE(messy_ecommerce_sales_data__27[[#This Row],[Quantity]]),"Invalid")) -> 5 | P77: =IFERROR(VALUE(SUBSTITUTE(SUBSTITUTE(H77,"$",""), ".",",")),"Invalid") -> 530.52 | Q77: =IF(LEN(TRIM(messy_ecommerce_sales_data__27[[#This Row],[Total]])) = 0, "Missing",IFERROR(VALUE(SUBSTITUTE(SUBSTITUTE(messy_ecommerce_sales_data__27[[#This Row],[Total]],"$",""), ".",",")),"Invalid")) -> 2652.6 | R77: =IFERROR(O77*P77, "Cannot Calculate") -> 2652.6 | S77: =IF(AND(ISNUMBER(R77),ISNUMBER(Q77)),IF(ROUND(R77,2)=ROUND(Q77,2),"OK","Mismatch"),"No Data") -> OK
A78: 177 | B78: Customer_177 | C78: ORD-64136 | D78: 7/28/2025 | E78: Laptop | F78: Electronics | G78: 1 | H78: 69.48 | I78: Bank Transfer | J78: Returned | K78: 69.48 | M78: =IF(OR(F78="",F78="Nan"),"Missing",IF(PROPER(TRIM(messy_ecommerce_sales_data__27[[#This Row],[ Category]]))="Electronic","Electronics",PROPER(TRIM(messy_ecommerce_sales_data__27[[#This Row],[ Category]])))) -> Electronics | N78: 45866 | O78: =IF(LEN(TRIM(messy_ecommerce_sales_data__27[[#This Row],[Quantity]])) = 0, "Missing",IFERROR(VALUE(messy_ecommerce_sales_data__27[[#This Row],[Quantity]]),"Invalid")) -> 1 | P78: =IFERROR(VALUE(SUBSTITUTE(SUBSTITUTE(H78,"$",""), ".",",")),"Invalid") -> 69.48 | Q78: =IF(LEN(TRIM(messy_ecommerce_sales_data__27[[#This Row],[Total]])) = 0, "Missing",IFERROR(VALUE(SUBSTITUTE(SUBSTITUTE(messy_ecommerce_sales_data__27[[#This Row],[Total]],"$",""), ".",",")),"Invalid")) -> 69.48 | R78: =IFERROR(O78*P78, "Cannot Calculate") -> 69.48 | S78: =IF(AND(ISNUMBER(R78),ISNUMBER(Q78)),IF(ROUND(R78,2)=ROUND(Q78,2),"OK","Mismatch"),"No Data") -> OK
A79: 178 | B79: Customer_178 | C79: ORD-89906 | D79: 9/18/2025 | E79: Tennis Racket | F79: Sports | G79: 3 | H79: 472.14 | I79: PayPal | J79: Returned | K79: 1416.42 | M79: =IF(OR(F79="",F79="Nan"),"Missing",IF(PROPER(TRIM(messy_ecommerce_sales_data__27[[#This Row],[ Category]]))="Electronic","Electronics",PROPER(TRIM(messy_ecommerce_sales_data__27[[#This Row],[ Category]])))) -> Sports | N79: 45918 | O79: =IF(LEN(TRIM(messy_ecommerce_sales_data__27[[#This Row],[Quantity]])) = 0, "Missing",IFERROR(VALUE(messy_ecommerce_sales_data__27[[#This Row],[Quantity]]),"Invalid")) -> 3 | P79: =IFERROR(VALUE(SUBSTITUTE(SUBSTITUTE(H79,"$",""), ".",",")),"Invalid") -> 472.14 | Q79: =IF(LEN(TRIM(messy_ecommerce_sales_data__27[[#This Row],[Total]])) = 0, "Missing",IFERROR(VALUE(SUBSTITUTE(SUBSTITUTE(messy_ecommerce_sales_data__27[[#This Row],[Total]],"$",""), ".",",")),"Invalid")) -> 1416.42 | R79: =IFERROR(O79*P79, "Cannot Calculate") -> 1416.42 | S79: =IF(AND(ISNUMBER(R79),ISNUMBER(Q79)),IF(ROUND(R79,2)=ROUND(Q79,2),"OK","Mismatch"),"No Data") -> OK
A80: 179 | B80: Customer_179 | C80: ORD-99328 | D80: 9/3/2025 | E80: Yoga Mat | F80: Sports | G80: 3 | H80: 868.67 | I80: PayPal | J80: Delivered | K80: 2606.01 | M80: =IF(OR(F80="",F80="Nan"),"Missing",IF(PROPER(TRIM(messy_ecommerce_sales_data__27[[#This Row],[ Category]]))="Electronic","Electronics",PROPER(TRIM(messy_ecommerce_sales_data__27[[#This Row],[ Category]])))) -> Sports | N80: 45903 | O80: =IF(LEN(TRIM(messy_ecommerce_sales_data__27[[#This Row],[Quantity]])) = 0, "Missing",IFERROR(VALUE(messy_ecommerce_sales_data__27[[#This Row],[Quantity]]),"Invalid")) -> 3 | P80: =IFERROR(VALUE(SUBSTITUTE(SUBSTITUTE(H80,"$",""), ".",",")),"Invalid") -> 868.67 | Q80: =IF(LEN(TRIM(messy_ecommerce_sales_data__27[[#This Row],[Total]])) = 0, "Missing",IFERROR(VALUE(SUBSTITUTE(SUBSTITUTE(messy_ecommerce_sales_data__27[[#This Row],[Total]],"$",""), ".",",")),"Invalid")) -> 2606.01 | R80: =IFERROR(O80*P80, "Cannot Calculate") -> 2606.01 | S80: =IF(AND(ISNUMBER(R80),ISNUMBER(Q80)),IF(ROUND(R80,2)=ROUND(Q80,2),"OK","Mismatch"),"No Data") -> OK
A81: 180 | B81: Customer_180 | C81: ORD-86629 | D81: 3/26/2025 | E81: Laptop | G81: 2 | H81: 418.38 | I81: Credit Card | J81: Processing | K81: 836.76 | M81: =IF(OR(F81="",F81="Nan"),"Missing",IF(PROPER(TRIM(messy_ecommerce_sales_data__27[[#This Row],[ Category]]))="Electronic","Electronics",PROPER(TRIM(messy_ecommerce_sales_data__27[[#This Row],[ Category]])))) -> Missing | N81: 45742 | O81: =IF(LEN(TRIM(messy_ecommerce_sales_data__27[[#This Row],[Quantity]])) = 0, "Missing",IFERROR(VALUE(messy_ecommerce_sales_data__27[[#This Row],[Quantity]]),"Invalid")) -> 2 | P81: =IFERROR(VALUE(SUBSTITUTE(SUBSTITUTE(H81,"$",""), ".",",")),"Invalid") -> 418.38 | Q81: =IF(LEN(TRIM(messy_ecommerce_sales_data__27[[#This Row],[Total]])) = 0, "Missing",IFERROR(VALUE(SUBSTITUTE(SUBSTITUTE(messy_ecommerce_sales_data__27[[#This Row],[Total]],"$",""), ".",",")),"Invalid")) -> 836.76 | R81: =IFERROR(O81*P81, "Cannot Calculate") -> 836.76 | S81: =IF(AND(ISNUMBER(R81),ISNUMBER(Q81)),IF(ROUND(R81,2)=ROUND(Q81,2),"OK","Mismatch"),"No Data") -> OK
A82: 181 | B82: Customer_181 | C82: ORD-54481 | D82: 12/29/2024 | E82: Smartphone | F82: nan | G82: 1 | H82: 266.48 | I82: Cash on Delivery | J82: Cancelled | K82: 266.48 | M82: =IF(OR(F82="",F82="Nan"),"Missing",IF(PROPER(TRIM(messy_ecommerce_sales_data__27[[#This Row],[ Category]]))="Electronic","Electronics",PROPER(TRIM(messy_ecommerce_sales_data__27[[#This Row],[ Category]])))) -> Missing | N82: 45655 | O82: =IF(LEN(TRIM(messy_ecommerce_sales_data__27[[#This Row],[Quantity]])) = 0, "Missing",IFERROR(VALUE(messy_ecommerce_sales_data__27[[#This Row],[Quantity]]),"Invalid")) -> 1 | P82: =IFERROR(VALUE(SUBSTITUTE(SUBSTITUTE(H82,"$",""), ".",",")),"Invalid") -> 266.48 | Q82: =IF(LEN(TRIM(messy_ecommerce_sales_data__27[[#This Row],[Total]])) = 0, "Missing",IFERROR(VALUE(SUBSTITUTE(SUBSTITUTE(messy_ecommerce_sales_data__27[[#This Row],[Total]],"$",""), ".",",")),"Invalid")) -> 266.48 | R82: =IFERROR(O82*P82, "Cannot Calculate") -> 266.48 | S82: =IF(AND(ISNUMBER(R82),ISNUMBER(Q82)),IF(ROUND(R82,2)=ROUND(Q82,2),"OK","Mismatch"),"No Data") -> OK
A83: 182 | B83: Customer_182 | C83: ORD-79672 | D83: 8/3/2025 | E83: Shoes | G83: 4 | H83: 538.35 | I83: PayPal | J83: Processing | K83: 2153.4 | M83: =IF(OR(F83="",F83="Nan"),"Missing",IF(PROPER(TRIM(messy_ecommerce_sales_data__27[[#This Row],[ Category]]))="Electronic","Electronics",PROPER(TRIM(messy_ecommerce_sales_data__27[[#This Row],[ Category]])))) -> Missing | N83: 45872 | O83: =IF(LEN(TRIM(messy_ecommerce_sales_data__27[[#This Row],[Quantity]])) = 0, "Missing",IFERROR(VALUE(messy_ecommerce_sales_data__27[[#This Row],[Quantity]]),"Invalid")) -> 4 | P83: =IFERROR(VALUE(SUBSTITUTE(SUBSTITUTE(H83,"$",""), ".",",")),"Invalid") -> 538.35 | Q83: =IF(LEN(TRIM(messy_ecommerce_sales_data__27[[#This Row],[Total]])) = 0, "Missing",IFERROR(VALUE(SUBSTITUTE(SUBSTITUTE(messy_ecommerce_sales_data__27[[#This Row],[Total]],"$",""), ".",",")),"Invalid")) -> 2153.4 | R83: =IFERROR(O83*P83, "Cannot Calculate") -> 2153.4 | S83: =IF(AND(ISNUMBER(R83),ISNUMBER(Q83)),IF(ROUND(R83,2)=ROUND(Q83,2),"OK","Mismatch"),"No Data") -> OK
A84: 183 | B84: Customer_183 | C84: ORD-20916 | D84: 3/10/2025 | E84: Shoes | F84: Clothing | G84: 5 | I84: Cash on Delivery | J84: Returned | M84: =IF(OR(F84="",F84="Nan"),"Missing",IF(PROPER(TRIM(messy_ecommerce_sales_data__27[[#This Row],[ Category]]))="Electronic","Electronics",PROPER(TRIM(messy_ecommerce_sales_data__27[[#This Row],[ Category]])))) -> Clothing | N84: 45726 | O84: =IF(LEN(TRIM(messy_ecommerce_sales_data__27[[#This Row],[Quantity]])) = 0, "Missing",IFERROR(VALUE(messy_ecommerce_sales_data__27[[#This Row],[Quantity]]),"Invalid")) -> 5 | P84: =IFERROR(VALUE(SUBSTITUTE(SUBSTITUTE(H84,"$",""), ".",",")),"Invalid") -> Invalid | Q84: =IF(LEN(TRIM(messy_ecommerce_sales_data__27[[#This Row],[Total]])) = 0, "Missing",IFERROR(VALUE(SUBSTITUTE(SUBSTITUTE(messy_ecommerce_sales_data__27[[#This Row],[Total]],"$",""), ".",",")),"Invalid")) -> Missing | R84: =IFERROR(O84*P84, "Cannot Calculate") -> Cannot Calculate | S84: =IF(AND(ISNUMBER(R84),ISNUMBER(Q84)),IF(ROUND(R84,2)=ROUND(Q84,2),"OK","Mismatch"),"No Data") -> No Data
A85: 184 | B85: Customer_184 | C85: ORD-67799 | D85: 2/15/2025 | E85: Jeans | G85: 4 | H85: 101.19 | I85: Bank Transfer | J85: Processing | K85: 404.76 | M85: =IF(OR(F85="",F85="Nan"),"Missing",IF(PROPER(TRIM(messy_ecommerce_sales_data__27[[#This Row],[ Category]]))="Electronic","Electronics",PROPER(TRIM(messy_ecommerce_sales_data__27[[#This Row],[ Category]])))) -> Missing | N85: 45703 | O85: =IF(LEN(TRIM(messy_ecommerce_sales_data__27[[#This Row],[Quantity]])) = 0, "Missing",IFERROR(VALUE(messy_ecommerce_sales_data__27[[#This Row],[Quantity]]),"Invalid")) -> 4 | P85: =IFERROR(VALUE(SUBSTITUTE(SUBSTITUTE(H85,"$",""), ".",",")),"Invalid") -> 101.19 | Q85: =IF(LEN(TRIM(messy_ecommerce_sales_data__27[[#This Row],[Total]])) = 0, "Missing",IFERROR(VALUE(SUBSTITUTE(SUBSTITUTE(messy_ecommerce_sales_data__27[[#This Row],[Total]],"$",""), ".",",")),"Invalid")) -> 404.76 | R85: =IFERROR(O85*P85, "Cannot Calculate") -> 404.76 | S85: =IF(AND(ISNUMBER(R85),ISNUMBER(Q85)),IF(ROUND(R85,2)=ROUND(Q85,2),"OK","Mismatch"),"No Data") -> OK
A86: 185 | B86: Customer_185 | C86: ORD-57123 | D86: 8/14/2025 | E86: Football | F86: Sports | G86: 2 | H86: 730.92 | I86: Cash on Delivery | J86: Cancelled | K86: 1023.288 | M86: =IF(OR(F86="",F86="Nan"),"Missing",IF(PROPER(TRIM(messy_ecommerce_sales_data__27[[#This Row],[ Category]]))="Electronic","Electronics",PROPER(TRIM(messy_ecommerce_sales_data__27[[#This Row],[ Category]])))) -> Sports | N86: 45883 | O86: =IF(LEN(TRIM(messy_ecommerce_sales_data__27[[#This Row],[Quantity]])) = 0, "Missing",IFERROR(VALUE(messy_ecommerce_sales_data__27[[#This Row],[Quantity]]),"Invalid")) -> 2 | P86: =IFERROR(VALUE(SUBSTITUTE(SUBSTITUTE(H86,"$",""), ".",",")),"Invalid") -> 730.92 | Q86: =IF(LEN(TRIM(messy_ecommerce_sales_data__27[[#This Row],[Total]])) = 0, "Missing",IFERROR(VALUE(SUBSTITUTE(SUBSTITUTE(messy_ecommerce_sales_data__27[[#This Row],[Total]],"$",""), ".",",")),"Invalid")) -> 1023.288 | R86: =IFERROR(O86*P86, "Cannot Calculate") -> 1461.84 | S86: =IF(AND(ISNUMBER(R86),ISNUMBER(Q86)),IF(ROUND(R86,2)=ROUND(Q86,2),"OK","Mismatch"),"No Data") -> Mismatch
A87: 186 | B87: Customer_186 | C87: ORD-90569 | D87: 10/6/2025 | E87: Laptop | F87: Electronics | G87: 1 | H87: 365.34 | I87: Bank Transfer | J87: Delivered | K87: 365.34 | M87: =IF(OR(F87="",F87="Nan"),"Missing",IF(PROPER(TRIM(messy_ecommerce_sales_data__27[[#This Row],[ Category]]))="Electronic","Electronics",PROPER(TRIM(messy_ecommerce_sales_data__27[[#This Row],[ Category]])))) -> Electronics | N87: 45936 | O87: =IF(LEN(TRIM(messy_ecommerce_sales_data__27[[#This Row],[Quantity]])) = 0, "Missing",IFERROR(VALUE(messy_ecommerce_sales_data__27[[#This Row],[Quantity]]),"Invalid")) -> 1 | P87: =IFERROR(VALUE(SUBSTITUTE(SUBSTITUTE(H87,"$",""), ".",",")),"Invalid") -> 365.34 | Q87: =IF(LEN(TRIM(messy_ecommerce_sales_data__27[[#This Row],[Total]])) = 0, "Missing",IFERROR(VALUE(SUBSTITUTE(SUBSTITUTE(messy_ecommerce_sales_data__27[[#This Row],[Total]],"$",""), ".",",")),"Invalid")) -> 365.34 | R87: =IFERROR(O87*P87, "Cannot Calculate") -> 365.34 | S87: =IF(AND(ISNUMBER(R87),ISNUMBER(Q87)),IF(ROUND(R87,2)=ROUND(Q87,2),"OK","Mismatch"),"No Data") -> OK
A88: 187 | B88: Customer_187 | C88: ORD-41292 | D88: 11/19/2024 | E88: Smartphone | F88: Electronics | G88: 3 | H88: 882.96 | I88: Bank Transfer | J88: Returned | K88: 2648.88 | M88: =IF(OR(F88="",F88="Nan"),"Missing",IF(PROPER(TRIM(messy_ecommerce_sales_data__27[[#This Row],[ Category]]))="Electronic","Electronics",PROPER(TRIM(messy_ecommerce_sales_data__27[[#This Row],[ Category]])))) -> Electronics | N88: 45615 | O88: =IF(LEN(TRIM(messy_ecommerce_sales_data__27[[#This Row],[Quantity]])) = 0, "Missing",IFERROR(VALUE(messy_ecommerce_sales_data__27[[#This Row],[Quantity]]),"Invalid")) -> 3 | P88: =IFERROR(VALUE(SUBSTITUTE(SUBSTITUTE(H88,"$",""), ".",",")),"Invalid") -> 882.96 | Q88: =IF(LEN(TRIM(messy_ecommerce_sales_data__27[[#This Row],[Total]])) = 0, "Missing",IFERROR(VALUE(SUBSTITUTE(SUBSTITUTE(messy_ecommerce_sales_data__27[[#This Row],[Total]],"$",""), ".",",")),"Invalid")) -> 2648.88 | R88: =IFERROR(O88*P88, "Cannot Calculate") -> 2648.88 | S88: =IF(AND(ISNUMBER(R88),ISNUMBER(Q88)),IF(ROUND(R88,2)=ROUND(Q88,2),"OK","Mismatch"),"No Data") -> OK
A89: 188 | B89: Customer_188 | C89: ORD-58590 | D89: 11/19/2024 | E89: Microwave | F89: Home | G89: 5 | H89: 504.05 | I89: Cash on Delivery | J89: Shipped | K89: 2520.25 | M89: =IF(OR(F89="",F89="Nan"),"Missing",IF(PROPER(TRIM(messy_ecommerce_sales_data__27[[#This Row],[ Category]]))="Electronic","Electronics",PROPER(TRIM(messy_ecommerce_sales_data__27[[#This Row],[ Category]])))) -> Home | N89: 45615 | O89: =IF(LEN(TRIM(messy_ecommerce_sales_data__27[[#This Row],[Quantity]])) = 0, "Missing",IFERROR(VALUE(messy_ecommerce_sales_data__27[[#This Row],[Quantity]]),"Invalid")) -> 5 | P89: =IFERROR(VALUE(SUBSTITUTE(SUBSTITUTE(H89,"$",""), ".",",")),"Invalid") -> 504.05 | Q89: =IF(LEN(TRIM(messy_ecommerce_sales_data__27[[#This Row],[Total]])) = 0, "Missing",IFERROR(VALUE(SUBSTITUTE(SUBSTITUTE(messy_ecommerce_sales_data__27[[#This Row],[Total]],"$",""), ".",",")),"Invalid")) -> 2520.25 | R89: =IFERROR(O89*P89, "Cannot Calculate") -> 2520.25 | S89: =IF(AND(ISNUMBER(R89),ISNUMBER(Q89)),IF(ROUND(R89,2)=ROUND(Q89,2),"OK","Mismatch"),"No Data") -> OK
A90: 189 | B90: Customer_189 | C90: ORD-30627 | D90: 8/14/2025 | E90: Lamp | F90: Home | G90: 1 | H90: 814.68 | I90: Cash on Delivery | J90: Returned | K90: 814.68 | M90: =IF(OR(F90="",F90="Nan"),"Missing",IF(PROPER(TRIM(messy_ecommerce_sales_data__27[[#This Row],[ Category]]))="Electronic","Electronics",PROPER(TRIM(messy_ecommerce_sales_data__27[[#This Row],[ Category]])))) -> Home | N90: 45883 | O90: =IF(LEN(TRIM(messy_ecommerce_sales_data__27[[#This Row],[Quantity]])) = 0, "Missing",IFERROR(VALUE(messy_ecommerce_sales_data__27[[#This Row],[Quantity]]),"Invalid")) -> 1 | P90: =IFERROR(VALUE(SUBSTITUTE(SUBSTITUTE(H90,"$",""), ".",",")),"Invalid") -> 814.68 | Q90: =IF(LEN(TRIM(messy_ecommerce_sales_data__27[[#This Row],[Total]])) = 0, "Missing",IFERROR(VALUE(SUBSTITUTE(SUBSTITUTE(messy_ecommerce_sales_data__27[[#This Row],[Total]],"$",""), ".",",")),"Invalid")) -> 814.68 | R90: =IFERROR(O90*P90, "Cannot Calculate") -> 814.68 | S90: =IF(AND(ISNUMBER(R90),ISNUMBER(Q90)),IF(ROUND(R90,2)=ROUND(Q90,2),"OK","Mismatch"),"No Data") -> OK
A91: 190 | B91: Customer_190 | C91: ORD-38469 | D91: 6/29/2025 | E91: Vacuum | F91: Home | G91: 1 | H91: 920.37 | I91: Bank Transfer | J91: Processing | K91: 920.37 | M91: =IF(OR(F91="",F91="Nan"),"Missing",IF(PROPER(TRIM(messy_ecommerce_sales_data__27[[#This Row],[ Category]]))="Electronic","Electronics",PROPER(TRIM(messy_ecommerce_sales_data__27[[#This Row],[ Category]])))) -> Home | N91: 45837 | O91: =IF(LEN(TRIM(messy_ecommerce_sales_data__27[[#This Row],[Quantity]])) = 0, "Missing",IFERROR(VALUE(messy_ecommerce_sales_data__27[[#This Row],[Quantity]]),"Invalid")) -> 1 | P91: =IFERROR(VALUE(SUBSTITUTE(SUBSTITUTE(H91,"$",""), ".",",")),"Invalid") -> 920.37 | Q91: =IF(LEN(TRIM(messy_ecommerce_sales_data__27[[#This Row],[Total]])) = 0, "Missing",IFERROR(VALUE(SUBSTITUTE(SUBSTITUTE(messy_ecommerce_sales_data__27[[#This Row],[Total]],"$",""), ".",",")),"Invalid")) -> 920.37 | R91: =IFERROR(O91*P91, "Cannot Calculate") -> 920.37 | S91: =IF(AND(ISNUMBER(R91),ISNUMBER(Q91)),IF(ROUND(R91,2)=ROUND(Q91,2),"OK","Mismatch"),"No Data") -> OK
A92: 191 | B92: Customer_191 | C92: ORD-41810 | D92: 7/18/2025 | E92: Fiction | F92: Books | G92: 2 | H92: 881.02 | I92: Cash on Delivery | J92: Returned | K92: 1762.04 | M92: =IF(OR(F92="",F92="Nan"),"Missing",IF(PROPER(TRIM(messy_ecommerce_sales_data__27[[#This Row],[ Category]]))="Electronic","Electronics",PROPER(TRIM(messy_ecommerce_sales_data__27[[#This Row],[ Category]])))) -> Books | N92: 45856 | O92: =IF(LEN(TRIM(messy_ecommerce_sales_data__27[[#This Row],[Quantity]])) = 0, "Missing",IFERROR(VALUE(messy_ecommerce_sales_data__27[[#This Row],[Quantity]]),"Invalid")) -> 2 | P92: =IFERROR(VALUE(SUBSTITUTE(SUBSTITUTE(H92,"$",""), ".",",")),"Invalid") -> 881.02 | Q92: =IF(LEN(TRIM(messy_ecommerce_sales_data__27[[#This Row],[Total]])) = 0, "Missing",IFERROR(VALUE(SUBSTITUTE(SUBSTITUTE(messy_ecommerce_sales_data__27[[#This Row],[Total]],"$",""), ".",",")),"Invalid")) -> 1762.04 | R92: =IFERROR(O92*P92, "Cannot Calculate") -> 1762.04 | S92: =IF(AND(ISNUMBER(R92),ISNUMBER(Q92)),IF(ROUND(R92,2)=ROUND(Q92,2),"OK","Mismatch"),"No Data") -> OK
A93: 192 | B93: Customer_192 | C93: ORD-35144 | D93: abc | E93: Jacket | F93: Clothing | G93: 4a | H93: 203.63 | I93: Credit Card | J93: Returned | M93: =IF(OR(F93="",F93="Nan"),"Missing",IF(PROPER(TRIM(messy_ecommerce_sales_data__27[[#This Row],[ Category]]))="Electronic","Electronics",PROPER(TRIM(messy_ecommerce_sales_data__27[[#This Row],[ Category]])))) -> Clothing | N93: Invalid | O93: =IF(LEN(TRIM(messy_ecommerce_sales_data__27[[#This Row],[Quantity]])) = 0, "Missing",IFERROR(VALUE(messy_ecommerce_sales_data__27[[#This Row],[Quantity]]),"Invalid")) -> Invalid | P93: =IFERROR(VALUE(SUBSTITUTE(SUBSTITUTE(H93,"$",""), ".",",")),"Invalid") -> 203.63 | Q93: =IF(LEN(TRIM(messy_ecommerce_sales_data__27[[#This Row],[Total]])) = 0, "Missing",IFERROR(VALUE(SUBSTITUTE(SUBSTITUTE(messy_ecommerce_sales_data__27[[#This Row],[Total]],"$",""), ".",",")),"Invalid")) -> Missing | R93: =IFERROR(O93*P93, "Cannot Calculate") -> Cannot Calculate | S93: =IF(AND(ISNUMBER(R93),ISNUMBER(Q93)),IF(ROUND(R93,2)=ROUND(Q93,2),"OK","Mismatch"),"No Data") -> No Data
A94: 193 | B94: Customer_193 | C94: ORD-42475 | D94: 6/6/2025 | E94: Basketball | H94: 522.02 | I94: PayPal | J94: Shipped | M94: =IF(OR(F94="",F94="Nan"),"Missing",IF(PROPER(TRIM(messy_ecommerce_sales_data__27[[#This Row],[ Category]]))="Electronic","Electronics",PROPER(TRIM(messy_ecommerce_sales_data__27[[#This Row],[ Category]])))) -> Missing | N94: 45814 | O94: =IF(LEN(TRIM(messy_ecommerce_sales_data__27[[#This Row],[Quantity]])) = 0, "Missing",IFERROR(VALUE(messy_ecommerce_sales_data__27[[#This Row],[Quantity]]),"Invalid")) -> Missing | P94: =IFERROR(VALUE(SUBSTITUTE(SUBSTITUTE(H94,"$",""), ".",",")),"Invalid") -> 522.02 | Q94: =IF(LEN(TRIM(messy_ecommerce_sales_data__27[[#This Row],[Total]])) = 0, "Missing",IFERROR(VALUE(SUBSTITUTE(SUBSTITUTE(messy_ecommerce_sales_data__27[[#This Row],[Total]],"$",""), ".",",")),"Invalid")) -> Missing | R94: =IFERROR(O94*P94, "Cannot Calculate") -> Cannot Calculate | S94: =IF(AND(ISNUMBER(R94),ISNUMBER(Q94)),IF(ROUND(R94,2)=ROUND(Q94,2),"OK","Mismatch"),"No Data") -> No Data
A95: 194 | B95: Customer_194 | C95: ORD-69764 | D95: 2/10/2025 | E95: Lamp | F95: Home | G95: 5 | H95: 944.54 | I95: Cash on Delivery | J95: Returned | K95: 4722.7 | M95: =IF(OR(F95="",F95="Nan"),"Missing",IF(PROPER(TRIM(messy_ecommerce_sales_data__27[[#This Row],[ Category]]))="Electronic","Electronics",PROPER(TRIM(messy_ecommerce_sales_data__27[[#This Row],[ Category]])))) -> Home | N95: 45698 | O95: =IF(LEN(TRIM(messy_ecommerce_sales_data__27[[#This Row],[Quantity]])) = 0, "Missing",IFERROR(VALUE(messy_ecommerce_sales_data__27[[#This Row],[Quantity]]),"Invalid")) -> 5 | P95: =IFERROR(VALUE(SUBSTITUTE(SUBSTITUTE(H95,"$",""), ".",",")),"Invalid") -> 944.54 | Q95: =IF(LEN(TRIM(messy_ecommerce_sales_data__27[[#This Row],[Total]])) = 0, "Missing",IFERROR(VALUE(SUBSTITUTE(SUBSTITUTE(messy_ecommerce_sales_data__27[[#This Row],[Total]],"$",""), ".",",")),"Invalid")) -> 4722.7 | R95: =IFERROR(O95*P95, "Cannot Calculate") -> 4722.7 | S95: =IF(AND(ISNUMBER(R95),ISNUMBER(Q95)),IF(ROUND(R95,2)=ROUND(Q95,2),"OK","Mismatch"),"No Data") -> OK
A96: 195 | B96: Customer_195 | C96: ORD-82876 | D96: 6/19/2025 | E96: Biography | F96: Books | G96: 5 | H96: 817.46 | I96: Cash on Delivery | J96: Returned | K96: 4087.3 | M96: =IF(OR(F96="",F96="Nan"),"Missing",IF(PROPER(TRIM(messy_ecommerce_sales_data__27[[#This Row],[ Category]]))="Electronic","Electronics",PROPER(TRIM(messy_ecommerce_sales_data__27[[#This Row],[ Category]])))) -> Books | N96: 45827 | O96: =IF(LEN(TRIM(messy_ecommerce_sales_data__27[[#This Row],[Quantity]])) = 0, "Missing",IFERROR(VALUE(messy_ecommerce_sales_data__27[[#This Row],[Quantity]]),"Invalid")) -> 5 | P96: =IFERROR(VALUE(SUBSTITUTE(SUBSTITUTE(H96,"$",""), ".",",")),"Invalid") -> 817.46 | Q96: =IF(LEN(TRIM(messy_ecommerce_sales_data__27[[#This Row],[Total]])) = 0, "Missing",IFERROR(VALUE(SUBSTITUTE(SUBSTITUTE(messy_ecommerce_sales_data__27[[#This Row],[Total]],"$",""), ".",",")),"Invalid")) -> 4087.3 | R96: =IFERROR(O96*P96, "Cannot Calculate") -> 4087.3 | S96: =IF(AND(ISNUMBER(R96),ISNUMBER(Q96)),IF(ROUND(R96,2)=ROUND(Q96,2),"OK","Mismatch"),"No Data") -> OK
A97: 196 | B97: Customer_196 | C97: ORD-78384 | D97: 12/23/2024 | E97: Vacuum | F97: Home | H97: abd | I97: PayPal | J97: Delivered | M97: =IF(OR(F97="",F97="Nan"),"Missing",IF(PROPER(TRIM(messy_ecommerce_sales_data__27[[#This Row],[ Category]]))="Electronic","Electronics",PROPER(TRIM(messy_ecommerce_sales_data__27[[#This Row],[ Category]])))) -> Home | N97: 45649 | O97: =IF(LEN(TRIM(messy_ecommerce_sales_data__27[[#This Row],[Quantity]])) = 0, "Missing",IFERROR(VALUE(messy_ecommerce_sales_data__27[[#This Row],[Quantity]]),"Invalid")) -> Missing | P97: =IFERROR(VALUE(SUBSTITUTE(SUBSTITUTE(H97,"$",""), ".",",")),"Invalid") -> Invalid | Q97: =IF(LEN(TRIM(messy_ecommerce_sales_data__27[[#This Row],[Total]])) = 0, "Missing",IFERROR(VALUE(SUBSTITUTE(SUBSTITUTE(messy_ecommerce_sales_data__27[[#This Row],[Total]],"$",""), ".",",")),"Invalid")) -> Missing | R97: =IFERROR(O97*P97, "Cannot Calculate") -> Cannot Calculate | S97: =IF(AND(ISNUMBER(R97),ISNUMBER(Q97)),IF(ROUND(R97,2)=ROUND(Q97,2),"OK","Mismatch"),"No Data") -> No Data
A98: 197 | B98: Customer_197 | C98: ORD-79139 | D98: 6/23/2025 | E98: Blender | F98: Home | G98: 1 | H98: 160.16 | I98: PayPal | J98: Cancelled | K98: 160.16 | M98: =IF(OR(F98="",F98="Nan"),"Missing",IF(PROPER(TRIM(messy_ecommerce_sales_data__27[[#This Row],[ Category]]))="Electronic","Electronics",PROPER(TRIM(messy_ecommerce_sales_data__27[[#This Row],[ Category]])))) -> Home | N98: 45831 | O98: =IF(LEN(TRIM(messy_ecommerce_sales_data__27[[#This Row],[Quantity]])) = 0, "Missing",IFERROR(VALUE(messy_ecommerce_sales_data__27[[#This Row],[Quantity]]),"Invalid")) -> 1 | P98: =IFERROR(VALUE(SUBSTITUTE(SUBSTITUTE(H98,"$",""), ".",",")),"Invalid") -> 160.16 | Q98: =IF(LEN(TRIM(messy_ecommerce_sales_data__27[[#This Row],[Total]])) = 0, "Missing",IFERROR(VALUE(SUBSTITUTE(SUBSTITUTE(messy_ecommerce_sales_data__27[[#This Row],[Total]],"$",""), ".",",")),"Invalid")) -> 160.16 | R98: =IFERROR(O98*P98, "Cannot Calculate") -> 160.16 | S98: =IF(AND(ISNUMBER(R98),ISNUMBER(Q98)),IF(ROUND(R98,2)=ROUND(Q98,2),"OK","Mismatch"),"No Data") -> OK
A99: 198 | B99: Customer_198 | C99: ORD-14608 | D99: 7/27/2025 | E99: Vacuum | G99: 2 | H99: 497.01 | I99: Cash on Delivery | J99: Shipped | K99: 994.02 | M99: =IF(OR(F99="",F99="Nan"),"Missing",IF(PROPER(TRIM(messy_ecommerce_sales_data__27[[#This Row],[ Category]]))="Electronic","Electronics",PROPER(TRIM(messy_ecommerce_sales_data__27[[#This Row],[ Category]])))) -> Missing | N99: 45865 | O99: =IF(LEN(TRIM(messy_ecommerce_sales_data__27[[#This Row],[Quantity]])) = 0, "Missing",IFERROR(VALUE(messy_ecommerce_sales_data__27[[#This Row],[Quantity]]),"Invalid")) -> 2 | P99: =IFERROR(VALUE(SUBSTITUTE(SUBSTITUTE(H99,"$",""), ".",",")),"Invalid") -> 497.01 | Q99: =IF(LEN(TRIM(messy_ecommerce_sales_data__27[[#This Row],[Total]])) = 0, "Missing",IFERROR(VALUE(SUBSTITUTE(SUBSTITUTE(messy_ecommerce_sales_data__27[[#This Row],[Total]],"$",""), ".",",")),"Invalid")) -> 994.02 | R99: =IFERROR(O99*P99, "Cannot Calculate") -> 994.02 | S99: =IF(AND(ISNUMBER(R99),ISNUMBER(Q99)),IF(ROUND(R99,2)=ROUND(Q99,2),"OK","Mismatch"),"No Data") -> OK
A100: 199 | B100: Customer_199 | C100: ORD-82922 | D100: 1/22/2025 | E100: Blender | F100: Home | G100: 5 | H100: 372.28 | I100: Credit Card | J100: Shipped | K100: 1861.4 | M100: =IF(OR(F100="",F100="Nan"),"Missing",IF(PROPER(TRIM(messy_ecommerce_sales_data__27[[#This Row],[ Category]]))="Electronic","Electronics",PROPER(TRIM(messy_ecommerce_sales_data__27[[#This Row],[ Category]])))) -> Home | N100: 45679 | O100: =IF(LEN(TRIM(messy_ecommerce_sales_data__27[[#This Row],[Quantity]])) = 0, "Missing",IFERROR(VALUE(messy_ecommerce_sales_data__27[[#This Row],[Quantity]]),"Invalid")) -> 5 | P100: =IFERROR(VALUE(SUBSTITUTE(SUBSTITUTE(H100,"$",""), ".",",")),"Invalid") -> 372.28 | Q100: =IF(LEN(TRIM(messy_ecommerce_sales_data__27[[#This Row],[Total]])) = 0, "Missing",IFERROR(VALUE(SUBSTITUTE(SUBSTITUTE(messy_ecommerce_sales_data__27[[#This Row],[Total]],"$",""), ".",",")),"Invalid")) -> 1861.4 | R100: =IFERROR(O100*P100, "Cannot Calculate") -> 1861.4 | S100: =IF(AND(ISNUMBER(R100),ISNUMBER(Q100)),IF(ROUND(R100,2)=ROUND(Q100,2),"OK","Mismatch"),"No Data") -> OK
A101: 142 | B101: Customer_142 | C101: ORD-69018 | D101: 10/30/2025 | E101: Shoes | F101: Clothing | G101: 5 | H101: 645.26 | I101: Credit Card | J101: Shipped | K101: 3226.3 | M101: =IF(OR(F101="",F101="Nan"),"Missing",IF(PROPER(TRIM(messy_ecommerce_sales_data__27[[#This Row],[ Category]]))="Electronic","Electronics",PROPER(TRIM(messy_ecommerce_sales_data__27[[#This Row],[ Category]])))) -> Clothing | N101: 45960 | O101: =IF(LEN(TRIM(messy_ecommerce_sales_data__27[[#This Row],[Quantity]])) = 0, "Missing",IFERROR(VALUE(messy_ecommerce_sales_data__27[[#This Row],[Quantity]]),"Invalid")) -> 5 | P101: =IFERROR(VALUE(SUBSTITUTE(SUBSTITUTE(H101,"$",""), ".",",")),"Invalid") -> 645.26 | Q101: =IF(LEN(TRIM(messy_ecommerce_sales_data__27[[#This Row],[Total]])) = 0, "Missing",IFERROR(VALUE(SUBSTITUTE(SUBSTITUTE(messy_ecommerce_sales_data__27[[#This Row],[Total]],"$",""), ".",",")),"Invalid")) -> 3226.3 | R101: =IFERROR(O101*P101, "Cannot Calculate") -> 3226.3 | S101: =IF(AND(ISNUMBER(R101),ISNUMBER(Q101)),IF(ROUND(R101,2)=ROUND(Q101,2),"OK","Mismatch"),"No Data") -> OK

Sheet 05_Clean_PowerQuery
A1: ID | B1: Customer_Name | C1: Order_ID | D1: Order_Date | E1: Product | F1: Category | G1: Quantity | H1: Price | I1: Payment_Method | J1: Status | K1: Total | L1: Total_Calc | M1: Total_Check
A2: 100 | B2: Customer_100 | C2: ORD-41285 | D2: 45618 | E2: Blender | F2: Home | G2: 3 | H2: 38 | I2: Cash on Delivery | J2: Shipped | K2: 114 | L2: 114 | M2: OK
A3: 101 | B3: Customer_101 | C3: ORD-35783 | D3: 45843 | E3: Smartphone | F3: Electronics | G3: 2 | I3: PayPal | J3: Processing | M3: No Data
A4: 102 | B4: Customer_102 | C4: ORD-84355 | D4: 45649 | E4: Tennis Racket | F4: Sports | G4: 1 | H4: 389.05 | I4: PayPal | J4: Delivered | K4: 389.05 | L4: 389.05 | M4: OK
A5: 103 | B5: Customer_103 | C5: ORD-57811 | D5: 45735 | E5: Science | F5: Books | G5: 5 | H5: 233.92 | I5: PayPal | J5: Processing | K5: 1169.6 | L5: 1169.6 | M5: OK
A6: 104 | B6: Customer_104 | C6: ORD-93614 | D6: 45950 | E6: Biography | F6: Books | G6: 1 | H6: 552.51 | I6: Cash on Delivery | J6: Processing | K6: 552.51 | L6: 552.51 | M6: OK
A7: 105 | B7: Customer_105 | C7: ORD-22442 | D7: 45616 | E7: Tennis Racket | F7: Sports | G7: 3 | H7: 122.06 | I7: Cash on Delivery | J7: Cancelled | K7: 366.18 | L7: 366.18 | M7: OK
A8: 106 | B8: Customer_106 | C8: ORD-25885 | D8: 45690 | E8: Blender | F8: Home | H8: 978.63 | I8: Bank Transfer | J8: Processing | M8: No Data
A9: 107 | B9: Customer_107 | C9: ORD-89122 | D9: 45660 | E9: Biography | F9: Books | G9: 5 | H9: 587.68 | I9: PayPal | J9: Returned | K9: 2938.4 | L9: 2938.4 | M9: OK
A10: 108 | B10: Customer_108 | C10: ORD-64400 | D10: 45953 | E10: Science | F10: Books | G10: 1 | H10: 600.29 | I10: Cash on Delivery | J10: Processing | K10: 600.29 | L10: 600.29 | M10: OK
A11: 109 | B11: Customer_109 | C11: ORD-18512 | D11: 45780 | E11: Tennis Racket | F11: Sports | G11: 5 | H11: 168.34 | I11: Credit Card | J11: Shipped | K11: 841.7 | L11: 841.7 | M11: OK
A12: 110 | B12: Customer_110 | C12: ORD-61020 | D12: 45926 | E12: Basketball | F12: Sports | G12: 5 | I12: Cash on Delivery | J12: Cancelled | M12: No Data
A13: 111 | B13: Customer_111 | C13: ORD-72349 | D13: 45952 | E13: Comics | F13: Books | G13: 2 | H13: 865.77 | I13: Credit Card | J13: Returned | K13: 1731.54 | L13: 1731.54 | M13: OK
A14: 112 | B14: Customer_112 | C14: ORD-80867 | D14: 45718 | E14: Shoes | F14: Clothing | G14: 4 | H14: 752.13 | I14: Bank Transfer | J14: Delivered | K14: 3008.52 | L14: 3008.52 | M14: OK
A15: 113 | B15: Customer_113 | C15: ORD-23994 | D15: 45862 | E15: Fiction | F15: Books | G15: 1 | H15: 411.81 | I15: Credit Card | J15: Processing | K15: 411.81 | L15: 411.81 | M15: OK
A16: 114 | B16: Customer_114 | C16: ORD-77417 | D16: 44931 | E16: Smartphone | F16: Electronics | G16: 2 | H16: 413.13 | I16: Cash on Delivery | J16: Shipped | K16: 826.26 | L16: 826.26 | M16: OK
A17: 115 | B17: Customer_115 | C17: ORD-72778 | D17: 45667 | E17: Fiction | F17: Books | G17: 2 | H17: 796.84 | I17: Cash on Delivery | J17: Returned | K17: 1115.576 | L17: 1593.68 | M17: Mismatch
A18: 116 | B18: Customer_116 | C18: ORD-63660 | D18: 45960 | E18: Microwave | F18: Home | G18: 4 | I18: Cash on Delivery | J18: Processing | M18: No Data
A19: 117 | B19: Customer_117 | C19: ORD-72751 | D19: 45700 | E19: Blender | F19: Electronics | G19: -2 | H19: 10000 | I19: Cash on Delivery | J19: Processing | K19: -20000 | L19: -20000 | M19: OK
A20: 118 | B20: Customer_118 | C20: ORD-96061 | D20: 45808 | E20: Science | F20: Books | G20: 5 | H20: 247.82 | I20: PayPal | J20: Processing | K20: 1239.1 | L20: 1239.1 | M20: OK
A21: 119 | B21: Customer_119 | C21: ORD-76016 | D21: 45645 | E21: Basketball | F21: Sports | G21: 4 | H21: 438.19 | I21: Cash on Delivery | J21: Processing | K21: 1752.76 | L21: 1752.76 | M21: OK
A22: 120 | B22: Customer_120 | C22: ORD-14659 | D22: 45821 | E22: Yoga Mat | F22: Electronics | G22: 5 | H22: 300 | I22: Credit Card | J22: Cancelled | L22: 1500 | M22: No Data
A23: 121 | B23: Customer_121 | C23: ORD-80067 | D23: 45941 | E23: Basketball | F23: Sports | G23: 4 | H23: 523.01 | I23: Credit Card | J23: Delivered | K23: 2092.04 | L23: 2092.04 | M23: OK
A24: 122 | B24: Customer_122 | C24: ORD-21443 | D24: 45793 | E24: Microwave | F24: Home | G24: 2 | H24: 556.93 | I24: PayPal | J24: Shipped | K24: 1113.86 | L24: 1113.86 | M24: OK
A25: 123 | B25: Customer_123 | C25: ORD-11314 | D25: 45936 | E25: Vacuum | F25: Electronics | G25: 3 | H25: 615.91 | I25: Cash on Delivery | J25: Cancelled | K25: 1847.73 | L25: 1847.73 | M25: OK
A26: 124 | B26: Customer_124 | C26: ORD-46136 | D26: 45808 | E26: Comics | F26: Books | G26: 5 | I26: PayPal | J26: Cancelled | M26: No Data
A27: 125 | B27: Customer_125 | C27: ORD-23202 | D27: 45697 | E27: Comics | F27: Books | G27: 4 | H27: 765.69 | I27: PayPal | J27: Shipped | K27: 3062.76 | L27: 3062.76 | M27: OK
A28: 126 | B28: Customer_126 | C28: ORD-11261 | D28: 45795 | E28: Shoes | F28: Clothing | G28: 4 | H28: 836.8 | I28: Bank Transfer | J28: Cancelled | K28: 3347.2 | L28: 3347.2 | M28: OK
A29: 127 | B29: Customer_127 | C29: ORD-65482 | D29: 45789 | E29: Blender | F29: Home | G29: 5 | H29: 336.02 | I29: Bank Transfer | J29: Returned | K29: 1680.1 | L29: 1680.1 | M29: OK
A30: 128 | B30: Customer_128 | C30: ORD-12270 | D30: 45606 | E30: Lamp | F30: Electronics | G30: 3 | H30: 898.69 | I30: Bank Transfer | J30: Delivered | K30: 2696.07 | L30: 2696.07 | M30: OK
A31: 129 | B31: Customer_129 | C31: ORD-48863 | D31: 45830 | E31: Science | F31: Books | G31: 4 | H31: 736.71 | I31: Bank Transfer | J31: Returned | K31: 2946.84 | L31: 2946.84 | M31: OK
A32: 130 | B32: Customer_130 | C32: ORD-34007 | D32: 45884 | E32: Tennis Racket | F32: Sports | G32: 2 | I32: Bank Transfer | J32: Processing | M32: No Data
A33: 131 | B33: Customer_131 | C33: ORD-91396 | D33: 45819 | E33: Lamp | F33: Home | G33: 5 | H33: 616.63 | I33: PayPal | J33: Shipped | K33: 3083.15 | L33: 3083.15 | M33: OK
A34: 132 | B34: Customer_132 | C34: ORD-40186 | D34: 45749 | E34: Yoga Mat | F34: Electronics | G34: 1 | H34: 266.7 | I34: PayPal | J34: Delivered | K34: 266.7 | L34: 266.7 | M34: OK
A35: 133 | B35: Customer_133 | C35: ORD-68182 | D35: 45631 | E35: Biography | G35: 5 | H35: 343.24 | I35: Credit Card | J35: Shipped | K35: 1716.2 | L35: 1716.2 | M35: OK
A36: 134 | B36: Customer_134 | C36: ORD-16585 | D36: 45934 | E36: T-Shirt | F36: Clothing | G36: -5 | H36: 591.53 | I36: PayPal | J36: Shipped | K36: -2957.65 | L36: -2957.65 | M36: OK
A37: 135 | B37: Customer_135 | C37: ORD-33656 | D37: 45697 | E37: Smartwatch | F37: Electronics | G37: 4 | H37: 446.19 | I37: Cash on Delivery | J37: Cancelled | K37: 1784.76 | L37: 1784.76 | M37: OK
A38: 136 | B38: Customer_136 | C38: ORD-20985 | D38: 45820 | E38: Headphones | G38: 1 | H38: 696.71 | I38: Credit Card | J38: Delivered | K38: 696.71 | L38: 696.71 | M38: OK
A39: 137 | B39: Customer_137 | C39: ORD-91254 | D39: 45711 | E39: Vacuum | F39: Home | G39: 3 | H39: -100 | I39: Cash on Delivery | J39: Delivered | K39: -300 | L39: -300 | M39: OK
A40: 138 | B40: Customer_138 | C40: ORD-34319 | D40: 45878 | E40: Lamp | F40: Home | G40: 1 | H40: 531.06 | I40: PayPal | J40: Processing | K40: 531.06 | L40: 531.06 | M40: OK
A41: 139 | B41: Customer_139 | C41: ORD-38418 | D41: 45697 | E41: Smartphone | F41: Electronics | G41: 2 | H41: 681.38 | I41: Credit Card | J41: Cancelled | K41: 1362.76 | L41: 1362.76 | M41: OK
A42: 140 | B42: Customer_140 | C42: ORD-67096 | D42: 45714 | E42: Fiction | F42: Books | G42: 4 | H42: 588.98 | I42: Credit Card | J42: Returned | K42: 2355.92 | L42: 2355.92 | M42: OK
A43: 141 | B43: Customer_141 | C43: ORD-45059 | D43: 45701 | E43: Fiction | F43: Books | G43: 3 | H43: 546.04 | I43: Cash on Delivery | J43: Returned | K43: 1638.12 | L43: 1638.12 | M43: OK
A44: 142 | B44: Customer_142 | C44: ORD-69018 | D44: 45960 | E44: Shoes | F44: Clothing | G44: 5 | H44: 645.26 | I44: Credit Card | J44: Shipped | K44: 3226.3 | L44: 3226.3 | M44: OK
A45: 143 | B45: Customer_143 | C45: ORD-14329 | D45: 45849 | E45: T-Shirt | F45: Clothing | G45: 5 | H45: 826.77 | I45: Bank Transfer | J45: Cancelled | K45: 4133.85 | L45: 4133.85 | M45: OK
A46: 144 | B46: Customer_144 | C46: ORD-89452 | D46: 45684 | E46: Football | F46: Sports | G46: 5 | H46: 849.07 | I46: Bank Transfer | J46: Processing | K46: 4245.35 | L46: 4245.35 | M46: OK
A47: 145 | B47: Customer_145 | C47: ORD-75314 | D47: 45047 | E47: Laptop | F47: Electronics | G47: 2 | H47: 860.99 | I47: Bank Transfer | J47: Returned | K47: 1721.98 | L47: 1721.98 | M47: OK
A48: 146 | B48: Customer_146 | C48: ORD-32755 | D48: 45847 | E48: Basketball | F48: Electronics | G48: 2 | H48: 705.42 | I48: Bank Transfer | J48: Processing | K48: 1410.84 | L48: 1410.84 | M48: OK
A49: 147 | B49: Customer_147 | C49: ORD-80707 | D49: 45778 | E49: Jacket | F49: Clothing | G49: 4 | H49: 596.15 | I49: Cash on Delivery | J49: Shipped | K49: 2384.6 | L49: 2384.6 | M49: OK
A50: 148 | B50: Customer_148 | C50: ORD-38423 | D50: 45729 | E50: Tennis Racket | F50: Sports | G50: 1 | H50: 660.98 | I50: Cash on Delivery | J50: Returned | K50: 660.98 | L50: 660.98 | M50: OK
... A57: 155 | B57: Customer_155 | C57: ORD-20182 | D57: 45778 | E57: Shoes | F57: Clothing | G57: 1 | H57: 40.95 | I57: PayPal | J57: Returned | K57: 40.95 | L57: 40.95 | M57: OK
A58: 156 | B58: Customer_156 | C58: ORD-34679 | D58: 45624 | E58: Jeans | F58: Clothing | G58: 2 | I58: Bank Transfer | J58: Shipped | M58: No Data
A59: 157 | B59: Customer_157 | C59: ORD-34407 | D59: 45967 | E59: Jacket | F59: Clothing | G59: 4 | H59: 275.1 | I59: Bank Transfer | J59: Processing | K59: 1100.4 | L59: 1100.4 | M59: OK
A60: 158 | B60: Customer_158 | C60: ORD-35817 | D60: 45752 | E60: Smartwatch | F60: Electronics | G60: 1 | H60: 933.58 | I60: Cash on Delivery | J60: Shipped | K60: 933.58 | L60: 933.58 | M60: OK
A61: 159 | B61: Customer_159 | C61: ORD-98162 | D61: 45866 | E61: Microwave | F61: Home | G61: 3 | H61: 163.16 | I61: PayPal | J61: Shipped | K61: 489.48 | L61: 489.48 | M61: OK
A62: 160 | B62: Customer_160 | C62: ORD-96037 | D62: 45660 | E62: Science | F62: Books | G62: 5 | H62: 242.52 | I62: Cash on Delivery | J62: Returned | K62: 1212.6 | L62: 1212.6 | M62: OK
A63: 161 | B63: Customer_161 | C63: ORD-27653 | D63: 45641 | E63: Science | F63: Books | G63: 4 | H63: 209.32 | I63: Bank Transfer | J63: Shipped | K63: 837.28 | L63: 837.28 | M63: OK
A64: 162 | B64: Customer_162 | C64: ORD-27743 | D64: 45796 | E64: Blender | F64: Home | G64: 2 | H64: 155.76 | I64: Credit Card | J64: Returned | K64: 311.52 | L64: 311.52 | M64: OK
A65: 163 | B65: Customer_163 | C65: ORD-24378 | D65: 44931 | E65: Smartwatch | F65: Electronics | G65: 3 | H65: 235.26 | I65: Cash on Delivery | J65: Shipped | K65: 705.78 | L65: 705.78 | M65: OK
A66: 164 | B66: Customer_164 | C66: ORD-23010 | D66: 45697 | E66: Tennis Racket | F66: Sports | H66: 587.64 | I66: Credit Card | J66: Returned | M66: No Data
A67: 165 | B67: Customer_165 | C67: ORD-55695 | D67: 45604 | E67: Shoes | F67: Clothing | G67: 2 | H67: 443.13 | I67: Credit Card | J67: Delivered | K67: 886.26 | L67: 886.26 | M67: OK
A68: 166 | B68: Customer_166 | C68: ORD-97756 | D68: 45841 | E68: T-Shirt | F68: Electronics | G68: 2 | H68: 569.38 | I68: Cash on Delivery | J68: Shipped | K68: 1138.76 | L68: 1138.76 | M68: OK
A69: 167 | B69: Customer_167 | C69: ORD-30329 | D69: 45876 | E69: Basketball | F69: Sports | H69: 593.93 | I69: Cash on Delivery | J69: Processing | M69: No Data
A70: 168 | B70: Customer_168 | C70: ORD-53430 | D70: 45965 | E70: Biography | F70: Books | G70: 2 | H70: 141.49 | I70: PayPal | J70: Cancelled | K70: 282.98 | L70: 282.98 | M70: OK
A71: 169 | B71: Customer_169 | C71: ORD-75539 | D71: 45881 | E71: Basketball | F71: Sports | G71: 1 | H71: 582.13 | I71: Credit Card | J71: Returned | K71: 582.13 | L71: 582.13 | M71: OK
A72: 170 | B72: Customer_170 | C72: ORD-21530 | D72: 45933 | E72: Jeans | F72: Clothing | G72: 5 | H72: 741.63 | I72: Bank Transfer | J72: Processing | K72: 3708.15 | L72: 3708.15 | M72: OK
A73: 171 | B73: Customer_171 | C73: ORD-99790 | D73: 45632 | E73: Shoes | F73: Clothing | G73: 3 | H73: 688.68 | I73: PayPal | J73: Processing | K73: 2066.04 | L73: 2066.04 | M73: OK
A74: 172 | B74: Customer_172 | C74: ORD-48008 | D74: 45614 | E74: Comics | F74: Books | G74: 2 | H74: 942.76 | I74: Bank Transfer | J74: Returned | K74: 1885.52 | L74: 1885.52 | M74: OK
A75: 173 | B75: Customer_173 | C75: ORD-42171 | D75: 45941 | E75: Lamp | F75: Home | G75: 5 | H75: 351.89 | I75: Credit Card | J75: Shipped | K75: 1759.45 | L75: 1759.45 | M75: OK
A76: 174 | B76: Customer_174 | C76: ORD-16766 | D76: 45920 | E76: Microwave | F76: Electronics | G76: 4 | H76: 187.48 | I76: Credit Card | J76: Returned | K76: 749.92 | L76: 749.92 | M76: OK
A77: 175 | B77: Customer_175 | C77: ORD-56651 | D77: 45712 | E77: Headphones | F77: Electronics | G77: 1 | H77: 111.36 | I77: Credit Card | J77: Processing | K77: 111.36 | L77: 111.36 | M77: OK
A78: 176 | B78: Customer_176 | C78: ORD-95794 | D78: 45860 | E78: Comics | F78: Books | G78: 5 | H78: 530.52 | I78: Cash on Delivery | J78: Shipped | K78: 2652.6 | L78: 2652.6 | M78: OK
A79: 177 | B79: Customer_177 | C79: ORD-64136 | D79: 45866 | E79: Laptop | F79: Electronics | G79: 1 | H79: 69.48 | I79: Bank Transfer | J79: Returned | K79: 69.48 | L79: 69.48 | M79: OK
A80: 178 | B80: Customer_178 | C80: ORD-89906 | D80: 45918 | E80: Tennis Racket | F80: Sports | G80: 3 | H80: 472.14 | I80: PayPal | J80: Returned | K80: 1416.42 | L80: 1416.42 | M80: OK
A81: 179 | B81: Customer_179 | C81: ORD-99328 | D81: 45903 | E81: Yoga Mat | F81: Sports | G81: 3 | H81: 868.67 | I81: PayPal | J81: Delivered | K81: 2606.01 | L81: 2606.01 | M81: OK
A82: 180 | B82: Customer_180 | C82: ORD-86629 | D82: 45742 | E82: Laptop | G82: 2 | H82: 418.38 | I82: Credit Card | J82: Processing | K82: 836.76 | L82: 836.76 | M82: OK
A83: 181 | B83: Customer_181 | C83: ORD-54481 | D83: 45655 | E83: Smartphone | G83: 1 | H83: 266.48 | I83: Cash on Delivery | J83: Cancelled | K83: 266.48 | L83: 266.48 | M83: OK
A84: 182 | B84: Customer_182 | C84: ORD-79672 | D84: 45872 | E84: Shoes | G84: 4 | H84: 538.35 | I84: PayPal | J84: Processing | K84: 2153.4 | L84: 2153.4 | M84: OK
A85: 183 | B85: Customer_183 | C85: ORD-20916 | D85: 45726 | E85: Shoes | F85: Clothing | G85: 5 | I85: Cash on Delivery | J85: Returned | M85: No Data
A86: 184 | B86: Customer_184 | C86: ORD-67799 | D86: 45703 | E86: Jeans | G86: 4 | H86: 101.19 | I86: Bank Transfer | J86: Processing | K86: 404.76 | L86: 404.76 | M86: OK
A87: 185 | B87: Customer_185 | C87: ORD-57123 | D87: 45883 | E87: Football | F87: Sports | G87: 2 | H87: 730.92 | I87: Cash on Delivery | J87: Cancelled | K87: 1023.288 | L87: 1461.84 | M87: Mismatch
A88: 186 | B88: Customer_186 | C88: ORD-90569 | D88: 45936 | E88: Laptop | F88: Electronics | G88: 1 | H88: 365.34 | I88: Bank Transfer | J88: Delivered | K88: 365.34 | L88: 365.34 | M88: OK
A89: 187 | B89: Customer_187 | C89: ORD-41292 | D89: 45615 | E89: Smartphone | F89: Electronics | G89: 3 | H89: 882.96 | I89: Bank Transfer | J89: Returned | K89: 2648.88 | L89: 2648.88 | M89: OK
A90: 188 | B90: Customer_188 | C90: ORD-58590 | D90: 45615 | E90: Microwave | F90: Home | G90: 5 | H90: 504.05 | I90: Cash on Delivery | J90: Shipped | K90: 2520.25 | L90: 2520.25 | M90: OK
A91: 189 | B91: Customer_189 | C91: ORD-30627 | D91: 45883 | E91: Lamp | F91: Home | G91: 1 | H91: 814.68 | I91: Cash on Delivery | J91: Returned | K91: 814.68 | L91: 814.68 | M91: OK
A92: 190 | B92: Customer_190 | C92: ORD-38469 | D92: 45837 | E92: Vacuum | F92: Home | G92: 1 | H92: 920.37 | I92: Bank Transfer | J92: Processing | K92: 920.37 | L92: 920.37 | M92: OK
A93: 191 | B93: Customer_191 | C93: ORD-41810 | D93: 45856 | E93: Fiction | F93: Books | G93: 2 | H93: 881.02 | I93: Cash on Delivery | J93: Returned | K93: 1762.04 | L93: 1762.04 | M93: OK
A94: 192 | B94: Customer_192 | C94: ORD-35144 | E94: Jacket | F94: Clothing | H94: 203.63 | I94: Credit Card | J94: Returned | M94: No Data
A95: 193 | B95: Customer_193 | C95: ORD-42475 | D95: 45814 | E95: Basketball | H95: 522.02 | I95: PayPal | J95: Shipped | M95: No Data
A96: 194 | B96: Customer_194 | C96: ORD-69764 | D96: 45698 | E96: Lamp | F96: Home | G96: 5 | H96: 944.54 | I96: Cash on Delivery | J96: Returned | K96: 4722.7 | L96: 4722.7 | M96: OK
A97: 195 | B97: Customer_195 | C97: ORD-82876 | D97: 45827 | E97: Biography | F97: Books | G97: 5 | H97: 817.46 | I97: Cash on Delivery | J97: Returned | K97: 4087.3 | L97: 4087.3 | M97: OK
A98: 196 | B98: Customer_196 | C98: ORD-78384 | D98: 45649 | E98: Vacuum | F98: Home | I98: PayPal | J98: Delivered | M98: No Data
A99: 197 | B99: Customer_197 | C99: ORD-79139 | D99: 45831 | E99: Blender | F99: Home | G99: 1 | H99: 160.16 | I99: PayPal | J99: Cancelled | K99: 160.16 | L99: 160.16 | M99: OK
A100: 198 | B100: Customer_198 | C100: ORD-14608 | D100: 45865 | E100: Vacuum | G100: 2 | H100: 497.01 | I100: Cash on Delivery | J100: Shipped | K100: 994.02 | L100: 994.02 | M100: OK
A101: 199 | B101: Customer_199 | C101: ORD-82922 | D101: 45679 | E101: Blender | F101: Home | G101: 5 | H101: 372.28 | I101: Credit Card | J101: Shipped | K101: 1861.4 | L101: 1861.4 | M101: OK

Sheet 04_Clean_Final
A1: ID | B1: Customer_Name | C1: Order_ID | D1: Order_Date | E1: Product | F1: Category | G1: Quantity | H1: Price | I1: Payment_Method | J1: Status | K1: Total | L1: Total_Check
A2: 100 | B2: Customer_100 | C2: ORD-41285 | D2: 45618 | E2: Blender | F2: Home | G2: 3 | H2: 38 | I2: Cash on Delivery | J2: Shipped | K2: 114 | L2: OK
A3: 101 | B3: Customer_101 | C3: ORD-35783 | D3: 45843 | E3: Smartphone | F3: Electronics | G3: 2 | I3: PayPal | J3: Processing | L3: No Data
A4: 102 | B4: Customer_102 | C4: ORD-84355 | D4: 45649 | E4: Tennis Racket | F4: Sports | G4: 1 | H4: 389.05 | I4: PayPal | J4: Delivered | K4: 389.05 | L4: OK
A5: 103 | B5: Customer_103 | C5: ORD-57811 | D5: 45735 | E5: Science | F5: Books | G5: 5 | H5: 233.92 | I5: PayPal | J5: Processing | K5: 1169.6 | L5: OK
A6: 104 | B6: Customer_104 | C6: ORD-93614 | D6: 45950 | E6: Biography | F6: Books | G6: 1 | H6: 552.51 | I6: Cash on Delivery | J6: Processing | K6: 552.51 | L6: OK
A7: 105 | B7: Customer_105 | C7: ORD-22442 | D7: 45616 | E7: Tennis Racket | F7: Sports | G7: 3 | H7: 122.06 | I7: Cash on Delivery | J7: Cancelled | K7: 366.18 | L7: OK
A8: 106 | B8: Customer_106 | C8: ORD-25885 | D8: 45690 | E8: Blender | F8: Home | H8: 978.63 | I8: Bank Transfer | J8: Processing | L8: No Data
A9: 107 | B9: Customer_107 | C9: ORD-89122 | D9: 45660 | E9: Biography | F9: Books | G9: 5 | H9: 587.68 | I9: PayPal | J9: Returned | K9: 2938.4 | L9: OK
A10: 108 | B10: Customer_108 | C10: ORD-64400 | D10: 45953 | E10: Science | F10: Books | G10: 1 | H10: 600.29 | I10: Cash on Delivery | J10: Processing | K10: 600.29 | L10: OK
A11: 109 | B11: Customer_109 | C11: ORD-18512 | D11: 45780 | E11: Tennis Racket | F11: Sports | G11: 5 | H11: 168.34 | I11: Credit Card | J11: Shipped | K11: 841.7 | L11: OK
A12: 110 | B12: Customer_110 | C12: ORD-61020 | D12: 45926 | E12: Basketball | F12: Sports | G12: 5 | I12: Cash on Delivery | J12: Cancelled | L12: No Data
A13: 111 | B13: Customer_111 | C13: ORD-72349 | D13: 45952 | E13: Comics | F13: Books | G13: 2 | H13: 865.77 | I13: Credit Card | J13: Returned | K13: 1731.54 | L13: OK
A14: 112 | B14: Customer_112 | C14: ORD-80867 | D14: 45718 | E14: Shoes | F14: Clothing | G14: 4 | H14: 752.13 | I14: Bank Transfer | J14: Delivered | K14: 3008.52 | L14: OK
A15: 113 | B15: Customer_113 | C15: ORD-23994 | D15: 45862 | E15: Fiction | F15: Books | G15: 1 | H15: 411.81 | I15: Credit Card | J15: Processing | K15: 411.81 | L15: OK
A16: 114 | B16: Customer_114 | C16: ORD-77417 | D16: 44931 | E16: Smartphone | F16: Electronics | G16: 2 | H16: 413.13 | I16: Cash on Delivery | J16: Shipped | K16: 826.26 | L16: OK
A17: 115 | B17: Customer_115 | C17: ORD-72778 | D17: 45667 | E17: Fiction | F17: Books | G17: 2 | H17: 796.84 | I17: Cash on Delivery | J17: Returned | K17: 1115.576 | L17: Mismatch
A18: 116 | B18: Customer_116 | C18: ORD-63660 | D18: 45960 | E18: Microwave | F18: Home | G18: 4 | I18: Cash on Delivery | J18: Processing | L18: No Data
A19: 117 | B19: Customer_117 | C19: ORD-72751 | D19: 45700 | E19: Blender | F19: Electronics | G19: -2 | H19: 10000 | I19: Cash on Delivery | J19: Processing | K19: -20000 | L19: OK
A20: 118 | B20: Customer_118 | C20: ORD-96061 | D20: 45808 | E20: Science | F20: Books | G20: 5 | H20: 247.82 | I20: PayPal | J20: Processing | K20: 1239.1 | L20: OK
A21: 119 | B21: Customer_119 | C21: ORD-76016 | D21: 45645 | E21: Basketball | F21: Sports | G21: 4 | H21: 438.19 | I21: Cash on Delivery | J21: Processing | K21: 1752.76 | L21: OK
A22: 120 | B22: Customer_120 | C22: ORD-14659 | D22: 45821 | E22: Yoga Mat | F22: Electronics | G22: 5 | H22: 300 | I22: Credit Card | J22: Cancelled | K22: 1500 | L22: Recalculated
A23: 121 | B23: Customer_121 | C23: ORD-80067 | D23: 45941 | E23: Basketball | F23: Sports | G23: 4 | H23: 523.01 | I23: Credit Card | J23: Delivered | K23: 2092.04 | L23: OK
A24: 122 | B24: Customer_122 | C24: ORD-21443 | D24: 45793 | E24: Microwave | F24: Home | G24: 2 | H24: 556.93 | I24: PayPal | J24: Shipped | K24: 1113.86 | L24: OK
A25: 123 | B25: Customer_123 | C25: ORD-11314 | D25: 45936 | E25: Vacuum | F25: Electronics | G25: 3 | H25: 615.91 | I25: Cash on Delivery | J25: Cancelled | K25: 1847.73 | L25: OK
A26: 124 | B26: Customer_124 | C26: ORD-46136 | D26: 45808 | E26: Comics | F26: Books | G26: 5 | I26: PayPal | J26: Cancelled | L26: No Data
A27: 125 | B27: Customer_125 | C27: ORD-23202 | D27: 45697 | E27: Comics | F27: Books | G27: 4 | H27: 765.69 | I27: PayPal | J27: Shipped | K27: 3062.76 | L27: OK
A28: 126 | B28: Customer_126 | C28: ORD-11261 | D28: 45795 | E28: Shoes | F28: Clothing | G28: 4 | H28: 836.8 | I28: Bank Transfer | J28: Cancelled | K28: 3347.2 | L28: OK
A29: 127 | B29: Customer_127 | C29: ORD-65482 | D29: 45789 | E29: Blender | F29: Home | G29: 5 | H29: 336.02 | I29: Bank Transfer | J29: Returned | K29: 1680.1 | L29: OK
A30: 128 | B30: Customer_128 | C30: ORD-12270 | D30: 45606 | E30: Lamp | F30: Electronics | G30: 3 | H30: 898.69 | I30: Bank Transfer | J30: Delivered | K30: 2696.07 | L30: OK
A31: 129 | B31: Customer_129 | C31: ORD-48863 | D31: 45830 | E31: Science | F31: Books | G31: 4 | H31: 736.71 | I31: Bank Transfer | J31: Returned | K31: 2946.84 | L31: OK
A32: 130 | B32: Customer_130 | C32: ORD-34007 | D32: 45884 | E32: Tennis Racket | F32: Sports | G32: 2 | I32: Bank Transfer | J32: Processing | L32: No Data
A33: 131 | B33: Customer_131 | C33: ORD-91396 | D33: 45819 | E33: Lamp | F33: Home | G33: 5 | H33: 616.63 | I33: PayPal | J33: Shipped | K33: 3083.15 | L33: OK
A34: 132 | B34: Customer_132 | C34: ORD-40186 | D34: 45749 | E34: Yoga Mat | F34: Electronics | G34: 1 | H34: 266.7 | I34: PayPal | J34: Delivered | K34: 266.7 | L34: OK
A35: 133 | B35: Customer_133 | C35: ORD-68182 | D35: 45631 | E35: Biography | G35: 5 | H35: 343.24 | I35: Credit Card | J35: Shipped | K35: 1716.2 | L35: OK
A36: 134 | B36: Customer_134 | C36: ORD-16585 | D36: 45934 | E36: T-shirt | F36: Clothing | G36: -5 | H36: 591.53 | I36: PayPal | J36: Shipped | K36: -2957.65 | L36: OK
A37: 135 | B37: Customer_135 | C37: ORD-33656 | D37: 45697 | E37: Smartwatch | F37: Electronics | G37: 4 | H37: 446.19 | I37: Cash on Delivery | J37: Cancelled | K37: 1784.76 | L37: OK
A38: 136 | B38: Customer_136 | C38: ORD-20985 | D38: 45820 | E38: Headphones | G38: 1 | H38: 696.71 | I38: Credit Card | J38: Delivered | K38: 696.71 | L38: OK
A39: 137 | B39: Customer_137 | C39: ORD-91254 | D39: 45711 | E39: Vacuum | F39: Home | G39: 3 | H39: -100 | I39: Cash on Delivery | J39: Delivered | K39: -300 | L39: OK
A40: 138 | B40: Customer_138 | C40: ORD-34319 | D40: 45878 | E40: Lamp | F40: Home | G40: 1 | H40: 531.06 | I40: PayPal | J40: Processing | K40: 531.06 | L40: OK
A41: 139 | B41: Customer_139 | C41: ORD-38418 | D41: 45697 | E41: Smartphone | F41: Electronics | G41: 2 | H41: 681.38 | I41: Credit Card | J41: Cancelled | K41: 1362.76 | L41: OK
A42: 140 | B42: Customer_140 | C42: ORD-67096 | D42: 45714 | E42: Fiction | F42: Books | G42: 4 | H42: 588.98 | I42: Credit Card | J42: Returned | K42: 2355.92 | L42: OK
A43: 141 | B43: Customer_141 | C43: ORD-45059 | D43: 45701 | E43: Fiction | F43: Books | G43: 3 | H43: 546.04 | I43: Cash on Delivery | J43: Returned | K43: 1638.12 | L43: OK
A44: 142 | B44: Customer_142 | C44: ORD-69018 | D44: 45960 | E44: Shoes | F44: Clothing | G44: 5 | H44: 645.26 | I44: Credit Card | J44: Shipped | K44: 3226.3 | L44: OK
A45: 143 | B45: Customer_143 | C45: ORD-14329 | D45: 45849 | E45: T-shirt | F45: Clothing | G45: 5 | H45: 826.77 | I45: Bank Transfer | J45: Cancelled | K45: 4133.85 | L45: OK
A46: 144 | B46: Customer_144 | C46: ORD-89452 | D46: 45684 | E46: Football | F46: Sports | G46: 5 | H46: 849.07 | I46: Bank Transfer | J46: Processing | K46: 4245.35 | L46: OK
A47: 145 | B47: Customer_145 | C47: ORD-75314 | D47: 45047 | E47: Laptop | F47: Electronics | G47: 2 | H47: 860.99 | I47: Bank Transfer | J47: Returned | K47: 1721.98 | L47: OK
A48: 146 | B48: Customer_146 | C48: ORD-32755 | D48: 45847 | E48: Basketball | F48: Electronics | G48: 2 | H48: 705.42 | I48: Bank Transfer | J48: Processing | K48: 1410.84 | L48: OK
A49: 147 | B49: Customer_147 | C49: ORD-80707 | D49: 45778 | E49: Jacket | F49: Clothing | G49: 4 | H49: 596.15 | I49: Cash on Delivery | J49: Shipped | K49: 2384.6 | L49: OK
A50: 148 | B50: Customer_148 | C50: ORD-38423 | D50: 45729 | E50: Tennis Racket | F50: Sports | G50: 1 | H50: 660.98 | I50: Cash on Delivery | J50: Returned | K50: 660.98 | L50: OK
... A57: 155 | B57: Customer_155 | C57: ORD-20182 | D57: 45778 | E57: Shoes | F57: Clothing | G57: 1 | H57: 40.95 | I57: PayPal | J57: Returned | K57: 40.95 | L57: OK
A58: 156 | B58: Customer_156 | C58: ORD-34679 | D58: 45624 | E58: Jeans | F58: Clothing | G58: 2 | I58: Bank Transfer | J58: Shipped | L58: No Data
A59: 157 | B59: Customer_157 | C59: ORD-34407 | D59: 45967 | E59: Jacket | F59: Clothing | G59: 4 | H59: 275.1 | I59: Bank Transfer | J59: Processing | K59: 1100.4 | L59: OK
A60: 158 | B60: Customer_158 | C60: ORD-35817 | D60: 45752 | E60: Smartwatch | F60: Electronics | G60: 1 | H60: 933.58 | I60: Cash on Delivery | J60: Shipped | K60: 933.58 | L60: OK
A61: 159 | B61: Customer_159 | C61: ORD-98162 | D61: 45866 | E61: Microwave | F61: Home | G61: 3 | H61: 163.16 | I61: PayPal | J61: Shipped | K61: 489.48 | L61: OK
A62: 160 | B62: Customer_160 | C62: ORD-96037 | D62: 45660 | E62: Science | F62: Books | G62: 5 | H62: 242.52 | I62: Cash on Delivery | J62: Returned | K62: 1212.6 | L62: OK
A63: 161 | B63: Customer_161 | C63: ORD-27653 | D63: 45641 | E63: Science | F63: Books | G63: 4 | H63: 209.32 | I63: Bank Transfer | J63: Shipped | K63: 837.28 | L63: OK
A64: 162 | B64: Customer_162 | C64: ORD-27743 | D64: 45796 | E64: Blender | F64: Home | G64: 2 | H64: 155.76 | I64: Credit Card | J64: Returned | K64: 311.52 | L64: OK
A65: 163 | B65: Customer_163 | C65: ORD-24378 | D65: 44931 | E65: Smartwatch | F65: Electronics | G65: 3 | H65: 235.26 | I65: Cash on Delivery | J65: Shipped | K65: 705.78 | L65: OK
A66: 164 | B66: Customer_164 | C66: ORD-23010 | D66: 45697 | E66: Tennis Racket | F66: Sports | H66: 587.64 | I66: Credit Card | J66: Returned | L66: No Data
A67: 165 | B67: Customer_165 | C67: ORD-55695 | D67: 45604 | E67: Shoes | F67: Clothing | G67: 2 | H67: 443.13 | I67: Credit Card | J67: Delivered | K67: 886.26 | L67: OK
A68: 166 | B68: Customer_166 | C68: ORD-97756 | D68: 45841 | E68: T-shirt | F68: Electronics | G68: 2 | H68: 569.38 | I68: Cash on Delivery | J68: Shipped | K68: 1138.76 | L68: OK
A69: 167 | B69: Customer_167 | C69: ORD-30329 | D69: 45876 | E69: Basketball | F69: Sports | H69: 593.93 | I69: Cash on Delivery | J69: Processing | L69: No Data
A70: 168 | B70: Customer_168 | C70: ORD-53430 | D70: 45965 | E70: Biography | F70: Books | G70: 2 | H70: 141.49 | I70: PayPal | J70: Cancelled | K70: 282.98 | L70: OK
A71: 169 | B71: Customer_169 | C71: ORD-75539 | D71: 45881 | E71: Basketball | F71: Sports | G71: 1 | H71: 582.13 | I71: Credit Card | J71: Returned | K71: 582.13 | L71: OK
A72: 170 | B72: Customer_170 | C72: ORD-21530 | D72: 45933 | E72: Jeans | F72: Clothing | G72: 5 | H72: 741.63 | I72: Bank Transfer | J72: Processing | K72: 3708.15 | L72: OK
A73: 171 | B73: Customer_171 | C73: ORD-99790 | D73: 45632 | E73: Shoes | F73: Clothing | G73: 3 | H73: 688.68 | I73: PayPal | J73: Processing | K73: 2066.04 | L73: OK
A74: 172 | B74: Customer_172 | C74: ORD-48008 | D74: 45614 | E74: Comics | F74: Books | G74: 2 | H74: 942.76 | I74: Bank Transfer | J74: Returned | K74: 1885.52 | L74: OK
A75: 173 | B75: Customer_173 | C75: ORD-42171 | D75: 45941 | E75: Lamp | F75: Home | G75: 5 | H75: 351.89 | I75: Credit Card | J75: Shipped | K75: 1759.45 | L75: OK
A76: 174 | B76: Customer_174 | C76: ORD-16766 | D76: 45920 | E76: Microwave | F76: Electronics | G76: 4 | H76: 187.48 | I76: Credit Card | J76: Returned | K76: 749.92 | L76: OK
A77: 175 | B77: Customer_175 | C77: ORD-56651 | D77: 45712 | E77: Headphones | F77: Electronics | G77: 1 | H77: 111.36 | I77: Credit Card | J77: Processing | K77: 111.36 | L77: OK
A78: 176 | B78: Customer_176 | C78: ORD-95794 | D78: 45860 | E78: Comics | F78: Books | G78: 5 | H78: 530.52 | I78: Cash on Delivery | J78: Shipped | K78: 2652.6 | L78: OK
A79: 177 | B79: Customer_177 | C79: ORD-64136 | D79: 45866 | E79: Laptop | F79: Electronics | G79: 1 | H79: 69.48 | I79: Bank Transfer | J79: Returned | K79: 69.48 | L79: OK
A80: 178 | B80: Customer_178 | C80: ORD-89906 | D80: 45918 | E80: Tennis Racket | F80: Sports | G80: 3 | H80: 472.14 | I80: PayPal | J80: Returned | K80: 1416.42 | L80: OK
A81: 179 | B81: Customer_179 | C81: ORD-99328 | D81: 45903 | E81: Yoga Mat | F81: Sports | G81: 3 | H81: 868.67 | I81: PayPal | J81: Delivered | K81: 2606.01 | L81: OK
A82: 180 | B82: Customer_180 | C82: ORD-86629 | D82: 45742 | E82: Laptop | G82: 2 | H82: 418.38 | I82: Credit Card | J82: Processing | K82: 836.76 | L82: OK
A83: 181 | B83: Customer_181 | C83: ORD-54481 | D83: 45655 | E83: Smartphone | G83: 1 | H83: 266.48 | I83: Cash on Delivery | J83: Cancelled | K83: 266.48 | L83: OK
A84: 182 | B84: Customer_182 | C84: ORD-79672 | D84: 45872 | E84: Shoes | G84: 4 | H84: 538.35 | I84: PayPal | J84: Processing | K84: 2153.4 | L84: OK
A85: 183 | B85: Customer_183 | C85: ORD-20916 | D85: 45726 | E85: Shoes | F85: Clothing | G85: 5 | I85: Cash on Delivery | J85: Returned | L85: No Data
A86: 184 | B86: Customer_184 | C86: ORD-67799 | D86: 45703 | E86: Jeans | G86: 4 | H86: 101.19 | I86: Bank Transfer | J86: Processing | K86: 404.76 | L86: OK
A87: 185 | B87: Customer_185 | C87: ORD-57123 | D87: 45883 | E87: Football | F87: Sports | G87: 2 | H87: 730.92 | I87: Cash on Delivery | J87: Cancelled | K87: 1023.288 | L87: Mismatch
A88: 186 | B88: Customer_186 | C88: ORD-90569 | D88: 45936 | E88: Laptop | F88: Electronics | G88: 1 | H88: 365.34 | I88: Bank Transfer | J88: Delivered | K88: 365.34 | L88: OK
A89: 187 | B89: Customer_187 | C89: ORD-41292 | D89: 45615 | E89: Smartphone | F89: Electronics | G89: 3 | H89: 882.96 | I89: Bank Transfer | J89: Returned | K89: 2648.88 | L89: OK
A90: 188 | B90: Customer_188 | C90: ORD-58590 | D90: 45615 | E90: Microwave | F90: Home | G90: 5 | H90: 504.05 | I90: Cash on Delivery | J90: Shipped | K90: 2520.25 | L90: OK
A91: 189 | B91: Customer_189 | C91: ORD-30627 | D91: 45883 | E91: Lamp | F91: Home | G91: 1 | H91: 814.68 | I91: Cash on Delivery | J91: Returned | K91: 814.68 | L91: OK
A92: 190 | B92: Customer_190 | C92: ORD-38469 | D92: 45837 | E92: Vacuum | F92: Home | G92: 1 | H92: 920.37 | I92: Bank Transfer | J92: Processing | K92: 920.37 | L92: OK
A93: 191 | B93: Customer_191 | C93: ORD-41810 | D93: 45856 | E93: Fiction | F93: Books | G93: 2 | H93: 881.02 | I93: Cash on Delivery | J93: Returned | K93: 1762.04 | L93: OK
A94: 192 | B94: Customer_192 | C94: ORD-35144 | E94: Jacket | F94: Clothing | H94: 203.63 | I94: Credit Card | J94: Returned | L94: No Data
A95: 193 | B95: Customer_193 | C95: ORD-42475 | D95: 45814 | E95: Basketball | H95: 522.02 | I95: PayPal | J95: Shipped | L95: No Data
A96: 194 | B96: Customer_194 | C96: ORD-69764 | D96: 45698 | E96: Lamp | F96: Home | G96: 5 | H96: 944.54 | I96: Cash on Delivery | J96: Returned | K96: 4722.7 | L96: OK
A97: 195 | B97: Customer_195 | C97: ORD-82876 | D97: 45827 | E97: Biography | F97: Books | G97: 5 | H97: 817.46 | I97: Cash on Delivery | J97: Returned | K97: 4087.3 | L97: OK
A98: 196 | B98: Customer_196 | C98: ORD-78384 | D98: 45649 | E98: Vacuum | F98: Home | I98: PayPal | J98: Delivered | L98: No Data
A99: 197 | B99: Customer_197 | C99: ORD-79139 | D99: 45831 | E99: Blender | F99: Home | G99: 1 | H99: 160.16 | I99: PayPal | J99: Cancelled | K99: 160.16 | L99: OK
A100: 198 | B100: Customer_198 | C100: ORD-14608 | D100: 45865 | E100: Vacuum | G100: 2 | H100: 497.01 | I100: Cash on Delivery | J100: Shipped | K100: 994.02 | L100: OK
A101: 199 | B101: Customer_199 | C101: ORD-82922 | D101: 45679 | E101: Blender | F101: Home | G101: 5 | H101: 372.28 | I101: Credit Card | J101: Shipped | K101: 1861.4 | L101: OK
